Workbook

Sheet Notas_CPerez
A1: Autor: | B1: Camilo Pérez Núñez
A2: Última
A3: Modificación: | B3: 41396
A5: La base de datos principal es la que se encuentra en la hoja "DatosVinculos", la cual contiene series construidas desde 1986q1 hasta 2012q4.
A6: En su mayoría corresponden a datos efectivos, de lo contrario se destaca el contenido de la celda con letra roja, la explicación de los datos construidos se encuentra en las Notas.
A7: La hoja "DatosSinVinculos", corresponde a la base consolidada sin vinculos, el resto de las hojas donde se realizan la mayoria de los empalmes estan ocultas.
A9: Notas:
A10: 1) Gran parte de los datos fueron extraidos de la Web (bcentral.cl) y son de carácter público
A11: 2) Las series del PIB y derivados, y los componentes del gasto, son datos efectivos con al metodología de encadenamiento a partir de 1996q1 en adelante. Hacia atras se empalman en variación anual hasta 1986q1 con las series construidas con metodología a base fijo.
A12: 3) Para construir el Pib Nominal entre 1986q1 y 1989q4 se aplica a los datos anuales de CCNN método de desagregación temporal Chow-Lin utilizando como control el PIB Real.
A13: 4) La Balanza Comercial Nominal, se construye en base a datos publicos a partir de 1996q1 hasta 2012q4, hacia atrás se empalma con una serie construida por desagregación temporal con el método Chow-Lin utilizando de input los datos anuales oficiales de balanza comercial y como variable de control la diferencia entre (X-M).
A14: 5) De la Serie Cuenta Corriente hay datos trimestrales desde 1996q1 hasta 2012q4, hacia atrás se empalma con una serie construida por desagregación temporal con el método Chow-Lin utilizando de input los datos anuales oficiales de cuenta corriente y como variable de control la diferencia entre (X-M).
A15: 6) La serie Meta de IPC es de uso interno, no es pública. La serie IPC Meta 2, corresponde a datos efectivos desde 1991q1 en adelante. Para completar la serie hasta 1986q1 se empalma con filtro hp 1600 a var. a/a del ipc.
A16: 7) Tanto las Series IPE como PIB externo (socios comerciales), por construccción estan desestacionalizadas.
A17: 8) Para las series IPCSAE, IPCSAE Bienes e IPCSAE Servicios hay datos desde 1989q2. Para completar datos hacia atrás se utiliza empalme según variación anual del IPC.
... A26: 17) La serie EMBI Chile 2 se construye con datos efectivos a partir de 1999q2, hacia atrás se utiliza empalme con distintas medidas de spread hasta 1991q1.

Sheet Empleo
A1: VALORES ESTIMADOS
A2: Año | B2: Mes | C2: Fecha | D2: Empleo Total Resto | E2: Empleo Total Resto SA | F2: Horas Resto | G2: Horas Resto SA | H2: Empleo Resto con agro y sin pesca | I2: Empleo Resto con agro y sin pesca SA | J2: Horas Resto con agro | K2: Horas Resto con agro SA | N2: Empleo Total Resto | O2: Empleo Total Resto SA | P2: Horas Resto | Q2: Horas Resto SA
A3: =YEAR(C3) -> 1986 | B3: =MONTH(C3) -> 3 | C3: 31472 | D3: 3034530.7 | E3: 3063628.3 | F3: 44.692947 | G3: 45.124091 | H3: 3729821.9 | I3: 3730405.3 | J3: 45.412215 | K3: 45.437662 | L3: 1 | M3: 1986T1 | N3: 3034530.7 | O3: 3063628.3 | P3: 44.692947 | Q3: 45.124091
A4: =YEAR(C4) -> 1986 | B4: =MONTH(C4) -> 4 | C4: 31503 | D4: 3054712.9 | E4: 3072306.3 | F4: 45.50087 | G4: 45.364405 | H4: 3754231.2 | I4: 3757664.6 | J4: 45.947561 | K4: 45.477736 | L4: 2 | M4: 1986T2 | N4: 3114314.7 | O4: 3090735.2 | P4: 46.034659 | Q4: 45.631548
A5: =YEAR(C5) -> 1986 | B5: =MONTH(C5) -> 5 | C5: 31533 | D5: 3075603.1 | E5: 3069906.8 | F5: 46.095575 | G5: 45.427785 | H5: 3763679.5 | I5: 3765039.9 | J5: 46.051659 | K5: 45.480781 | L5: 3 | M5: 1986T3 | N5: 3161638.8 | O5: 3139220.4 | P5: 44.461316 | Q5: 44.887846
A6: =YEAR(C6) -> 1986 | B6: =MONTH(C6) -> 6 | C6: 31564 | D6: 3114314.7 | E6: 3090735.2 | F6: 46.034659 | G6: 45.631548 | H6: 3783099.6 | I6: 3788164.9 | J6: 45.615946 | K6: 45.359474 | L6: 4 | M6: 1986T4 | N6: 3137479.1 | O6: 3157510.1 | P6: 46.166941 | Q6: 46.003329
A7: =YEAR(C7) -> 1986 | B7: =MONTH(C7) -> 7 | C7: 31594 | D7: 3140530.1 | E7: 3108184.2 | F7: 45.841103 | G7: 45.628952 | H7: 3804019.3 | I7: 3808485.1 | J7: 45.386586 | K7: 45.599525 | L7: 5 | M7: 1987T1 | N7: 3147932.4 | O7: 3178129.6 | P7: 45.003883 | Q7: 45.404197
A8: =YEAR(C8) -> 1986 | B8: =MONTH(C8) -> 8 | C8: 31625 | D8: 3159258.2 | E8: 3129778.8 | F8: 45.573923 | G8: 45.499859 | H8: 3828764.3 | I8: 3833530.9 | J8: 45.303009 | K8: 45.650512 | L8: 6 | M8: 1987T2 | N8: 3220168.6 | O8: 3196015.6 | P8: 45.003129 | Q8: 44.665485
A9: =YEAR(C9) -> 1986 | B9: =MONTH(C9) -> 9 | C9: 31656 | D9: 3161638.8 | E9: 3139220.4 | F9: 44.461316 | G9: 44.887846 | H9: 3843614.3 | I9: 3844816.3 | J9: 44.492809 | K9: 45.291854 | L9: 7 | M9: 1987T3 | N9: 3216438 | O9: 3192960.9 | P9: 44.747245 | Q9: 45.072519
A10: =YEAR(C10) -> 1986 | B10: =MONTH(C10) -> 10 | C10: 31686 | D10: 3160968.6 | E10: 3147900.4 | F10: 44.593515 | G10: 44.950591 | H10: 3857882.5 | I10: 3855261.8 | J10: 44.725339 | K10: 45.110844 | L10: 8 | M10: 1987T4 | N10: 3233010.3 | O10: 3253686.8 | P10: 45.617001 | Q10: 45.395379
A11: =YEAR(C11) -> 1986 | B11: =MONTH(C11) -> 11 | C11: 31717 | D11: 3144117.4 | E11: 3143791.7 | F11: 44.945038 | G11: 44.949466 | H11: 3853486.1 | I11: 3845753.7 | J11: 45.107255 | K11: 45.227414 | L11: 9 | M11: 1988T1 | N11: 3258670 | O11: 3290151.3 | P11: 44.782103 | Q11: 45.187321
A12: =YEAR(C12) -> 1986 | B12: =MONTH(C12) -> 12 | C12: 31747 | D12: 3137479.1 | E12: 3157510.1 | F12: 46.166941 | G12: 46.003329 | H12: 3866772.9 | I12: 3862557.1 | J12: 46.319481 | K12: 45.961702 | L12: 10 | M12: 1988T2 | N12: 3384826.7 | O12: 3360078.5 | P12: 46.200887 | Q12: 45.883847
A13: =YEAR(C13) -> 1987 | B13: =MONTH(C13) -> 1 | C13: 31778 | D13: 3134626.1 | E13: 3161788.7 | F13: 45.452396 | G13: 45.460614 | H13: 3876857.3 | I13: 3872513.6 | J13: 45.856614 | K13: 45.560787 | L13: 11 | M13: 1988T3 | N13: 3459808 | O13: 3433244.9 | P13: 45.789391 | Q13: 46.151104
A14: =YEAR(C14) -> 1987 | B14: =MONTH(C14) -> 2 | C14: 31809 | D14: 3135036.4 | E14: 3167876.5 | F14: 44.700104 | G14: 45.183147 | H14: 3883208.2 | I14: 3881108.1 | J14: 45.408583 | K14: 45.466508 | L14: 12 | M14: 1988T4 | N14: 3465894.4 | O14: 3488547.1 | P14: 46.008931 | Q14: 45.764282
... A110: =YEAR(C110) -> 1995 | B110: =MONTH(C110) -> 2 | C110: 34731 | D110: 4331269.1 | E110: 4369669.4 | F110: 45.415756 | G110: 46.275924 | H110: 5126473.7 | I110: 5126492.6 | J110: 45.613579 | K110: 46.155228 | L110: 108 | M110: 2012T4 | N110: 6582462.5 | O110: 6591955.4 | P110: 39.691614 | Q110: 39.235313
A111: =YEAR(C111) -> 1995 | B111: =MONTH(C111) -> 3 | C111: 34759 | D111: 4325876.3 | E111: 4361411.6 | F111: 45.57587 | G111: 46.004248 | H111: 5116256.6 | I111: 5113559 | J111: 45.824876 | K111: 45.883763 | L111: 109
A112: =YEAR(C112) -> 1995 | B112: =MONTH(C112) -> 4 | C112: 34790 | D112: 4329645.3 | E112: 4356226.3 | F112: 46.1336 | G112: 45.923003 | H112: 5117640.7 | I112: 5119977.8 | J112: 46.129329 | K112: 45.835408 | L112: 110
A113: =YEAR(C113) -> 1995 | B113: =MONTH(C113) -> 5 | C113: 34820 | D113: 4347586.1 | E113: 4343964.2 | F113: 46.696716 | G113: 46.031582 | H113: 5107655 | I113: 5110287.1 | J113: 46.553356 | K113: 45.922749 | L113: 111
A114: =YEAR(C114) -> 1995 | B114: =MONTH(C114) -> 6 | C114: 34851 | D114: 4389321.9 | E114: 4360309.9 | F114: 46.126671 | G114: 45.905324 | H114: 5118143.6 | I114: 5118954.9 | J114: 45.896009 | K114: 45.923755 | L114: 112
A115: =YEAR(C115) -> 1995 | B115: =MONTH(C115) -> 7 | C115: 34881 | D115: 4409244.5 | E115: 4366455.2 | F115: 46.20902 | G115: 45.938948 | H115: 5116046.9 | I115: 5117346.3 | J115: 45.936448 | K115: 45.915571 | L115: 113
A116: =YEAR(C116) -> 1995 | B116: =MONTH(C116) -> 8 | C116: 34912 | D116: 4421123.2 | E116: 4379520.6 | F116: 46.094094 | G116: 45.800574 | H116: 5126029.8 | I116: 5126681 | J116: 45.805276 | K116: 45.705116 | L116: 114
A117: =YEAR(C117) -> 1995 | B117: =MONTH(C117) -> 9 | C117: 34943 | D117: 4428537.9 | E117: 4393875 | F117: 45.570321 | G117: 45.638098 | H117: 5140995.7 | I117: 5143769.3 | J117: 45.305311 | K117: 45.532044 | L117: 115
A118: =YEAR(C118) -> 1995 | B118: =MONTH(C118) -> 10 | C118: 34973 | D118: 4414623.4 | E118: 4400122.1 | F118: 45.477524 | G118: 45.608434 | H118: 5135425.6 | I118: 5137333.7 | J118: 45.315005 | K118: 45.538904 | L118: 116
A119: =YEAR(C119) -> 1995 | B119: =MONTH(C119) -> 11 | C119: 35004 | D119: 4420418.3 | E119: 4429066.6 | F119: 45.47776 | G119: 45.451231 | H119: 5169144.1 | I119: 5168159.8 | J119: 45.378361 | K119: 45.423161 | L119: 117
A120: =YEAR(C120) -> 1995 | B120: =MONTH(C120) -> 12 | C120: 35034 | D120: 4366314.1 | E120: 4388337.1 | F120: 45.845429 | G120: 45.647613 | H120: 5144227.5 | I120: 5141919.8 | J120: 45.835441 | K120: 45.584959 | L120: 118
A121: =YEAR(C121) -> 1996 | B121: =MONTH(C121) -> 1 | C121: 35065 | D121: 4358650.6 | E121: 4392781.7 | F121: 44.828936 | G121: 45.199521 | H121: 5160197 | I121: 5156144.1 | J121: 45.078935 | K121: 45.345498 | L121: 119
A122: =YEAR(C122) -> 1996 | B122: =MONTH(C122) -> 2 | C122: 35096 | D122: 4356864.7 | E122: 4395540 | F122: 45.092667 | G122: 46.024411 | H122: 5149954.3 | I122: 5144547.8 | J122: 45.403351 | K122: 45.874353 | L122: 120
... A324: =YEAR(C324) -> 2012 | B324: =MONTH(C324) -> 12 | C324: 41244 | D324: 6582462.5 | E324: 6591955.4 | F324: 39.691614 | G324: 39.235313 | H324: 7327746.4 | I324: 7307347 | J324: 39.715302 | K324: 39.232081 | L324: 322

Sheet IPCSAE
A3: Fecha Inicio | B3: 32599 | H3: Fecha Inicio | I3: 32599
A4: Fecha Termino | B4: =EOMONTH(NOW(),-1) -> 43708 | H4: Fecha Termino | I4: 42004
A5: Frecuencia | B5: Q | H5: Frecuencia | I5: Q
A6: Indice de Precios al Consumidor | H6: Indice de Precios al Consumidor
A7: Series Originales | H7: Factores Estacionales
A8: Empalmadas, 2009=100 | H8: Empalmadas, 2009=100
B10: Fecha | C10: IPC | D10: IPCSAE | E10: IPCSAE bienes | F10: IPCSAE servicios | G10: IPCX1 | I10: Fecha | J10: IPC_FE | K10: IPCSAE_FE | L10: IPCSAE bienes_FE | M10: IPCSAE servicios_FE | N10: IPCX1_FE | P10: IPC SA | Q10: IPCSAE SA | R10: IPCSAE bienes SA | S10: IPCSAE servicios SA | T10: IPCX1 SA
B11: Serie o formula | C11: base1'G074.IPC.IND.Z.EP09.C.T | D11: base1'G074.IPCSAE.IND.Z.EP09.C.T | E11: base1'G074.IPCSAE.IND.TRANS.EP09.C.T | F11: base1'G074.IPCSAE.IND.NTRANS.EP09.C.T | G11: base1'G074.IPCX1.IND.Z.EP09.C.T | I11: Serie o formula | J11: base1'G074.IPC.IND.Z.EP09.C.T.X12R.D16 | K11: base1'G074.IPCSAE.IND.Z.EP09.C.T.X12R.D16 | L11: base1'G074.IPCSAE.IND.TRANS.EP09.C.T.X12R.D16 | M11: base1'G074.IPCSAE.IND.NTRANS.EP09.C.T.X12R.D16 | N11: base1'G074.IPCX1.IND.Z.EP09.C.T.X12R.D16
B12: Serie o formula | I12: Serie o formula
B13: fame | I13: fame
B14: =[1]!FAMEData("FAMEDATE", $B$3, $B$4, 0,$B$5, "Down", "Heading", "Normal") -> #NAME? | C14: =[1]!FAMEData(IF(C$13="",C$11,C$13&"("&C$11&")"), $B$3, $B$4, 0,$B$5, "Down", "Heading", "Normal") -> #NAME? | D14: =[1]!FAMEData(IF(D$13="",D$11,D$13&"("&D$11&")"), $B$3, $B$4, 0,$B$5, "Down", "Heading", "Normal") -> #NAME? | E14: =[1]!FAMEData(IF(E$13="",E$11,E$13&"("&E$11&")"), $B$3, $B$4, 0,$B$5, "Down", "Heading", "Normal") -> #NAME? | F14: =[1]!FAMEData(IF(F$13="",F$11,F$13&"("&F$11&")"), $B$3, $B$4, 0,$B$5, "Down", "Heading", "Normal") -> #NAME? | G14: =[1]!FAMEData(IF(G$13="",G$11,G$13&"("&G$11&")"), $B$3, $B$4, 0,$B$5, "Down", "Heading", "Normal") -> #NAME? | I14: =[1]!FAMEData("FAMEDATE", $B$3, $B$4, 0,$B$5, "Down", "Heading", "Normal") -> #NAME? | J14: =[1]!FAMEData(IF(J$13="",J$11,J$13&"("&J$11&")"), $B$3, $B$4, 0,$B$5, "Down", "Heading", "Normal") -> #NAME? | K14: =[1]!FAMEData(IF(K$13="",K$11,K$13&"("&K$11&")"), $B$3, $B$4, 0,$B$5, "Down", "Heading", "Normal") -> #NAME? | L14: =[1]!FAMEData(IF(L$13="",L$11,L$13&"("&L$11&")"), $B$3, $B$4, 0,$B$5, "Down", "Heading", "Normal") -> #NAME? | M14: =[1]!FAMEData(IF(M$13="",M$11,M$13&"("&M$11&")"), $B$3, $B$4, 0,$B$5, "Down", "Heading", "Normal") -> #NAME? | N14: =[1]!FAMEData(IF(N$13="",N$11,N$13&"("&N$11&")"), $B$3, $B$4, 0,$B$5, "Down", "Heading", "Normal") -> #NAME?
B15: 32689 | C15: 23.099144 | D15: 24.066851 | E15: 41.651495 | F15: 17.98604 | G15: 23.31666 | I15: 32689 | J15: 0.99490934 | K15: 1.0066494 | L15: 1.0113833 | M15: 1.004607 | N15: 1.0060425 | P15: =C15/J15 -> 23.217336 | Q15: =D15/K15 -> 23.907877 | R15: =E15/L15 -> 41.182698 | S15: =F15/M15 -> 17.903559 | T15: =G15/N15 -> 23.176615
B16: 32781 | C16: 24.278653 | D16: 25.098168 | E16: 42.530962 | F16: 18.996427 | G16: 24.417276 | I16: 32781 | J16: 0.99803031 | K16: 0.99804638 | L16: 0.99705312 | M16: 0.99949829 | N16: 0.99917368 | P16: =C16/J16 -> 24.326569 | Q16: =D16/K16 -> 25.147296 | R16: =E16/L16 -> 42.656666 | S16: =F16/M16 -> 19.005963 | T16: =G16/N16 -> 24.437469
B17: 32873 | C17: 25.88818 | D17: 26.407535 | E17: 44.431313 | F17: 20.071766 | G17: 25.663891 | I17: 32873 | J17: 1.0107771 | K17: 0.99581328 | L17: 1.0023602 | M17: 0.99235587 | N17: 0.99706262 | P17: =C17/J17 -> 25.612156 | Q17: =D17/K17 -> 26.518561 | R17: =E17/L17 -> 44.326692 | S17: =F17/M17 -> 20.22638 | T17: =G17/N17 -> 25.739497
B18: 32963 | C18: 27.329935 | D18: 28.226595 | E18: 45.863447 | F18: 21.885431 | G18: 27.009741 | I18: 32963 | J18: 0.99938137 | K18: 0.9996659 | L18: 0.98764355 | M18: 1.0049246 | N18: 0.99734254 | P18: =C18/J18 -> 27.346852 | Q18: =D18/K18 -> 28.236028 | R18: =E18/L18 -> 46.437247 | S18: =F18/M18 -> 21.778182 | T18: =G18/N18 -> 27.08171
B19: 33054 | C19: 28.785801 | D19: 30.072803 | E19: 49.275174 | F19: 23.207847 | G19: 28.806828 | I19: 33054 | J19: 0.99424229 | K19: 1.0073594 | L19: 1.0111904 | M19: 1.0056235 | N19: 1.006297 | P19: =C19/J19 -> 28.952501 | Q19: =D19/K19 -> 29.853102 | R19: =E19/L19 -> 48.729867 | S19: =F19/M19 -> 23.078068 | T19: =G19/N19 -> 28.626567
B20: 33146 | C20: 30.735199 | D20: 31.459721 | E20: 51.073178 | F20: 24.403757 | G20: 30.241231 | I20: 33146 | J20: 0.9984882 | K20: 0.99712361 | L20: 0.9971819 | M20: 0.99719604 | N20: 0.99950569 | P20: =C20/J20 -> 30.781735 | Q20: =D20/K20 -> 31.550473 | R20: =E20/L20 -> 51.217514 | S20: =F20/M20 -> 24.472377 | T20: =G20/N20 -> 30.256188
B21: 33238 | C21: 33.401313 | D21: 33.286027 | E21: 53.833069 | F21: 25.874715 | G21: 32.007264 | I21: 33238 | J21: 1.0127685 | K21: 0.9972826 | L21: 1.0028477 | M21: 0.99410694 | N21: 0.99743635 | P21: =C21/J21 -> 32.980206 | Q21: =D21/K21 -> 33.376724 | R21: =E21/L21 -> 53.680205 | S21: =F21/M21 -> 26.0281 | T21: =G21/N21 -> 32.089531
B22: 33328 | C22: 33.916486 | D22: 34.699419 | E22: 55.390087 | F22: 27.166324 | G22: 33.515833 | I22: 33328 | J22: 0.99660405 | K22: 0.99985708 | L22: 0.98870142 | M22: 1.0052589 | N22: 0.99815548 | P22: =C22/J22 -> 34.032058 | Q22: =D22/K22 -> 34.704379 | R22: =E22/L22 -> 56.023068 | S22: =F22/M22 -> 27.024205 | T22: =G22/N22 -> 33.577767
B23: 33419 | C23: 35.620055 | D23: 36.672025 | E23: 59.890404 | F23: 28.352964 | G23: 35.769589 | I23: 33419 | J23: 0.99457307 | K23: 1.0065034 | L23: 1.0100134 | M23: 1.0049861 | N23: 1.0055664 | P23: =C23/J23 -> 35.814418 | Q23: =D23/K23 -> 36.435072 | R23: =E23/L23 -> 59.296644 | S23: =F23/M23 -> 28.212296 | T23: =G23/N23 -> 35.571583
B24: 33511 | C24: 37.467818 | D24: 38.067093 | E24: 61.82855 | F24: 29.521605 | G24: 37.380652 | I24: 33511 | J24: 0.99927964 | K24: 0.99794414 | L24: 0.99725497 | M24: 0.99870823 | N24: 0.99937269 | P24: =C24/J24 -> 37.494828 | Q24: =D24/K24 -> 38.145515 | R24: =E24/L24 -> 61.998738 | S24: =F24/M24 -> 29.55979 | T24: =G24/N24 -> 37.404116
B25: 33603 | C25: 39.442023 | D25: 39.560112 | E25: 64.960348 | F25: 30.492373 | G25: 38.775181 | I25: 33603 | J25: 1.0102212 | K25: 0.99663504 | L25: 1.0037526 | M25: 0.99324518 | N25: 0.99727151 | P25: =C25/J25 -> 39.042957 | Q25: =D25/K25 -> 39.69368 | R25: =E25/L25 -> 64.71749 | S25: =F25/M25 -> 30.699744 | T25: =G25/N25 -> 38.881268
B26: 33694 | C26: 40.250745 | D26: 41.05696 | E26: 66.079483 | F26: 32.000484 | G26: 40.241956 | I26: 33694 | J26: 0.99787118 | K26: 0.99913521 | L26: 0.99055926 | M26: 1.0024577 | N26: 0.99846282 | P26: =C26/J26 -> 40.336615 | Q26: =D26/K26 -> 41.092496 | R26: =E26/L26 -> 66.709268 | S26: =F26/M26 -> 31.922027 | T26: =G26/N26 -> 40.303911
... B109: 41274 | C109: 108.79211 | D109: 104.34936 | E109: 90.181036 | F109: 116.42251 | G109: 103.44011 | I109: 41274 | J109: 1.0016126 | K109: 0.99871145 | L109: 0.9997174 | M109: 0.9978355 | N109: 0.99892638 | P109: =C109/J109 -> 108.61696 | Q109: =D109/K109 -> 104.48399 | R109: =E109/L109 -> 90.206528 | S109: =F109/M109 -> 116.67506 | T109: =G109/N109 -> 103.55129
I110: 41364 | J110: 0.99983027 | K110: 1.0016221 | L110: 1.0017547 | M110: 1.0005471 | N110: 1.0008038
I111: 41455 | J111: 0.9989773 | K111: 1.0008928 | L111: 1.0009316 | M111: 1.0011241 | N111: 1.0005327
I112: 41547 | J112: 0.99978514 | K112: 0.99881867 | L112: 0.99850623 | M112: 0.99983698 | N112: 1.0002611
I113: 41639 | J113: 1.0029687 | K113: 0.99942629 | L113: 0.99963177 | M113: 0.99876089 | N113: 0.99948766
I114: 41729 | J114: 0.99706501 | K114: 1.0008955 | L114: 1.0005334 | M114: 1.0000552 | N114: 0.99994157
I115: 41820 | J115: 0.99855047 | K115: 1.000161 | L115: 1.0003116 | M115: 1.0008892 | N115: 1.0001047
I116: 41912 | J116: 1.0006662 | K116: 0.99956609 | L116: 0.99880799 | M116: 1.0009598 | N116: 1.0001991
I117: 42004 | J117: 1.0018831 | K117: 0.99926413 | L117: 0.99958295 | M117: 0.99930925 | N117: 0.99904709

Sheet PIB_Nominal
A1: Exportar Canasta
A2: Reg | B2: 1 | C2: 2
A3: Descripción series | B3: PIB a precios corrientes serie empalmada | C3: PIB a precios corrientes serie empalmada
A4: Cálculo | B4: Serie Original | C4: Serie Original
A5: 32933 | B5: 2272486 | C5: =+C9*B5/B9 -> 2380661
A6: 33025 | B6: 2435975 | C6: =+C10*B6/B10 -> 2485127.8
A7: 33117 | B7: 2393863 | C7: =+C11*B7/B11 -> 2450244
A8: 33208 | B8: 2649100 | C8: =+C12*B8/B12 -> 2717112.5
A9: 33298 | B9: 2987340 | C9: =+C13*B9/B13 -> 3129543.5
A10: 33390 | B10: 3194308 | C10: =+C14*B10/B14 -> 3258762.4
A11: 33482 | B11: 3134596 | C11: =+C15*B11/B15 -> 3208423
A12: 33573 | B12: 3543079 | C12: =+C16*B12/B16 -> 3634043.3
A13: 33664 | B13: 3899291 | C13: =+C17*B13/B17 -> 4084905.2
A14: 33756 | B14: 3962580 | C14: =+C18*B14/B18 -> 4042536.5
A15: 33848 | B15: 4071912 | C15: =+C19*B15/B19 -> 4167815
A16: 33939 | B16: 4338483 | C16: =+C20*B16/B20 -> 4449868.3
... A56: 37591 | B56: 12225029 | C56: =+C60*B56/B60 -> 12538892
A57: 37681 | B57: 12372622 | C57: 12961584
A58: 37773 | B58: 12911207 | C58: 13171728
A59: 37865 | B59: 12572311 | C59: 12868419
A60: 37956 | B60: 13300275 | C60: 13641744
A61: 38047 | B61: 13463275 | C61: 14302232
A62: 38139 | B62: 14476214 | C62: 14879253
A63: 38231 | B63: 14728838 | C63: 15112053
A64: 38322 | B64: 15634884 | C64: 16252987
A65: 38412 | B65: 15395518 | C65: 16437017
A66: 38504 | B66: 16537704 | C66: 16952650
A67: 38596 | B67: 16670597 | C67: 17080992
A68: 38687 | B68: 17588776 | C68: 18412109
... A91: 40787 | B91: 27929602 | C91: 29078201
A92: 40878 | C92: 31861703
A93: 40969 | C93: 31405318
A94: 41061 | C94: 31623765
A95: 41153 | C95: 31260912
A96: 41244 | C96: 33617704

Sheet EMBI_Chile
B2: EMBI | C2: EMBI Empalmada | D2: EMBI ex Codelco | E2: Spread | F2: EMBI ex Codelco | G2: EMBI BASE 7 | J2: Date | K2: F019.SPS.PBP.91.M
A3: 1986T1 | B3: =[2]data_ipom!W14 -> 0 | C3: =F3*C4/F4 -> 213.7201 | D3: =[2]data_ipom!X14 -> 0 | E3: 2 | F3: =+E3*100 -> 200 | J3: 36281 | K3: 192
A4: 1986T2 | B4: =[2]data_ipom!W15 -> 0 | C4: =F4*C5/F5 -> 234.91045 | D4: =[2]data_ipom!X15 -> 0 | E4: 2.1983 | F4: =+E4*100 -> 219.83 | J4: 36312 | K4: 188
A5: 1986T3 | B5: =[2]data_ipom!W16 -> 224.665 | C5: =F5*C6/F6 -> 240.07713 | D5: =[2]data_ipom!X16 -> 224.665 | E5: 2.24665 | F5: =+E5*100 -> 224.665 | J5: 36342 | K5: 185 | L5: 1
A6: 1986T4 | B6: =[2]data_ipom!W17 -> 205 | C6: =F6*C7/F7 -> 219.0631 | D6: =[2]data_ipom!X17 -> 205 | E6: 2.05 | F6: =+E6*100 -> 205 | J6: 36373 | K6: 191 | L6: 2
A7: 1987T1 | B7: =[2]data_ipom!W18 -> 160.665 | C7: =F7*C8/F8 -> 171.6867 | D7: =[2]data_ipom!X18 -> 160.665 | E7: 1.60665 | F7: =+E7*100 -> 160.665 | J7: 36404 | K7: 187 | L7: 3
A8: 1987T2 | B8: =[2]data_ipom!W19 -> 172.165 | C8: =F8*C9/F9 -> 183.9756 | D8: =[2]data_ipom!X19 -> 172.165 | E8: 1.72165 | F8: =+E8*100 -> 172.165 | J8: 36434 | K8: 159 | L8: 4
A9: 1987T3 | B9: =[2]data_ipom!W20 -> 196.665 | C9: =F9*C10/F10 -> 210.15632 | D9: =[2]data_ipom!X20 -> 196.665 | E9: 1.96665 | F9: =+E9*100 -> 196.665 | J9: 36465 | K9: 156 | L9: 5
A10: 1987T4 | B10: =[2]data_ipom!W21 -> 107.665 | C10: =F10*C11/F11 -> 115.05087 | D10: =[2]data_ipom!X21 -> 107.665 | E10: 1.07665 | F10: =+E10*100 -> 107.665 | J10: 36495 | K10: 145 | L10: 6
A11: 1988T1 | B11: =[2]data_ipom!W22 -> 56 | C11: =F11*C12/F12 -> 59.841627 | D11: =[2]data_ipom!X22 -> 56 | E11: 0.56 | F11: =+E11*100 -> 56 | J11: 36526 | K11: 150 | L11: 7
A12: 1988T2 | B12: =[2]data_ipom!W23 -> 52.5 | C12: =F12*C13/F13 -> 56.101526 | D12: =[2]data_ipom!X23 -> 52.5 | E12: 0.525 | F12: =+E12*100 -> 52.5 | J12: 36557 | K12: 161 | L12: 8
A13: 1988T3 | B13: =[2]data_ipom!W24 -> 52.165 | C13: =F13*C14/F14 -> 55.743544 | D13: =[2]data_ipom!X24 -> 52.165 | E13: 0.52165 | F13: =+E13*100 -> 52.165 | J13: 36586 | K13: 172 | L13: 9
A14: 1988T4 | B14: =[2]data_ipom!W25 -> 67.5 | C14: =F14*C15/F15 -> 72.130533 | D14: =[2]data_ipom!X25 -> 67.5 | E14: 0.675 | F14: =+E14*100 -> 67.5 | J14: 36617 | K14: 200 | L14: 10
A15: 1989T1 | B15: =[2]data_ipom!W26 -> 66.835 | C15: =F15*C16/F16 -> 71.419914 | D15: =[2]data_ipom!X26 -> 66.835 | E15: 0.66835 | F15: =+E15*100 -> 66.835 | J15: 36647 | K15: 186 | L15: 11
A16: 1989T2 | B16: =[2]data_ipom!W27 -> 63.165 | C16: =F16*C17/F17 -> 67.49815 | D16: =[2]data_ipom!X27 -> 63.165 | E16: 0.63165 | F16: =+E16*100 -> 63.165 | J16: 36678 | K16: 220 | L16: 12
... A55: 1999T1 | B55: =[2]data_ipom!W66 -> 195.83333 | C55: =F55*C56/F56 -> 209.2676 | D55: =[2]data_ipom!X66 -> 195.83333 | E55: 1.9583333 | F55: =+E55*100 -> 195.83333 | J55: 37865 | K55: 108 | L55: 51
A56: 1999T2 | B56: =[2]data_ipom!W67 -> 190.03279 | C56: =B56 -> 190.03279 | D56: =[2]data_ipom!X67 -> 177.83333 | E56: 1.7783333 | F56: =+E56*100 -> 177.83333 | J56: 37895 | K56: 97 | L56: 52
A57: 1999T3 | B57: =[2]data_ipom!W68 -> 187.67391 | C57: =B57 -> 187.67391 | D57: =[2]data_ipom!X68 -> 161 | E57: 1.61 | F57: =+E57*100 -> 161 | G57: =AVERAGE(OFFSET($K$5,(L5-1)*3,0,3,1)) -> 187.66667 | H57: =B57-G57 -> 0.0072463768 | J57: 37926 | K57: 87 | L57: 53 | N57: =[1]!FAMEData(K2, "1999q3", "2013", 0,"Quarterly", "Down", "No Heading", "Normal") -> #NAME? | O57: =N57/B57 -> #NAME?
A58: 1999T4 | B58: =[2]data_ipom!W69 -> 153.30435 | C58: =B58 -> 153.30435 | D58: =[2]data_ipom!X69 -> 153 | E58: 1.53 | F58: =+E58*100 -> 153 | G58: =AVERAGE(OFFSET($K$5,(L6-1)*3,0,3,1)) -> 153.33333 | H58: =B58-G58 -> -0.028985507 | J58: 37956 | K58: 86 | L58: 54 | N58: 153.30435 | O58: =N58/B58 -> 1
A59: 2000T1 | B59: =[2]data_ipom!W70 -> 161 | C59: =B59 -> 161 | D59: =[2]data_ipom!X70 -> 161.08144 | E59: 1.6479581 | F59: =+E59*100 -> 164.79581 | G59: =AVERAGE(OFFSET($K$5,(L7-1)*3,0,3,1)) -> 161 | H59: =B59-G59 -> 0 | J59: 37987 | K59: 88 | L59: 55 | N59: 161 | O59: =N59/B59 -> 1
A60: 2000T2 | B60: =[2]data_ipom!W71 -> 201.82418 | C60: =B60 -> 201.82418 | D60: =[2]data_ipom!X71 -> 201.74394 | E60: 2.1809634 | F60: =+E60*100 -> 218.09634 | G60: =AVERAGE(OFFSET($K$5,(L8-1)*3,0,3,1)) -> 202 | H60: =B60-G60 -> -0.17582418 | J60: 38018 | K60: 93 | L60: 56 | N60: 201.82418 | O60: =N60/B60 -> 1
A61: 2000T3 | B61: =[2]data_ipom!W72 -> 202.44565 | C61: =B61 -> 202.44565 | D61: =[2]data_ipom!X72 -> 202.61422 | E61: 1.93 | F61: =+E61*100 -> 193 | G61: =AVERAGE(OFFSET($K$5,(L9-1)*3,0,3,1)) -> 202.33333 | H61: =B61-G61 -> 0.11231884 | J61: 38047 | K61: 93 | L61: 57 | N61: 202.44565 | O61: =N61/B61 -> 1
A62: 2000T4 | B62: =[2]data_ipom!W73 -> 223.61957 | C62: =B62 -> 223.61957 | D62: =[2]data_ipom!X73 -> 223.76912 | E62: 2.27 | F62: =+E62*100 -> 227 | G62: =AVERAGE(OFFSET($K$5,(L10-1)*3,0,3,1)) -> 223.66667 | H62: =B62-G62 -> -0.047101449 | J62: 38078 | K62: 86 | L62: 58 | N62: 223.61957 | O62: =N62/B62 -> 1
A63: 2001T1 | B63: =[2]data_ipom!W74 -> 196.92222 | C63: =B63 -> 196.92222 | D63: =[2]data_ipom!X74 -> 196.52069 | E63: 1.93 | F63: =+E63*100 -> 193 | G63: =AVERAGE(OFFSET($K$5,(L11-1)*3,0,3,1)) -> 196.66667 | H63: =B63-G63 -> 0.25555556 | J63: 38108 | K63: 98 | L63: 59 | N63: 196.92222 | O63: =N63/B63 -> 1
A64: 2001T2 | B64: =[2]data_ipom!W75 -> 177.68132 | C64: =B64 -> 177.68132 | D64: =[2]data_ipom!X75 -> 178.45549 | E64: 1.91 | F64: =+E64*100 -> 191 | G64: =AVERAGE(OFFSET($K$5,(L12-1)*3,0,3,1)) -> 177.66667 | H64: =B64-G64 -> 0.014652015 | J64: 38139 | K64: 86 | L64: 60 | N64: 177.68132 | O64: =N64/B64 -> 1
A65: 2001T3 | B65: =[2]data_ipom!W76 -> 192.3913 | C65: =B65 -> 192.3913 | D65: =[2]data_ipom!X76 -> 191.80837 | E65: 1.75 | F65: =+E65*100 -> 175 | G65: =AVERAGE(OFFSET($K$5,(L13-1)*3,0,3,1)) -> 192.66667 | H65: =B65-G65 -> -0.27536232 | J65: 38169 | K65: 85 | L65: 61 | N65: 192.3913 | O65: =N65/B65 -> 1
A66: 2001T4 | B66: =[2]data_ipom!W77 -> 201.98913 | C66: =B66 -> 201.98913 | D66: =[2]data_ipom!X77 -> 201.9963 | E66: 1.67 | F66: =+E66*100 -> 167 | G66: =AVERAGE(OFFSET($K$5,(L14-1)*3,0,3,1)) -> 202 | H66: =B66-G66 -> -0.010869565 | J66: 38200 | K66: 73 | L66: 62 | N66: 201.98913 | O66: =N66/B66 -> 1
A67: 2002T1 | B67: =[2]data_ipom!W78 -> 159.38889 | C67: =B67 -> 159.38889 | D67: =[2]data_ipom!X78 -> 159.39451 | E67: 1.62 | F67: =+E67*100 -> 162 | G67: =AVERAGE(OFFSET($K$5,(L15-1)*3,0,3,1)) -> 159.66667 | H67: =B67-G67 -> -0.27777778 | J67: 38231 | K67: 72 | L67: 63 | N67: 159.38889 | O67: =N67/B67 -> 1
A68: 2002T2 | B68: =[2]data_ipom!W79 -> 144.61538 | C68: =B68 -> 144.61538 | D68: =[2]data_ipom!X79 -> 144.55501 | E68: 1.6 | F68: =+E68*100 -> 160 | G68: =AVERAGE(OFFSET($K$5,(L16-1)*3,0,3,1)) -> 144.66667 | H68: =B68-G68 -> -0.051282051 | J68: 38261 | K68: 78 | L68: 64 | N68: 144.61538 | O68: =N68/B68 -> 1
A69: 2002T3 | B69: =[2]data_ipom!W80 -> 204.71739 | C69: =B69 -> 204.71739 | D69: =[2]data_ipom!X80 -> 204.62626 | E69: 1.58 | F69: =+E69*100 -> 158 | G69: =AVERAGE(OFFSET($K$5,(L17-1)*3,0,3,1)) -> 204.66667 | H69: =B69-G69 -> 0.050724638 | J69: 38292 | K69: 73 | L69: 65 | N69: 204.71739 | O69: =N69/B69 -> 1
... A95: 2009T1 | B95: =[2]data_ipom!W106 -> 357.22222 | C95: =B95 -> 357.22222 | D95: =[2]data_ipom!X106 -> 204.22437 | E95: 1.6673756 | F95: =+E95*100 -> 166.73756 | G95: =AVERAGE(OFFSET($K$5,(L43-1)*3,0,3,1)) -> 357.66667 | H95: =B95-G95 -> -0.44444444 | J95: 39083 | K95: 81 | L95: 91 | N95: 357.22222 | O95: =N95/B95 -> 1
A96: 2009T2 | B96: =[2]data_ipom!W107 -> 241.41758 | C96: =B96 -> 241.41758 | D96: =[2]data_ipom!X107 -> 149.99875 | G96: =AVERAGE(OFFSET($K$5,(L44-1)*3,0,3,1)) -> 241.33333 | H96: =B96-G96 -> 0.084249084 | J96: 39114 | K96: 80 | L96: 92 | N96: 241.41758 | O96: =N96/B96 -> 1
A97: 2009T3 | B97: =[2]data_ipom!W108 -> 146.70652 | C97: =B97 -> 146.70652 | D97: =[2]data_ipom!X108 -> 74.605603 | G97: =AVERAGE(OFFSET($K$5,(L45-1)*3,0,3,1)) -> 146.66667 | H97: =B97-G97 -> 0.039855072 | J97: 39142 | K97: 86 | L97: 93 | N97: 146.70652 | O97: =N97/B97 -> 1
A98: 2009T4 | B98: =[2]data_ipom!W109 -> 126.29348 | C98: =B98 -> 126.29348 | D98: =[2]data_ipom!X109 -> 68.09663 | G98: =AVERAGE(OFFSET($K$5,(L46-1)*3,0,3,1)) -> 126.33333 | H98: =B98-G98 -> -0.039855072 | J98: 39173 | K98: 82 | L98: 94 | N98: 126.29348 | O98: =N98/B98 -> 1
A99: 2010T1 | B99: =[2]data_ipom!W110 -> 122.35556 | C99: =B99 -> 122.35556 | D99: =[2]data_ipom!X110 -> 73.306297 | G99: =AVERAGE(OFFSET($K$5,(L47-1)*3,0,3,1)) -> 122.66667 | H99: =B99-G99 -> -0.31111111 | J99: 39203 | K99: 80 | L99: 95 | N99: 122.35556 | O99: =N99/B99 -> 1
A100: 2010T2 | B100: =[2]data_ipom!W111 -> 135.05495 | C100: =B100 -> 135.05495 | D100: =[2]data_ipom!X111 -> 85.694232 | G100: =AVERAGE(OFFSET($K$5,(L48-1)*3,0,3,1)) -> 135 | H100: =B100-G100 -> 0.054945055 | J100: 39234 | K100: 80 | L100: 96 | N100: 135.05495 | O100: =N100/B100 -> 1
A101: 2010T3 | B101: =[2]data_ipom!W112 -> 134.68478 | C101: =B101 -> 134.68478 | D101: =[2]data_ipom!X112 -> 85.350124 | G101: =AVERAGE(OFFSET($K$5,(L49-1)*3,0,3,1)) -> 134.66667 | H101: =B101-G101 -> 0.018115942 | J101: 39264 | K101: 90 | L101: 97 | N101: 134.68478 | O101: =N101/B101 -> 1
A102: 2010T4 | B102: =[2]data_ipom!W113 -> 124.33696 | C102: =B102 -> 124.33696 | D102: =[2]data_ipom!X113 -> 75.449363 | G102: =AVERAGE(OFFSET($K$5,(L50-1)*3,0,3,1)) -> 124.33333 | H102: =B102-G102 -> 0.0036231884 | J102: 39295 | K102: 108 | L102: 98 | N102: 124.33696 | O102: =N102/B102 -> 1
A103: 2011T1 | B103: =[2]data_ipom!W114 -> 114.68889 | C103: =B103 -> 114.68889 | D103: =[2]data_ipom!X114 -> 75.639479 | G103: =AVERAGE(OFFSET($K$5,(L51-1)*3,0,3,1)) -> 114.66667 | H103: =B103-G103 -> 0.022222222 | J103: 39326 | K103: 121 | L103: 99 | N103: 114.68889 | O103: =N103/B103 -> 1
A104: 2011T2 | B104: =[2]data_ipom!W115 -> 127.65934 | C104: =B104 -> 127.65934 | D104: =[2]data_ipom!X115 -> 82.544277 | G104: =AVERAGE(OFFSET($K$5,(L52-1)*3,0,3,1)) -> 127.66667 | H104: =B104-G104 -> -0.0073260073 | J104: 39356 | K104: 117 | L104: 100 | N104: 127.65934 | O104: =N104/B104 -> 1
A105: 2011T3 | B105: =[2]data_ipom!W116 -> 149.41304 | C105: =B105 -> 149.41304 | D105: =[2]data_ipom!X116 -> 98.751368 | G105: =AVERAGE(OFFSET($K$5,(L53-1)*3,0,3,1)) -> 149.66667 | H105: =B105-G105 -> -0.25362319 | J105: 39387 | K105: 134 | L105: 101 | N105: 149.41304 | O105: =N105/B105 -> 1
A106: 2011T4 | B106: =[2]data_ipom!W117 -> 162.38043 | C106: =B106 -> 162.38043 | D106: =[2]data_ipom!X117 -> 112.63476 | G106: =AVERAGE(OFFSET($K$5,(L54-1)*3,0,3,1)) -> 162.33333 | H106: =B106-G106 -> 0.047101449 | J106: 39417 | K106: 153 | L106: 102 | N106: 162.38043 | O106: =N106/B106 -> 1
A107: 2012T1 | B107: =[2]data_ipom!W118 -> 157.31868 | C107: =B107 -> 157.31868 | D107: =[2]data_ipom!X118 -> 99.183369 | G107: =AVERAGE(OFFSET($K$5,(L55-1)*3,0,3,1)) -> 157.33333 | H107: =B107-G107 -> -0.014652015 | J107: 39448 | K107: 165 | L107: 103 | N107: 157.31868 | O107: =N107/B107 -> 1
... A110: 2012T4 | B110: =[2]data_ipom!W121 -> 128.25 | C110: =B110 -> 128.25 | D110: =[2]data_ipom!X121 -> 65.122194 | G110: =AVERAGE(OFFSET($K$5,(L58-1)*3,0,3,1)) -> 128.33333 | H110: =B110-G110 -> -0.083333333 | J110: 39539 | K110: 172 | L110: 106 | N110: 128.25 | O110: =N110/B110 -> 1
A111: 2013T1 | J111: 39569 | K111: 159 | L111: 107 | N111: 115 | O111: =N111/B111 -> #DIV/0!
A112: 2013T2 | J112: 39600 | K112: 166 | L112: 108
A113: 2013T3 | J113: 39630 | K113: 181 | L113: 109
A114: 2013T4 | J114: 39661 | K114: 173 | L114: 110
A115: 2014T1 | J115: 39692 | K115: 189 | L115: 111
A116: 2014T2 | J116: 39722 | K116: 307 | L116: 112
A117: 2014T3 | J117: 39753 | K117: 353 | L117: 113
A118: 2014T4 | J118: 39783 | K118: 351 | L118: 114
A119: 2015T1 | J119: 39814 | K119: 383 | L119: 115
A120: 2015T2 | J120: 39845 | K120: 371 | L120: 116
A121: 2015T3 | J121: 39873 | K121: 319 | L121: 117
A122: 2015T4 | J122: 39904 | K122: 303 | L122: 118
J123: 39934 | K123: 249 | L123: 119
J124: 39965 | K124: 172 | L124: 120
J125: 39995 | K125: 163 | L125: 121
J126: 40026 | K126: 134 | L126: 122
J127: 40057 | K127: 143 | L127: 123
J128: 40087 | K128: 138 | L128: 124
J129: 40118 | K129: 130 | L129: 125
J130: 40148 | K130: 111 | L130: 126
J131: 40179 | K131: 108 | L131: 127
J132: 40210 | K132: 132 | L132: 128
J133: 40238 | K133: 128 | L133: 129
J134: 40269 | K134: 111 | L134: 130
... J167: 41275 | K167: 115 | L167: 163
J168: 41306 | L168: 164
L169: 165

Sheet Balanza_Comercial
B1: fuente: bcentral.cl
A2: Nombre Largo | B2: Exportaciones de Bienes por Trimestre | C2: Total de importación de bienes (cif) | D2: Total de importación de bienes (fob) | E2: Exportaciones de bienes (FOB) | F2: Importaciones Totales (CIF) | G2: Exportaciones Reales | H2: Importaciones Reales | I2: Balanza Comercial Nominal | J2: Balanza Comercial Real
A3: Unidad | B3: Mill. US$ | C3: Mill. US$ | D3: Mill. US$ | E3: Mill. US$ | F3: Mill. US$ | G3: Mill. $ 08 | H3: Mill. $ 08 | I3: Mill. US $ | J3: Mill. $ 08
A4: Origen datos | B4: bcentral.cl | C4: bcentral.cl | D4: bcentral.cl | E4: DAC | F4: DAC | G4: CC.NN | H4: CC.NN | I4: CC.NN. | J4: CC.NN
A5: Acceso | B5: Público | C5: Público | D5: Público | E5: Público | F5: Público | G5: Público | H5: Público | I5: Pública | J5: Público
A6: Fecha actualización | B6: 41319 | C6: 41319 | D6: 41319 | E6: 41319 | F6: 41319 | G6: 41319 | H6: 41319 | I6: 41319 | J6: 41319
A7: Ult. Dato Efectivo | B7: 2012T4 | C7: 2012T4 | D7: 2012T4 | E7: 2012T4 | F7: 2012T4 | G7: 2012T4 | H7: 2012T4 | I7: 2012T4 | J7: 2012T4
A8: 1986T1 | B8: =G8*B9/G9 -> 1310.3364 | C8: =H8*C9/H9 -> 791.63475 | G8: =[3]Originales!M12 -> 1896676.5 | H8: =[3]Originales!N12 -> 768338.27 | I8: =B8-C8 -> 518.70168 | J8: =G8-H8 -> 1128338.3
A9: 1986T2 | B9: =G9*B10/G10 -> 1231.2845 | C9: =H9*C10/H10 -> 805.18262 | G9: =[3]Originales!M13 -> 1782251 | H9: =[3]Originales!N13 -> 781487.45 | I9: =B9-C9 -> 426.10185 | J9: =G9-H9 -> 1000763.5
A10: 1986T3 | B10: =G10*B11/G11 -> 1094.4157 | C10: =H10*C11/H11 -> 911.9106 | G10: =[3]Originales!M14 -> 1584137.1 | H10: =[3]Originales!N14 -> 885074.61 | I10: =B10-C10 -> 182.50509 | J10: =G10-H10 -> 699062.52
A11: 1986T4 | B11: =G11*B12/G12 -> 1240.1651 | C11: =H11*C12/H12 -> 929.75667 | G11: =[3]Originales!M15 -> 1795105.5 | H11: =[3]Originales!N15 -> 902395.49 | I11: =B11-C11 -> 310.40844 | J11: =G11-H11 -> 892709.96
A12: 1987T1 | B12: =G12*B13/G13 -> 1505.1514 | C12: =H12*C13/H13 -> 1017.8823 | G12: =[3]Originales!M16 -> 2178666 | H12: =[3]Originales!N16 -> 987927.75 | I12: =B12-C12 -> 487.2691 | J12: =G12-H12 -> 1190738.2
A13: 1987T2 | B13: =G13*B14/G14 -> 1336.0283 | C13: =H13*C14/H14 -> 999.16291 | G13: =[3]Originales!M17 -> 1933864.9 | H13: =[3]Originales!N17 -> 969759.23 | I13: =B13-C13 -> 336.86543 | J13: =G13-H13 -> 964105.67
A14: 1987T3 | B14: =G14*B15/G15 -> 1128.6698 | C14: =H14*C15/H15 -> 1055.5741 | G14: =[3]Originales!M18 -> 1633719 | H14: =[3]Originales!N18 -> 1024510.3 | I14: =B14-C14 -> 73.09576 | J14: =G14-H14 -> 609208.75
A15: 1987T4 | B15: =G15*B16/G16 -> 1235.0212 | C15: =H15*C16/H16 -> 1005.7601 | G15: =[3]Originales!M19 -> 1787659.8 | H15: =[3]Originales!N19 -> 976162.24 | I15: =B15-C15 -> 229.26114 | J15: =G15-H15 -> 811497.56
A16: 1988T1 | B16: =G16*B17/G17 -> 1583.0845 | C16: =H16*C17/H17 -> 1116.9117 | G16: =[3]Originales!M20 -> 2291472 | H16: =[3]Originales!N20 -> 1084042.8 | I16: =B16-C16 -> 466.17283 | J16: =G16-H16 -> 1207429.2
A17: 1988T2 | B17: =G17*B18/G18 -> 1463.1005 | C17: =H17*C18/H18 -> 1062.4343 | G17: =[3]Originales!M21 -> 2117798.4 | H17: =[3]Originales!N21 -> 1031168.7 | I17: =B17-C17 -> 400.66617 | J17: =G17-H17 -> 1086629.7
A18: 1988T3 | B18: =G18*B19/G19 -> 1287.7687 | C18: =H18*C19/H19 -> 1162.6795 | G18: =[3]Originales!M22 -> 1864010.4 | H18: =[3]Originales!N22 -> 1128463.8 | I18: =B18-C18 -> 125.08919 | J18: =G18-H18 -> 735546.58
A19: 1988T4 | B19: =G19*B20/G20 -> 1472.3764 | C19: =H19*C20/H20 -> 1258.1125 | G19: =[3]Originales!M23 -> 2131225 | H19: =[3]Originales!N23 -> 1221088.4 | I19: =B19-C19 -> 214.2639 | J19: =G19-H19 -> 910136.65
... A75: 2002T4 | B75: =G75*B76/G76 -> 4926.1392 | C75: =H75*C76/H76 -> 4534.8859 | G75: =[3]Originales!M79 -> 7130453.3 | H75: =[3]Originales!N79 -> 4401431.9 | I75: =B75-C75 -> 391.25326 | J75: =G75-H75 -> 2729021.4
A76: 2003T1 | B76: 5193.575 | C76: 4518.0658 | D76: 4200.1962 | E76: =[4]Expo!C12 -> 5193.575 | F76: =[4]Impo!C12 -> 4518.0658 | G76: =[3]Originales!M80 -> 7517559.4 | H76: =[3]Originales!N80 -> 4385106.7 | I76: =B76-C76 -> 675.50923 | J76: =G76-H76 -> 3132452.7
A77: 2003T2 | B77: 5307.8952 | C77: 4805.9948 | D77: 4461.7284 | E77: =[4]Expo!C13 -> 5307.8952 | F77: =[4]Impo!C13 -> 4805.9948 | G77: =[3]Originales!M81 -> 7392756.8 | H77: =[3]Originales!N81 -> 4725916.3 | I77: =B77-C77 -> 501.90042 | J77: =G77-H77 -> 2666840.5
A78: 2003T3 | B78: 5182.2164 | C78: 4894.6989 | D78: 4541.7479 | E78: =[4]Expo!C14 -> 5182.2164 | F78: =[4]Impo!C14 -> 4894.6989 | G78: =[3]Originales!M82 -> 7278440.4 | H78: =[3]Originales!N82 -> 4790481.8 | I78: =B78-C78 -> 287.51744 | J78: =G78-H78 -> 2487958.6
A79: 2003T4 | B79: 5967.2203 | C79: 5045.3656 | D79: 4681.8457 | E79: =[4]Expo!C15 -> 5967.2203 | F79: =[4]Impo!C15 -> 5045.3656 | G79: =[3]Originales!M83 -> 7510067.5 | H79: =[3]Originales!N83 -> 4991522.6 | I79: =B79-C79 -> 921.85474 | J79: =G79-H79 -> 2518545
A80: 2004T1 | B80: 7685.2243 | C80: 5381.1762 | D80: 4966.5554 | E80: =[4]Expo!C16 -> 7685.2243 | F80: =[4]Impo!C16 -> 5381.1762 | G80: =[3]Originales!M84 -> 8349255.1 | H80: =[3]Originales!N84 -> 4973381.2 | I80: =B80-C80 -> 2304.048 | J80: =G80-H80 -> 3375873.9
A81: 2004T2 | B81: 7974.575 | C81: 5707.8526 | D81: 5299.3152 | E81: =[4]Expo!C17 -> 7974.575 | F81: =[4]Impo!C17 -> 5707.8526 | G81: =[3]Originales!M85 -> 8319262 | H81: =[3]Originales!N85 -> 5360876.8 | I81: =B81-C81 -> 2266.7224 | J81: =G81-H81 -> 2958385.2
A82: 2004T3 | B82: 8426.19 | C82: 6626.6082 | D82: 6122.6989 | E82: =[4]Expo!C18 -> 8426.19 | F82: =[4]Impo!C18 -> 6626.6082 | G82: =[3]Originales!M86 -> 8489441.4 | H82: =[3]Originales!N86 -> 5917325.8 | I82: =B82-C82 -> 1799.5818 | J82: =G82-H82 -> 2572115.6
A83: 2004T4 | B83: 8939.4177 | C83: 7011.3098 | D83: 6480.7238 | E83: =[4]Expo!C19 -> 8939.4177 | F83: =[4]Impo!C19 -> 7011.3098 | G83: =[3]Originales!M87 -> 8703018.5 | H83: =[3]Originales!N87 -> 6099485.6 | I83: =B83-C83 -> 1928.1079 | J83: =G83-H83 -> 2603532.9
A84: 2005T1 | B84: 9430.7375 | C84: 7254.1994 | D84: 6723.5241 | E84: =[4]Expo!C20 -> 9430.7375 | F84: =[4]Impo!C20 -> 7254.1994 | G84: =[3]Originales!M88 -> 8470058.2 | H84: =[3]Originales!N88 -> 5920375 | I84: =B84-C84 -> 2176.5381 | J84: =G84-H84 -> 2549683.2
A85: 2005T2 | B85: 10257.305 | C85: 7913.464 | D85: 7369.7329 | E85: =[4]Expo!C21 -> 10257.305 | F85: =[4]Impo!C21 -> 7913.464 | G85: =[3]Originales!M89 -> 8715657.7 | H85: =[3]Originales!N89 -> 6383443.7 | I85: =B85-C85 -> 2343.8409 | J85: =G85-H85 -> 2332214
A86: 2005T3 | B86: 10275.302 | C86: 8747.8717 | D86: 8168.4437 | E86: =[4]Expo!C22 -> 10275.302 | F86: =[4]Impo!C22 -> 8747.8717 | G86: =[3]Originales!M90 -> 8590562.1 | H86: =[3]Originales!N90 -> 6893546.9 | I86: =B86-C86 -> 1527.43 | J86: =G86-H86 -> 1697015.3
A87: 2005T4 | B87: 12010.648 | C87: 9009.9731 | D87: 8402.8284 | E87: =[4]Expo!C23 -> 12010.648 | F87: =[4]Impo!C23 -> 9009.9731 | G87: =[3]Originales!M91 -> 9043925.5 | H87: =[3]Originales!N91 -> 7010330.4 | I87: =B87-C87 -> 3000.6754 | J87: =G87-H87 -> 2033595.2
... A115: 2012T4 | B115: 21703.293 | C115: 21257.371 | D115: 20046.397 | E115: =[4]Expo!C51 -> 20451.694 | F115: =[4]Impo!C51 -> 22146.749 | G115: =[3]Originales!M119 -> 10820081 | H115: =[3]Originales!N119 -> 12730946 | I115: =B115-C115 -> 445.92171 | J115: =G115-H115 -> -1910864.6

Sheet Cuenta_Corriente
C1: Balanza de pagos resumen (millones de dólares) 2003-2012q3 | K1: Balanza de pagos resumen (millones de dólares) 1996-2011 | N1: Datos Modelo Macro | X1: Balanza de Pagos, 1973-1995 (Millones de dólares) | Z1: Balanza de pagos resumen 1996-2011 (millones de dólares) | AB1: Balanza de pagos resumen (millones de dólares)
B2: CC Empalmada | C2: 1. Cuenta corriente | D2: 2. Bienes (X-M) | E2: 3. Exportaciones | F2: 4. Importaciones (FOB) | G2: 5. Servicios | H2: 6. Renta (ingreso primario) | I2: 7. Transferencias corrientes (ingreso secundario) | J2: Construccion Cuenta Corriente | K2: 1. Cuenta corriente | L2: CC - Método Linear Matcgh Last - trimestralizar serie anual | O2: Cuenta Corriente | P2: Balanza Comercial | Q2: Balance Servicios | R2: Rentas | S2: Transferencias | X2: Periodo | Y2: Cuenta Corriente Empalmada | Z2: 1. Cuenta corriente | AA2: 1. Cuenta corriente | AB2: 1. Cuenta corriente
A3: 1986T1 | B3: =B4*L3/L4 -> -263.23384 | L3: -1446.2017 | N3: 2008 | O3: 1307.1366 | P3: 6072.4574 | Q3: -176.1973 | R3: -5096.8235 | S3: 507.7 | T3: =+P3+Q3+R3+S3 -> 1307.1366 | X3: 26665 | Y3: =Y4*Z3/Z4 -> -312.77288 | Z3: -293.6
A4: 1986T2 | B4: =B5*L4/L5 -> -252.48189 | L4: -1387.1307 | N4: 2008.25 | O4: -881.11661 | P4: 2832.9158 | Q4: -370.82882 | R4: -4600.4036 | S4: 1257.2 | T4: =+P4+Q4+R4+S4 -> -881.11661 | X4: 27030 | Y4: =Y5*Z4/Z5 -> -224.56581 | Z4: -210.8
A5: 1986T3 | B5: =B6*L5/L6 -> -241.72993 | L5: -1328.0596 | N5: 2008.5 | O5: -3350.0903 | P5: -1457.515 | Q5: -398.29125 | R5: -2222.884 | S5: 728.6 | T5: =+P5+Q5+R5+S5 -> -3350.0903 | X5: 27395 | Y5: =Y6*Z5/Z6 -> -523.80934 | Z5: -491.7
A6: 1986T4 | B6: =B7*L6/L7 -> -230.97798 | L6: -1268.9886 | N6: 2008.75 | O6: -2875.9473 | P6: -1373.7181 | Q6: -262.35903 | R6: -1676.1701 | S6: 436.3 | T6: =+P6+Q6+R6+S6 -> -2875.9473 | X6: 27760 | Y6: =Y7*Z6/Z7 -> 157.34521 | Z6: 147.7
A7: 1987T1 | B7: =B8*L7/L8 -> -208.88751 | L7: -1147.624 | N7: 2009 | O7: 953.4918 | P7: 2541.4623 | Q7: -311.57506 | R7: -1539.5954 | S7: 263.2 | T7: =+P7+Q7+R7+S7 -> 953.4918 | X7: 28126 | Y7: =Y8*Z7/Z8 -> -586.98179 | Z7: -551
A8: 1987T2 | B8: =B9*L8/L9 -> -186.79704 | L8: -1026.2594 | N8: 2009.25 | O8: 1812.5861 | P8: 4137.798 | Q8: -576.42855 | R8: -2472.6833 | S8: 723.9 | T8: =+P8+Q8+R8+S8 -> 1812.5861 | X8: 28491 | Y8: =Y9*Z8/Z9 -> -1158.9428 | Z8: -1087.9
A9: 1987T3 | B9: =B10*L9/L10 -> -164.70657 | L9: -904.89475 | N9: 2009.5 | O9: 305.81884 | P9: 3585.8413 | Q9: -683.39954 | R9: -2830.9229 | S9: 234.3 | T9: =+P9+Q9+R9+S9 -> 305.81884 | X9: 28856 | Y9: =Y10*Z9/Z10 -> -1267.071 | Z9: -1189.4
A10: 1987T4 | B10: =B11*L10/L11 -> -142.6161 | L10: -783.53014 | N10: 2009.75 | O10: 446.10735 | P10: 5094.9308 | Q10: -439.03987 | R10: -4551.4836 | S10: 341.7 | T10: =+P10+Q10+R10+S10 -> 446.10735 | X10: 29221 | Y10: =Y11*Z10/Z11 -> -2099.2855 | Z10: -1970.6
A11: 1988T1 | B11: =B12*L11/L12 -> -118.16971 | L11: -649.2221 | N11: 2010 | O11: 2161.0674 | P11: 3864.1278 | Q11: -174.82762 | R11: -3185.2498 | S11: 1657.0169 | T11: =+P11+Q11+R11+S11 -> 2161.0674 | X11: 29587 | Y11: =Y12*Z11/Z12 -> -5041.6516 | Z11: -4732.6
A12: 1988T2 | B12: =B13*L12/L13 -> -93.723309 | L12: -514.91406 | N12: 2010.25 | O12: 793.62469 | P12: 3056.9269 | Q12: -457.79172 | R12: -3159.9194 | S12: 1354.4089 | T12: =+P12+Q12+R12+S12 -> 793.62469 | X12: 29952 | Y12: =Y13*Z12/Z13 -> -2454.6705 | Z12: -2304.2
A13: 1988T3 | B13: =B14*L13/L14 -> -69.276912 | L13: -380.60602 | N13: 2010.5 | O13: -757.75826 | P13: 3503.792 | Q13: -628.14095 | R13: -4151.0022 | S13: 517.59288 | T13: =+P13+Q13+R13+S13 -> -757.75826 | X13: 30317 | Y13: =Y14*Z13/Z14 -> -1190.2627 | Z13: -1117.3
A14: 1988T4 | B14: =B15*L14/L15 -> -44.830514 | L14: -246.29799 | N14: 2010.75 | O14: 1071.6331 | P14: 4899.6251 | Q14: -545.06671 | R14: -4269.06 | S14: 986.13466 | T14: =+P14+Q14+R14+S14 -> 1071.6331 | X14: 30682 | Y14: =Y15*Z14/Z15 -> -2248.3214 | Z14: -2110.5
... A22: 1990T4 | B22: =B23*L22/L23 -> -94.004469 | L22: -516.45875 | N22: 2012.75 | O22: -3614.7742 | P22: -230.43876 | Q22: -428.79477 | R22: -3832.9009 | S22: 877.36032 | T22: =+P22+Q22+R22+S22 -> -3614.7742 | X22: 33604 | Y22: =Y23*Z22/Z23 -> -1020.7731 | Z22: -958.2
A23: 1991T1 | B23: =B24*L23/L24 -> -75.283076 | L23: -413.60378 | X23: 33970 | Y23: =Y24*Z23/Z24 -> -2720.1439 | Z23: -2553.4
A24: 1991T2 | B24: =B25*L24/L25 -> -56.561683 | L24: -310.7488 | X24: 34335 | Y24: =Y25*Z24/Z25 -> -1688.8244 | Z24: -1585.3
A25: 1991T3 | B25: =B26*L25/L26 -> -37.840289 | L25: -207.89382 | X25: 34700 | Y25: =Y26*Z25/Z26 -> -1432.9387 | Z25: -1345.1
A26: 1991T4 | B26: =B27*L26/L27 -> -19.118896 | L26: -105.03885 | X26: 35065 | Y26: =Y27*AA26/AA27 -> -3284.0087 | Z26: =AA26 -> -3082.7 | AA26: -3082.7
A27: 1992T1 | B27: =B28*L27/L28 -> -60.788781 | L27: -333.9724 | X27: 35431 | Y27: =Y28*AA27/AA28 -> -3899.221 | AA27: -3660.2
A28: 1992T2 | B28: =B29*L28/L29 -> -102.45867 | L28: -562.90595 | X28: 35796 | Y28: =Y29*AA28/AA29 -> -4174.2821 | AA28: -3918.4
A29: 1992T3 | B29: =B30*L29/L30 -> -144.12855 | L29: -791.8395 | X29: 36161 | Y29: =Y30*AA29/AA30 -> 105.99762 | AA29: 99.5
A30: 1992T4 | B30: =B31*L30/L31 -> -185.79844 | L30: -1020.7731 | X30: 36526 | Y30: =Y31*AA30/AA31 -> -956.00265 | AA30: -897.4
A31: 1993T1 | B31: =B32*L31/L32 -> -263.1272 | L31: -1445.6158 | X31: 36892 | Y31: =Y32*AA31/AA32 -> -1172.1526 | AA31: -1100.3
A32: 1993T2 | B32: =B33*L32/L33 -> -340.45596 | L32: -1870.4585 | X32: 37257 | Y32: =Y33*AA32/AA33 -> -617.9821 | AA32: -580.1
A33: 1993T3 | B33: =B34*L33/L34 -> -417.78471 | L33: -2295.3012 | X33: 37622 | Y33: =AB33 -> -829.55122 | AA33: -778.7 | AB33: -829.55122
A34: 1993T4 | B34: =B35*L34/L35 -> -495.11347 | L34: -2720.1439 | X34: 37987 | Y34: =AB34 -> 2597.4318 | AA34: 2074.5 | AB34: 2597.4318
A35: 1994T1 | B35: =B36*L35/L36 -> -448.18395 | L35: -2462.314 | X35: 38353 | Y35: =AB35 -> 1891.0492 | AA35: 1449 | AB35: 1891.0492
A36: 1994T2 | B36: =B37*L36/L37 -> -401.25443 | L36: -2204.4842 | X36: 38718 | Y36: =AB36 -> 7115.5641 | AA36: 7154.3 | AB36: 7115.5641
A37: 1994T3 | B37: =B38*L37/L38 -> -354.32491 | L37: -1946.6543 | X37: 39083 | Y37: =AB37 -> 7078.7728 | AA37: 7458.1 | AB37: 7078.7728
A38: 1994T4 | B38: =B39*L38/L39 -> -307.39539 | L38: -1688.8244 | X38: 39448 | Y38: =AB38 -> -5800.0804 | AA38: -3307.3 | AB38: -5800.0804
A39: 1995T1 | B39: =B40*L39/L40 -> -295.75148 | L39: -1624.853 | X39: 39814 | Y39: =AB39 -> 3518.0596 | AA39: 2570.1 | AB39: 3518.0596
A40: 1995T2 | B40: =B41*L40/L41 -> -284.10757 | L40: -1560.8815 | X40: 40179 | Y40: =AB40 -> 3268.5669 | AA40: 3801.7 | AB40: 3268.5669
A41: 1995T3 | B41: =B42*L41/L42 -> -272.46366 | L41: -1496.9101 | X41: 40544 | Y41: =AB41 -> -3220.1832 | AB41: -3220.1832
A42: 1995T4 | B42: =B43*L42/L43 -> -260.81974 | L42: -1432.9387 | X42: 40909
A43: 1996T1 | B43: =B44*K43/K44 -> -345.05147 | K43: -150.5 | L43: -1895.7062
A44: 1996T2 | B44: =B45*K44/K45 -> -582.57527 | K44: -254.1 | L44: -2358.4737
A45: 1996T3 | B45: =B46*K45/K46 -> -2751.9288 | K45: -1200.3 | L45: -2821.2412
A46: 1996T4 | B46: =B47*K46/K47 -> -3388.1532 | K46: -1477.8 | L46: -3284.0087
A47: 1997T1 | B47: =B48*K47/K48 -> 1022.3153 | K47: 445.9 | L47: -3437.8117
A48: 1997T2 | B48: =B49*K48/K49 -> -1379.7473 | K48: -601.8 | L48: -3591.6148
A49: 1997T3 | B49: =B50*K49/K50 -> -3515.6274 | K49: -1533.4 | L49: -3745.4179
A50: 1997T4 | B50: =B51*K50/K51 -> -4518.684 | K50: -1970.9 | L50: -3899.221
A51: 1998T1 | B51: =B52*K51/K52 -> -1796.1018 | K51: -783.4 | L51: -3967.9863
A52: 1998T2 | B52: =B53*K52/K53 -> -2426.8238 | K52: -1058.5 | L52: -4036.7516
A53: 1998T3 | B53: =B54*K53/K54 -> -3453.266 | K53: -1506.2 | L53: -4105.5168
A54: 1998T4 | B54: =B55*K54/K55 -> -1307.5273 | K54: -570.3 | L54: -4174.2821
... A70: 2002T4 | B70: =B71*K70/K71 -> 30.722191 | K70: 13.4 | L70: -617.9821
A71: 2003T1 | B71: =C71 -> 256.55322 | C71: 256.55322 | D71: 993.37885 | E71: 5193.575 | F71: 4200.1962 | G71: -159.55697 | H71: -707.21819 | I71: 129.9 | J71: =D71+G71+H71+I71 -> 256.50369 | K71: 111.9 | L71: -670.87438
A72: 2003T2 | B72: =C72 -> -193.30417 | C72: -193.30417 | D72: 846.1668 | E72: 5307.8952 | F72: 4461.7284 | G72: -230.69975 | H72: -943.10512 | I72: 134.3 | J72: =D72+G72+H72+I72 -> -193.33808 | K72: -314.5 | L72: -723.76666
A73: 2003T3 | B73: =C73 -> -567.56436 | C73: -567.56436 | D73: 640.46847 | E73: 5182.2164 | F73: 4541.7479 | G73: -258.6492 | H73: -1093.481 | I73: 144.1 | J73: =D73+G73+H73+I73 -> -567.56177 | K73: -596.9 | L73: -776.65894
A74: 2003T4 | B74: =C74 -> -325.23591 | C74: -325.23591 | D74: 1285.3746 | E74: 5967.2203 | F74: 4681.8457 | G74: -40.357342 | H74: -1766.8784 | I74: 196.6 | J74: =D74+G74+H74+I74 -> -325.26109 | K74: 20.8 | L74: -829.55122
A75: 2004T1 | B75: =C75 -> 1539.2474 | C75: 1539.2474 | D75: 2718.6689 | E75: 7685.2243 | F75: 4966.5554 | G75: -100.77033 | H75: -1232.1582 | I75: 153.5 | J75: =D75+G75+H75+I75 -> 1539.2404 | K75: 737 | L75: 27.194529
A76: 2004T2 | B76: =C76 -> 827.03123 | C76: 827.03123 | D76: 2675.2598 | E76: 7974.575 | F76: 5299.3152 | G76: -282.9316 | H76: -1960.8087 | I76: 395.5 | J76: =D76+G76+H76+I76 -> 827.01952 | K76: 735.1 | L76: 883.94028
A77: 2004T3 | B77: =C77 -> 36.223993 | C77: 36.223993 | D77: 2303.4911 | E77: 8426.19 | F77: 6122.6989 | G77: -306.13666 | H77: -2209.7645 | I77: 248.6 | J77: =D77+G77+H77+I77 -> 36.189878 | K77: -15.6 | L77: 1740.686
A78: 2004T4 | B78: =C78 -> 194.92915 | C78: 194.92915 | D78: 2458.6939 | E78: 8939.4177 | F78: 6480.7238 | G78: -114.35157 | H78: -2423.6406 | I78: 274.2 | J78: =D78+G78+H78+I78 -> 194.90172 | K78: 618 | L78: 2597.4318
A79: 2005T1 | B79: =C79 -> 769.95648 | C79: 769.95648 | D79: 2707.2134 | E79: 9430.7375 | F79: 6723.5241 | G79: -163.80963 | H79: -2072.8898 | I79: 299.4 | J79: =D79+G79+H79+I79 -> 769.914 | K79: 487.2 | L79: 2420.8361
A80: 2005T2 | B80: =C80 -> 756.24297 | C80: 756.24297 | D80: 2887.5719 | E80: 10257.305 | F80: 7369.7329 | G80: -320.84447 | H80: -2227.0984 | I80: 416.6 | J80: =D80+G80+H80+I80 -> 756.22912 | K80: 437.4 | L80: 2244.2405
A81: 2005T3 | B81: =C81 -> -389.16433 | C81: -389.16433 | D81: 2106.858 | E81: 10275.302 | F81: 8168.4437 | G81: -227.39211 | H81: -2671.2177 | I81: 402.6 | J81: =D81+G81+H81+I81 -> -389.15184 | K81: -505.6 | L81: 2067.6449
A82: 2005T4 | B82: =C82 -> 754.01411 | C82: 754.01411 | D82: 3607.8201 | E82: 12010.648 | F82: 8402.8284 | G82: -123.36762 | H82: -3394.6727 | I82: 664.2 | J82: =D82+G82+H82+I82 -> 753.97976 | K82: 1030 | L82: 1891.0492
... A105: 2011T3 | B105: =C105 -> -2998.7324 | C105: -2998.7324 | D105: 312.09701 | E105: 19298.621 | F105: 18986.531 | G105: -801.81574 | H105: -2991.4201 | I105: 482.4064 | J105: =D105+G105+H105+I105 -> -2998.7324 | K105: -2894.7 | L105: -1597.9957
A106: 2011T4 | B106: =C106 -> -1267.373 | C106: -1267.373 | D106: 2358.4188 | E106: 20565.442 | F106: 18207.06 | G106: -629.60392 | H106: -3491.5621 | I106: 495.37422 | J106: =D106+G106+H106+I106 -> -1267.373 | L106: -3220.1832
A107: 2012T1 | B107: =C107 -> 157.43594 | C107: 157.43594 | D107: 2646.8798 | E107: 19872.831 | F107: 17225.951 | G107: 83.941157 | H107: -2922.3198 | I107: 348.93474 | J107: =D107+G107+H107+I107 -> 157.43594
A108: 2012T2 | B108: =C108 -> -1744.7935 | C108: -1744.7935 | D108: 1681.4536 | E108: 19786.983 | F108: 18105.53 | G108: -549.80328 | H108: -3268.8255 | I108: 392.38167 | J108: =D108+G108+H108+I108 -> -1744.7935
A109: 2012T3 | B109: =C109 -> -4782.9634 | C109: -4782.9634 | D109: -1776.9777 | E109: 17449.681 | F109: 19226.658 | G109: -557.81842 | H109: -2735.8538 | I109: 287.68652 | J109: =D109+G109+H109+I109 -> -4782.9634
A110: 2012T4 | B110: =D110+G110+H110+I110 -> -1727.4391 | D110: =E110-F110 -> 1656.8963 | E110: 21703.293 | F110: 20046.397 | G110: =Q22 -> -428.79477 | H110: =R22 -> -3832.9009 | I110: =S22 -> 877.36032

Sheet fedfunds
A1: FEDFUNDS
A2: lin | B2: Percent
A3: M | B3: Monthly
A4: 19906 | B4: 1954-07-01 to 2013-01-01
A5: Effective Federal Funds Rate
A6: Board of Governors of the Federal Reserve System
A7: date | B7: value
A8: 19906 | B8: 0.8
A9: 19937 | B9: 1.22
A10: 19968 | B10: 1.06
A11: 19998 | B11: 0.85
A12: 20029 | B12: 0.83
A13: 20059 | B13: 1.28
A14: 20090 | B14: 1.39
A15: 20121 | B15: 1.29
A16: 20149 | B16: 1.35
A17: 20180 | B17: 1.43
A18: 20210 | B18: 1.43
A19: 20241 | B19: 1.64
... A710: 41275 | B710: 0.14

Sheet FEDFUNDS2
A1: FEDFUNDS
A2: lin | B2: Percent
A3: M | B3: Monthly
A4: 19906 | B4: 1954-07-01 to 2013-01-01
A5: Effective Federal Funds Rate
A6: Board of Governors of the Federal Reserve System
A7: date | B7: value | E7: Fed Fund
A8: 19906 | B8: =fedfunds!B8 -> 0.8 | D8: 1986T1 | E8: =AVERAGE(OFFSET($B$386,(C386-1)*3,0,3,1)) -> 7.8266667
A9: 19937 | B9: =fedfunds!B9 -> 1.22 | D9: 1986T2 | E9: =AVERAGE(OFFSET($B$386,(C387-1)*3,0,3,1)) -> 6.92
A10: 19968 | B10: =fedfunds!B10 -> 1.06 | D10: 1986T3 | E10: =AVERAGE(OFFSET($B$386,(C388-1)*3,0,3,1)) -> 6.2066667
A11: 19998 | B11: =fedfunds!B11 -> 0.85 | D11: 1986T4 | E11: =AVERAGE(OFFSET($B$386,(C389-1)*3,0,3,1)) -> 6.2666667
A12: 20029 | B12: =fedfunds!B12 -> 0.83 | D12: 1987T1 | E12: =AVERAGE(OFFSET($B$386,(C390-1)*3,0,3,1)) -> 6.22
A13: 20059 | B13: =fedfunds!B13 -> 1.28 | D13: 1987T2 | E13: =AVERAGE(OFFSET($B$386,(C391-1)*3,0,3,1)) -> 6.65
A14: 20090 | B14: =fedfunds!B14 -> 1.39 | D14: 1987T3 | E14: =AVERAGE(OFFSET($B$386,(C392-1)*3,0,3,1)) -> 6.8433333
A15: 20121 | B15: =fedfunds!B15 -> 1.29 | D15: 1987T4 | E15: =AVERAGE(OFFSET($B$386,(C393-1)*3,0,3,1)) -> 6.9166667
A16: 20149 | B16: =fedfunds!B16 -> 1.35 | D16: 1988T1 | E16: =AVERAGE(OFFSET($B$386,(C394-1)*3,0,3,1)) -> 6.6633333
A17: 20180 | B17: =fedfunds!B17 -> 1.43 | D17: 1988T2 | E17: =AVERAGE(OFFSET($B$386,(C395-1)*3,0,3,1)) -> 7.1566667
A18: 20210 | B18: =fedfunds!B18 -> 1.43 | D18: 1988T3 | E18: =AVERAGE(OFFSET($B$386,(C396-1)*3,0,3,1)) -> 7.9833333
A19: 20241 | B19: =fedfunds!B19 -> 1.64 | D19: 1988T4 | E19: =AVERAGE(OFFSET($B$386,(C397-1)*3,0,3,1)) -> 8.47
... A115: 23163 | B115: =fedfunds!B115 -> 2.99 | D115: 2012T4 | E115: =AVERAGE(OFFSET($B$386,(C493-1)*3,0,3,1)) -> 0.16
A116: 23193 | B116: =fedfunds!B116 -> 3.02
A117: 23224 | B117: =fedfunds!B117 -> 3.49
A118: 23255 | B118: =fedfunds!B118 -> 3.48
A119: 23285 | B119: =fedfunds!B119 -> 3.5
A120: 23316 | B120: =fedfunds!B120 -> 3.48
A121: 23346 | B121: =fedfunds!B121 -> 3.38
A122: 23377 | B122: =fedfunds!B122 -> 3.48
A123: 23408 | B123: =fedfunds!B123 -> 3.48
A124: 23437 | B124: =fedfunds!B124 -> 3.43
A125: 23468 | B125: =fedfunds!B125 -> 3.47
A126: 23498 | B126: =fedfunds!B126 -> 3.5
A127: 23529 | B127: =fedfunds!B127 -> 3.5
... A385: 31382 | B385: =fedfunds!B385 -> 8.27
A386: 31413 | B386: =fedfunds!B386 -> 8.14 | C386: 1
A387: 31444 | B387: =fedfunds!B387 -> 7.86 | C387: 2
A388: 31472 | B388: =fedfunds!B388 -> 7.48 | C388: 3
A389: 31503 | B389: =fedfunds!B389 -> 6.99 | C389: 4
A390: 31533 | B390: =fedfunds!B390 -> 6.85 | C390: 5
A391: 31564 | B391: =fedfunds!B391 -> 6.92 | C391: 6
A392: 31594 | B392: =fedfunds!B392 -> 6.56 | C392: 7
A393: 31625 | B393: =fedfunds!B393 -> 6.17 | C393: 8
A394: 31656 | B394: =fedfunds!B394 -> 5.89 | C394: 9
A395: 31686 | B395: =fedfunds!B395 -> 5.85 | C395: 10
A396: 31717 | B396: =fedfunds!B396 -> 6.04 | C396: 11
A397: 31747 | B397: =fedfunds!B397 -> 6.91 | C397: 12
... A710: 41275 | B710: =fedfunds!B710 -> 0.14 | C710: 325

Sheet SalarioResto
B1: Minería | C1: Industria Manufacturera | D1: Electricidad Gas y Agua | E1: Construcción | F1: Comercio | G1: Hoteles y Restaurantes | H1: Transporte y Comunicaciones | I1: Intermediación Financiera | J1: Actividades Inmobiliaria y Empresarial | K1: Administración Pública | L1: Enseñanza | M1: Servicios Sociales y Salud | N1: Otros Servicios Comunitarios y Sociales
A2: ponderadores 2009 | B2: 3.57375 | C2: 16.50973 | D2: 1.382 | E2: 10.88111 | F2: 16.90506 | G2: 2.3165 | H2: 7.1729 | I2: 7.06254 | J2: 16.59242 | K2: 5.6614 | L2: 6.65604 | M2: 3.64955 | N2: 1.637
J3: Alquiler | N3: Personales
A4: 40148 | B4: 1810760 | C4: 687226 | D4: 1260225 | E4: 513577 | F4: 646066 | G4: 345693 | H4: 664623 | I4: 1148823 | J4: 590830 | K4: 942565 | L4: 734621 | M4: 634524 | N4: 590218
B6: MIN | C6: IND | D6: EGA | E6: CONS | F6: COM | H6: TRAN | I6: SFIN | K6: SCOM | P6: CMO RESTO
B7: =+B4 -> 1810760 | C7: =+C4 -> 687226 | D7: =+D4 -> 1260225 | E7: =+E4 -> 513577 | F7: =+SUMPRODUCT(F2:G2,F4:G4)/SUM(F2:G2) -> 609866.33 | H7: =+H4 -> 664623 | I7: =+SUMPRODUCT(I2:J2,I4:J4)/SUM(I2:J2) -> 757427.11 | K7: =+SUMPRODUCT(K2:N2,K4:N4)/SUM(K2:N2) -> 767315.72 | P7: =+(C7*C2+E7*E2+F7*SUM(F2:G2)+H7*H2+I7*SUM(I2:J2)+K7*SUM(K2:N2))/SUM(C2,E2:N2) -> 682300.99
B9: CMO RESTO Nom | C9: CMO Resto en $ | F9: CMO Resto Nom. | G9: CMO Resto Nom. en $ | H9: CMO Resto Nom. SA | I9: CMO Resto Nom. en $ SA
A10: 31413 | B10: =+$M15 -> 0 | C10: =+C11*B10/B11 -> #DIV/0! | D10: 1 | E10: 1986T1 | F10: =AVERAGE(OFFSET($B$10,(D10-1)*3,0,3,1)) -> 0 | G10: =AVERAGE(OFFSET($C$10,(D10-1)*3,0,3,1)) -> #DIV/0! | H10: 7.7125911 | I10: 51654.53
A11: 31444 | B11: =+$M16 -> 0 | C11: =+C12*B11/B12 -> #DIV/0! | D11: 2 | E11: 1986T2 | F11: =AVERAGE(OFFSET($B$10,(D11-1)*3,0,3,1)) -> 0 | G11: =AVERAGE(OFFSET($C$10,(D11-1)*3,0,3,1)) -> #DIV/0! | H11: 8.085441 | I11: 54151.666
A12: 31472 | B12: =+$M17 -> 0 | C12: =+C13*B12/B13 -> #DIV/0! | D12: 3 | E12: 1986T3 | F12: =AVERAGE(OFFSET($B$10,(D12-1)*3,0,3,1)) -> 0 | G12: =AVERAGE(OFFSET($C$10,(D12-1)*3,0,3,1)) -> #DIV/0! | H12: 8.3900272 | I12: 56191.61
A13: 31503 | B13: =+$M18 -> 0 | C13: =+C14*B13/B14 -> #DIV/0! | D13: 4 | E13: 1986T4 | F13: =AVERAGE(OFFSET($B$10,(D13-1)*3,0,3,1)) -> 0 | G13: =AVERAGE(OFFSET($C$10,(D13-1)*3,0,3,1)) -> #DIV/0! | H13: 8.8195389 | I13: 59068.234
A14: 31533 | B14: =+$M19 -> 0 | C14: =+C15*B14/B15 -> #DIV/0! | D14: 5 | E14: 1987T1 | F14: =AVERAGE(OFFSET($B$10,(D14-1)*3,0,3,1)) -> 0 | G14: =AVERAGE(OFFSET($C$10,(D14-1)*3,0,3,1)) -> #DIV/0! | H14: 9.1349101 | I14: 61180.41
A15: 31564 | B15: =+$M20 -> 0 | C15: =+C16*B15/B16 -> #DIV/0! | D15: 6 | E15: 1987T2 | F15: =AVERAGE(OFFSET($B$10,(D15-1)*3,0,3,1)) -> 0 | G15: =AVERAGE(OFFSET($C$10,(D15-1)*3,0,3,1)) -> #DIV/0! | H15: 9.49579 | I15: 63597.378
A16: 31594 | B16: =+$M21 -> 0 | C16: =+C17*B16/B17 -> #DIV/0! | D16: 7 | E16: 1987T3 | F16: =AVERAGE(OFFSET($B$10,(D16-1)*3,0,3,1)) -> 0 | G16: =AVERAGE(OFFSET($C$10,(D16-1)*3,0,3,1)) -> #DIV/0! | H16: 10.039106 | I16: 67236.197
A17: 31625 | B17: =+$M22 -> 0 | C17: =+C18*B17/B18 -> #DIV/0! | D17: 8 | E17: 1987T4 | F17: =AVERAGE(OFFSET($B$10,(D17-1)*3,0,3,1)) -> 0 | G17: =AVERAGE(OFFSET($C$10,(D17-1)*3,0,3,1)) -> #DIV/0! | H17: 10.626293 | I17: 71168.839
A18: 31656 | B18: =+$M23 -> 0 | C18: =+C19*B18/B19 -> #DIV/0! | D18: 9 | E18: 1988T1 | F18: =AVERAGE(OFFSET($B$10,(D18-1)*3,0,3,1)) -> 0 | G18: =AVERAGE(OFFSET($C$10,(D18-1)*3,0,3,1)) -> #DIV/0! | H18: 11.183113 | I18: 74898.101
A19: 31686 | B19: =+$M24 -> 0 | C19: =+C20*B19/B20 -> #DIV/0! | D19: 10 | E19: 1988T2 | F19: =AVERAGE(OFFSET($B$10,(D19-1)*3,0,3,1)) -> 0 | G19: =AVERAGE(OFFSET($C$10,(D19-1)*3,0,3,1)) -> #DIV/0! | H19: 11.802899 | I19: 79049.075
A20: 31717 | B20: =+$M25 -> 0 | C20: =+C21*B20/B21 -> #DIV/0! | D20: 11 | E20: 1988T3 | F20: =AVERAGE(OFFSET($B$10,(D20-1)*3,0,3,1)) -> 0 | G20: =AVERAGE(OFFSET($C$10,(D20-1)*3,0,3,1)) -> #DIV/0! | H20: 12.555957 | I20: 84092.626
A21: 31747 | B21: =+$M26 -> 0 | C21: =+C22*B21/B22 -> #DIV/0! | D21: 12 | E21: 1988T4 | F21: =AVERAGE(OFFSET($B$10,(D21-1)*3,0,3,1)) -> 0 | G21: =AVERAGE(OFFSET($C$10,(D21-1)*3,0,3,1)) -> #DIV/0! | H21: 12.85543 | I21: 86098.325
... A117: 34669 | B117: =+$M122 -> 0 | C117: =+C118*B117/B118 -> #DIV/0! | D117: 108 | E117: 2012T4 | F117: =AVERAGE(OFFSET($B$10,(D117-1)*3,0,3,1)) -> 0 | G117: =AVERAGE(OFFSET($C$10,(D117-1)*3,0,3,1)) -> #DIV/0! | H117: 122.43832 | I117: 820021.93
A118: 34700 | B118: =+$M123 -> 0 | C118: =+C119*B118/B119 -> #DIV/0! | D118: 109
A119: 34731 | B119: =+$M124 -> 0 | C119: =+C120*B119/B120 -> #DIV/0! | D119: 110
A120: 34759 | B120: =+$M125 -> 0 | C120: =+C121*B120/B121 -> #DIV/0! | D120: 111
A121: 34790 | B121: =+$M126 -> 0 | C121: =+C122*B121/B122 -> #DIV/0! | D121: 112
A122: 34820 | B122: =+$M127 -> 0 | C122: =+C123*B122/B123 -> #DIV/0! | D122: 113
A123: 34851 | B123: =+$M128 -> 0 | C123: =+C124*B123/B124 -> #DIV/0! | D123: 114
A124: 34881 | B124: =+$M129 -> 0 | C124: =+C125*B124/B125 -> #DIV/0! | D124: 115
A125: 34912 | B125: =+$M130 -> 0 | C125: =+C126*B125/B126 -> #DIV/0! | D125: 116
A126: 34943 | B126: =+$M131 -> 0 | C126: =+C127*B126/B127 -> #DIV/0! | D126: 117
A127: 34973 | B127: =+$M132 -> 0 | C127: =+C128*B127/B128 -> #DIV/0! | D127: 118
A128: 35004 | B128: =+$M133 -> 0 | C128: =+C129*B128/B129 -> #DIV/0! | D128: 119
A129: 35034 | B129: =+$M134 -> 0 | C129: =+C130*B129/B130 -> #DIV/0! | D129: 120
... A296: 40118 | B296: =+$M301 -> 0 | C296: =+C297*B296/B297 -> #DIV/0! | D296: 287
A297: 40148 | B297: =+$M302 -> 0 | C297: =P7 -> 682300.99 | D297: 288
A298: 40179 | B298: =+$M303 -> 0 | C298: =+C297*B298/B297 -> #DIV/0! | D298: 289
A299: 40210 | B299: =+$M304 -> 0 | C299: =+C298*B299/B298 -> #DIV/0! | D299: 290
A300: 40238 | B300: =+$M305 -> 0 | C300: =+C299*B300/B299 -> #DIV/0! | D300: 291
A301: 40269 | B301: =+$M306 -> 0 | C301: =+C300*B301/B300 -> #DIV/0! | D301: 292
A302: 40299 | B302: =+$M307 -> 0 | C302: =+C301*B302/B301 -> #DIV/0! | D302: 293
A303: 40330 | B303: =+$M308 -> 0 | C303: =+C302*B303/B302 -> #DIV/0! | D303: 294
A304: 40360 | B304: =+$M309 -> 0 | C304: =+C303*B304/B303 -> #DIV/0! | D304: 295
A305: 40391 | B305: =+$M310 -> 0 | C305: =+C304*B305/B304 -> #DIV/0! | D305: 296
A306: 40422 | B306: =+$M311 -> 0 | C306: =+C305*B306/B305 -> #DIV/0! | D306: 297
A307: 40452 | B307: =+$M312 -> 0 | C307: =+C306*B307/B306 -> #DIV/0! | D307: 298
A308: 40483 | B308: =+$M313 -> 0 | C308: =+C307*B308/B307 -> #DIV/0! | D308: 299
A309: 40513 | B309: =+$M314 -> 0 | C309: =+C308*B309/B308 -> #DIV/0! | D309: 300
... A333: 41244 | B333: =+$M338 -> 0 | C333: =+C332*B333/B332 -> #DIV/0! | D333: 324

Sheet Notas_RTranamil
A1: Autor: | B1: Rodrigo Tranamil
A2: Última
A3: Modificación: | B3: 42247
A5: La base de datos principal es la que se encuentra en la hoja "DatosVinculos", la cual contiene series construidas desde 1986q1 hasta 2014q4. (Ver "Notas_CPerez" para información sobre la base de datos anterior 1986q1 hasta 2014q4).
A6: En su mayoría corresponden a datos efectivos, de lo contrario se destaca el contenido de la celda con letra roja, la explicación de los datos construidos se encuentra en las Notas. (Además ver "Notas_Cperez")
A7: La hoja "DatosSinVinculos" corresponde a la base consolidada sin vinculos.
A9: Notas adicionales a "Notas_CPerez":
A10: 1) La serie IPC fue construdia a partir de los datos extraídos de la Base Siete. Se tomó la serie mensual IPC base 2013=100 y se empalmó hacia atrás utilizando la variación mensual del IPC base 2008=100. Luego, se usó el promedio como método de agregación para que la serie tenga frecuencia trimestral.
A11: 2) Las series PIB Resto, PIB RRNN, PIB Minería son extraídas de la base de datos de la GAM.
A12: 3) La serie PIB Minería del Cobre es extraída de la base de datos de la GAM pero tiene datos efectivos desde 1996q1. Hacia atrás se realiza un empalme de variación anual respecto a la serie PIB Minería.
A13: 4) La serie Consumo Total, Consumo de Gobierno, Consumo Privado son extraídos de la base de datos de la GAM pero tiene datos efectivos desde 1996q1. Hacia atrás se realiza un empalme de variación anual respecto a una serie de Consumo y sus desagregados entregada por el DAC.
A14: 5) La serie IREM y sus desagregados son estraídos de la base de datos de la GAM.
A15: 6) La serie CMO y sus desagregados son estraídos de la base de datos de la GAM.
A16: 7) La serie Empleo y sus desagregados son estraídos de la base de datos de la GAM.
A17: 8) La serie TPM nominal se extrae desde la base siete con datos efectivos a partir de 1995q2.
A18: 9) En esta versión, se agregan las variables horas y desempleo como observables.

Sheet DatosVinculos
A1: Nombre Largo | B1: PIB Real | C1: PIB Real SA | D1: PIB Nominal | E1: PIB Resto Real | F1: PIB Resto Real SA | G1: PIB RRNN Real | H1: PIB RRNN Real SA | I1: PIB Minería Real | J1: PIB Minería Real SA | K1: PIB Minería del Cobre Real | L1: PIB Minería del Cobre Real SA | M1: Consumo Total | N1: Consumo Total SA | O1: Consumo de Gobierno | P1: Consumo de Gobierno SA | Q1: Consumo Privado | R1: Consumo Privado SA | S1: Consumo Durable | T1: Consumo Durable SA | U1: Consumo Habitual | V1: Consumo Habitual SA | W1: FBCF Real | X1: FBCF Real SA | Y1: Balanza Comercial Nominal | Z1: Balanza Comercial Real | AA1: Cuenta Corriente | AB1: IPC | AC1: IPC SA | AD1: IPCSAE | AE1: IPCSAE SA | AF1: IPCSAE Bienes | AG1: IPCSAE Bienes SA | AH1: IPCSAE Servicios | AI1: IPCSAE Servicios SA | AJ1: Meta IPC | AK1: Meta IPC 2 | AL1: TPM Nominal | AM1: TCR | AN1: TCN | AO1: Precio Cobre Nominal | AP1: Precio Petróleo WTI | AQ1: IPE | AR1: PIB Externo Real | AS1: Libor | AT1: FED Funds | AU1: EMBI Chile | AV1: EMBI Chile 2 | AW1: TDI | AX1: CMO Total Real | AY1: CMO Total Real SA | AZ1: CMO Total Real en Pesos | BA1: CMO Total Real en Pesos SA | BB1: CMO Total Nom. | BC1: CMO Total Nom. SA | BD1: CMO Total Nom. en Pesos | BE1: CMO Total Nom. en Pesos SA | BF1: CMO Real Resto | BG1: CMO Real Resto SA | BH1: CMO Real Resto en Pesos | BI1: CMO Real Resto en Pesos SA | BJ1: CMO Nom. Resto | BK1: CMO Nom. Resto SA | BL1: CMO Nom. Resto en Pesos | BM1: CMO Nom. Resto en Pesos SA | BN1: IREM Total Real | BO1: IREM Total Real SA | BP1: IREM Total Real en Pesos | BQ1: IREM Total Real en Pesos SA | BR1: IREM Total Nom. | BS1: IREM Total Nom. SA | BT1: IREM Total Nom. en Pesos | BU1: IREM Total Nom. en Pesos SA | BV1: IREM MINERÍA Real | BW1: IREM MINERÍA Real SA | BX1: IREM MINERÍA Real en Pesos | BY1: IREM MINERÍA Real en Pesos SA | BZ1: IREM MINERÍA Nom. | CA1: IREM MINERÍA Nom. SA | CB1: IREM MINERÍA Nom. en Pesos | CC1: IREM MINERÍA Nom. en Pesos SA | CD1: IREM RESTO Real | CE1: IREM RESTO Real SA | CF1: IREM RESTO Real en Pesos | CG1: IREM RESTO Real en Pesos SA | CH1: IREM RESTO Nom. | CI1: IREM RESTO Nom. SA | CJ1: IREM RESTO Nom. en Pesos | CK1: IREM RESTO Nom. en Pesos SA | CL1: Empleo Total | CM1: Empleo Total SA | CN1: Empleo Minería | CO1: Empleo Minería SA | CP1: Horas Total | CQ1: Horas Total SA | CR1: Horas Minería | CS1: Horas Minería SA | CT1: Empleo Total Resto | CU1: Empleo Total Resto SA | CV1: Horas Resto | CW1: Horas Resto SA | CX1: Población > 15 años | CY1: Fuerza de Trabajo Total | CZ1: Fuerza de Trabajo Total SA | DA1: Tasa Desempleo | DB1: Tasa Desempleo SA | DC1: Tasa vacantes | DD1: Tasa Vacantes SA
A2: Unidad | B2: Mill. $ | C2: Mill. $ | D2: Mill. $ | E2: Mill. $ | F2: Mill. $ | G2: Mill. $ | H2: Mill. $ | I2: Mill. $ | J2: Mill. $ | K2: Mill. $ | L2: Mill. $ | M2: Mill. $ | N2: Mill. $ | O2: Mill. $ | P2: Mill. $ | Q2: Mill. $ | R2: Mill. $ | S2: Mill. $ | T2: Mill. $ | U2: Mill. $ | V2: Mill. $ | W2: Mill. $ | X2: Mill. $ | Y2: Mill. $ | Z2: Mill. $ | AA2: Mill. US $ | AB2: Índice | AC2: Índice | AD2: Índice | AE2: Índice | AF2: Índice | AG2: Índice | AH2: Índice | AI2: Índice | AJ2: Índice | AK2: Índice | AL2: Índice | AM2: Índice | AN2: Índice | AO2: USD/libra | AP2: USD/Barril | AQ2: Índice | AR2: Índice | AS2: Tasa, 3 meses | AT2: Tasa | AU2: Índice | AV2: Índice | AW2: Índice | AX2: Índice | AY2: Índice | AZ2: Pesos | BA2: Pesos | BB2: Índice | BC2: Índice | BD2: Pesos | BE2: Pesos | BF2: Índice | BG2: Índice | BH2: Pesos | BI2: Pesos | BJ2: Índice | BK2: Índice | BL2: Pesos | BM2: Pesos | BN2: Índice | BO2: Índice | BP2: Pesos | BQ2: Pesos | BR2: Índice | BS2: Índice | BT2: Pesos | BU2: Pesos | BV2: Índice | BW2: Índice | BX2: Pesos | BY2: Pesos | BZ2: Índice | CA2: Índice | CB2: Pesos | CC2: Pesos | CD2: Índice | CE2: Índice | CF2: Pesos | CG2: Pesos | CH2: Índice | CI2: Índice | CJ2: Pesos | CK2: Pesos | CL2: miles de personas | CM2: miles de personas | CN2: miles de personas | CO2: miles de personas | CP2: Horas semanales | CQ2: Horas semanales | CR2: Horas semanales | CS2: Horas semanales | CT2: miles de personas | CU2: miles de personas | CV2: Horas semanales | CW2: Horas semanales | CX2: miles de personas | CY2: miles de personas | CZ2: Unidades | DA2: Tasa | DB2: Tasa | DC2: Tasa | DD2: Tasa
A3: Origen datos | B3: GAM | C3: Propio | D3: GAM | E3: GAM | F3: Propio | G3: GAM | H3: Propio | I3: GAM | J3: Propio | K3: GAM | L3: Propio | M3: GAM | N3: Propio | O3: GAM | P3: Propio | Q3: GAM | R3: Propio | S3: GAM | T3: Propio | U3: GAM | V3: Propio | W3: GAM | X3: Propio | Y3: B7/CC.NN | Z3: B7/CC.NN | AA3: B7/CC.NN | AB3: INE/DAC | AC3: Propio | AD3: INE/DAC | AE3: Propio | AF3: INE/DAC | AG3: Propio | AH3: INE/DAC | AI3: Propio | AJ3: CC.NN. | AK3: CC.NN. | AL3: DMP/B7 | AM3: B7 | AN3: B7 | AO3: B7 | AP3: B7 | AQ3: B7 | AR3: DMP | AS3: B7 | AT3: FRED | AU3: GAM/B7 | AV3: GAM/B7 | AW3: DMP/B7 | AX3: Propio | AY3: Propio | AZ3: Propio | BA3: Propio | BB3: GAM | BC3: Propio | BD3: Propio | BE3: Propio | BF3: Propio | BG3: Propio | BH3: Propio | BI3: Propio | BJ3: GAM | BK3: Propio | BL3: Propio | BM3: Propio | BN3: INE/DAC | BO3: Propio | BP3: INE/DAC | BQ3: Propio | BR3: INE/DAC | BS3: Propio | BT3: INE/DAC | BU3: Propio | BV3: INE/DAC | BW3: Propio | BX3: INE/DAC | BY3: Propio | BZ3: INE/DAC | CA3: Propio | CB3: INE/DAC | CC3: Propio | CD3: INE/DAC | CE3: Propio | CF3: INE/DAC | CG3: Propio | CH3: INE/DAC | CI3: Propio | CJ3: INE/DAC | CK3: Propio | CL3: GAM | CM3: Propio | CN3: GAM | CO3: Propio | CP3: GAM | CQ3: Propio | CR3: GAM | CS3: Propio | CT3: GAM | CU3: Propio | CV3: GAM | CW3: Propio | CX3: GAM | CY3: GAM | CZ3: Propio | DA3: GAM | DB3: Propio | DC3: GAM | DD3: Propio
A4: Acceso | B4: Pública | D4: Pública | E4: No Público | G4: No Público | I4: Pública | K4: Pública | M4: No Público | O4: Pública | Q4: Pública | S4: Pública | U4: Pública | W4: Pública | Y4: Pública | Z4: Pública | AA4: Pública | AB4: Pública | AD4: Pública | AF4: No Pública | AH4: No Pública | AJ4: No Pública | AK4: Pública | AL4: Pública | AM4: Pública | AN4: Pública | AO4: Pública | AP4: Pública | AQ4: Pública | AR4: Pública | AS4: Pública | AT4: Pública | AU4: No Pública | AV4: Pública | AW4: Pública | AX4: Pública | AZ4: Pública | BB4: Pública | BD4: Pública | BF4: Pública | BH4: Pública | BJ4: Pública | BL4: Pública | BN4: Pública | BP4: Pública | BR4: Pública | BT4: Pública | BV4: Pública | BX4: Pública | BZ4: Pública | CB4: Pública | CD4: Pública | CF4: Pública | CH4: Pública | CJ4: Pública | CL4: Pública | CN4: Pública | CP4: Pública | CR4: Pública | CT4: Pública | CV4: Pública | CX4: Pública | CY4: Pública | DA4: Pública | DC4: Pública
A5: Fecha actualización | B5: 42572 | C5: 42572 | D5: 42572 | E5: 42572 | F5: 42572 | G5: 42572 | H5: 42572 | I5: 42572 | J5: 42572 | K5: 42572 | L5: 42572 | M5: 42572 | N5: 42572 | O5: 42572 | P5: 42572 | Q5: 42572 | R5: 42572 | S5: 42572 | T5: 42572 | U5: 42572 | V5: 42572 | W5: 42572 | X5: 42572 | Y5: 42572 | Z5: 42572 | AA5: 42572 | AB5: 42572 | AC5: 42572 | AD5: 42572 | AE5: 42572 | AF5: 42572 | AG5: 42572 | AH5: 42572 | AI5: 42572 | AJ5: 42572 | AK5: 42572 | AL5: 42572 | AM5: 42572 | AN5: 42572 | AO5: 42572 | AP5: 42572 | AQ5: 42572 | AR5: 42572 | AS5: 42572 | AT5: 42572 | AU5: 42572 | AV5: 42572 | AW5: 42572 | AX5: 42572 | AY5: 42572 | AZ5: 42572 | BA5: 42572 | BB5: 42572 | BC5: 42572 | BD5: 42572 | BE5: 42572 | BF5: 42572 | BG5: 42572 | BH5: 42572 | BI5: 42572 | BJ5: 42572 | BK5: 42572 | BL5: 42572 | BM5: 42572 | BN5: 42572 | BO5: 42572 | BP5: 42572 | BQ5: 42572 | BR5: 42572 | BS5: 42572 | BT5: 42572 | BU5: 42572 | BV5: 42572 | BW5: 42572 | BX5: 42572 | BY5: 42572 | BZ5: 42572 | CA5: 42572 | CB5: 42572 | CC5: 42572 | CD5: 42572 | CE5: 42572 | CF5: 42572 | CG5: 42572 | CH5: 42572 | CI5: 42572 | CJ5: 42572 | CK5: 42572 | CL5: 42572 | CM5: 42572 | CN5: 42572 | CO5: 42572 | CP5: 42572 | CQ5: 42572 | CR5: 42572 | CS5: 42572 | CT5: 42572 | CU5: 42572 | CV5: 42572 | CW5: 42572 | CX5: 42572 | CY5: 42572 | CZ5: 42572 | DA5: 42572 | DB5: 42572 | DC5: 42572 | DD5: 42572
A6: Ult. Dato Efectivo | B6: 2016T1 | C6: 2016T1 | D6: 2016T1 | E6: 2016T1 | F6: 2016T1 | G6: 2016T1 | H6: 2016T1 | I6: 2016T1 | J6: 2016T1 | K6: 2016T1 | L6: 2016T1 | M6: 2016T1 | N6: 2016T1 | O6: 2016T1 | P6: 2016T1 | Q6: 2016T1 | R6: 2016T1 | S6: 2016T1 | T6: 2016T1 | U6: 2016T1 | V6: 2016T1 | W6: 2016T1 | X6: 2016T1 | Y6: 2016T1 | Z6: 2016T1 | AA6: 2016T1 | AB6: 2016T1 | AC6: 2016T1 | AD6: 2016T1 | AE6: 2016T1 | AF6: 2016T1 | AG6: 2016T1 | AH6: 2016T1 | AI6: 2016T1 | AJ6: 2016T1 | AK6: 2016T1 | AL6: 2016T1 | AM6: 2016T1 | AN6: 2016T1 | AO6: 2016T1 | AP6: 2016T1 | AQ6: 2016T1 | AR6: 2016T1 | AS6: 2016T1 | AT6: 2016T1 | AU6: 2016T1 | AV6: 2016T1 | AW6: 2016T1 | AX6: 2016T1 | AY6: 2016T1 | AZ6: 2016T1 | BA6: 2016T1 | BB6: 2016T1 | BC6: 2016T1 | BD6: 2016T1 | BE6: 2016T1 | BF6: 2016T1 | BG6: 2016T1 | BH6: 2016T1 | BI6: 2016T1 | BJ6: 2016T1 | BK6: 2016T1 | BL6: 2016T1 | BM6: 2016T1 | BN6: 2016T1 | BO6: 2016T1 | BP6: 2016T1 | BQ6: 2016T1 | BR6: 2016T1 | BS6: 2016T1 | BT6: 2016T1 | BU6: 2016T1 | BV6: 2016T1 | BW6: 2016T1 | BX6: 2016T1 | BY6: 2016T1 | BZ6: 2016T1 | CA6: 2016T1 | CB6: 2016T1 | CC6: 2016T1 | CD6: 2016T1 | CE6: 2016T1 | CF6: 2016T1 | CG6: 2016T1 | CH6: 2016T1 | CI6: 2016T1 | CJ6: 2016T1 | CK6: 2016T1 | CL6: 2016T1 | CM6: 2016T1 | CN6: 2016T1 | CO6: 2016T1 | CP6: 2016T1 | CQ6: 2016T1 | CR6: 2016T1 | CS6: 2016T1 | CT6: 2016T1 | CU6: 2016T1 | CV6: 2016T1 | CW6: 2016T1 | CX6: 2016T1 | CY6: 2016T1 | CZ6: 2016T1 | DA6: 2016T1 | DB6: 2016T1 | DC6: 2016T1 | DD6: 2016T1
A7: 1986T1 | B7: =HLOOKUP(B$1,[5]DatosVinculos!$B$1:$DH$127,$DF7,FALSE) -> 6597579.2 | C7: =HLOOKUP(C$1,[5]DatosVinculos!$B$1:$DH$127,$DF7,FALSE) -> 6586781.3 | D7: =HLOOKUP(D$1,[5]DatosVinculos!$B$1:$DH$127,$DF7,FALSE) -> 226339.71 | E7: =HLOOKUP(E$1,[5]DatosVinculos!$B$1:$DH$127,$DF7,FALSE) -> 5008334.3 | F7: =HLOOKUP(F$1,[5]DatosVinculos!$B$1:$DH$127,$DF7,FALSE) -> 4792721 | G7: =HLOOKUP(G$1,[5]DatosVinculos!$B$1:$DH$127,$DF7,FALSE) -> 1552179.2 | H7: =HLOOKUP(H$1,[5]DatosVinculos!$B$1:$DH$127,$DF7,FALSE) -> 1662532.2 | I7: =HLOOKUP(I$1,[5]DatosVinculos!$B$1:$DH$127,$DF7,FALSE) -> 1291807 | ... DD7: =HLOOKUP(DD$1,[5]DatosVinculos!$B$1:$DH$127,$DF7,FALSE) -> 1.1529623 | DF7: 7
A8: 1986T2 | B8: =HLOOKUP(B$1,[5]DatosVinculos!$B$1:$DH$127,$DF8,FALSE) -> 6932888.5 | C8: =HLOOKUP(C$1,[5]DatosVinculos!$B$1:$DH$127,$DF8,FALSE) -> 6867057.2 | D8: =HLOOKUP(D$1,[5]DatosVinculos!$B$1:$DH$127,$DF8,FALSE) -> 227443.88 | E8: =HLOOKUP(E$1,[5]DatosVinculos!$B$1:$DH$127,$DF8,FALSE) -> 5080417.1 | F8: =HLOOKUP(F$1,[5]DatosVinculos!$B$1:$DH$127,$DF8,FALSE) -> 5037438.2 | G8: =HLOOKUP(G$1,[5]DatosVinculos!$B$1:$DH$127,$DF8,FALSE) -> 1732906.2 | H8: =HLOOKUP(H$1,[5]DatosVinculos!$B$1:$DH$127,$DF8,FALSE) -> 1667568.6 | I8: =HLOOKUP(I$1,[5]DatosVinculos!$B$1:$DH$127,$DF8,FALSE) -> 1381416.4 | ... DD8: =HLOOKUP(DD$1,[5]DatosVinculos!$B$1:$DH$127,$DF8,FALSE) -> 1.227143 | DF8: 8
A9: 1986T3 | B9: =HLOOKUP(B$1,[5]DatosVinculos!$B$1:$DH$127,$DF9,FALSE) -> 6825215.5 | C9: =HLOOKUP(C$1,[5]DatosVinculos!$B$1:$DH$127,$DF9,FALSE) -> 7007356.7 | D9: =HLOOKUP(D$1,[5]DatosVinculos!$B$1:$DH$127,$DF9,FALSE) -> 229020.71 | E9: =HLOOKUP(E$1,[5]DatosVinculos!$B$1:$DH$127,$DF9,FALSE) -> 4845933 | F9: =HLOOKUP(F$1,[5]DatosVinculos!$B$1:$DH$127,$DF9,FALSE) -> 5113008 | G9: =HLOOKUP(G$1,[5]DatosVinculos!$B$1:$DH$127,$DF9,FALSE) -> 1733732.7 | H9: =HLOOKUP(H$1,[5]DatosVinculos!$B$1:$DH$127,$DF9,FALSE) -> 1703619.4 | I9: =HLOOKUP(I$1,[5]DatosVinculos!$B$1:$DH$127,$DF9,FALSE) -> 1389412.8 | ... DD9: =HLOOKUP(DD$1,[5]DatosVinculos!$B$1:$DH$127,$DF9,FALSE) -> 1.1776982 | DF9: 9
A10: 1986T4 | B10: =HLOOKUP(B$1,[5]DatosVinculos!$B$1:$DH$127,$DF10,FALSE) -> 7251292.1 | C10: =HLOOKUP(C$1,[5]DatosVinculos!$B$1:$DH$127,$DF10,FALSE) -> 7149515.2 | D10: =HLOOKUP(D$1,[5]DatosVinculos!$B$1:$DH$127,$DF10,FALSE) -> 229910.33 | E10: =HLOOKUP(E$1,[5]DatosVinculos!$B$1:$DH$127,$DF10,FALSE) -> 5251839.4 | F10: =HLOOKUP(F$1,[5]DatosVinculos!$B$1:$DH$127,$DF10,FALSE) -> 5264111.8 | G10: =HLOOKUP(G$1,[5]DatosVinculos!$B$1:$DH$127,$DF10,FALSE) -> 1680204.6 | H10: =HLOOKUP(H$1,[5]DatosVinculos!$B$1:$DH$127,$DF10,FALSE) -> 1664716.2 | I10: =HLOOKUP(I$1,[5]DatosVinculos!$B$1:$DH$127,$DF10,FALSE) -> 1417365 | ... DD10: =HLOOKUP(DD$1,[5]DatosVinculos!$B$1:$DH$127,$DF10,FALSE) -> 1.1057671 | DF10: 10
A11: 1987T1 | B11: =HLOOKUP(B$1,[5]DatosVinculos!$B$1:$DH$127,$DF11,FALSE) -> 7227526.9 | C11: =HLOOKUP(C$1,[5]DatosVinculos!$B$1:$DH$127,$DF11,FALSE) -> 7210289.2 | D11: =HLOOKUP(D$1,[5]DatosVinculos!$B$1:$DH$127,$DF11,FALSE) -> 230737.18 | E11: =HLOOKUP(E$1,[5]DatosVinculos!$B$1:$DH$127,$DF11,FALSE) -> 5503497.1 | F11: =HLOOKUP(F$1,[5]DatosVinculos!$B$1:$DH$127,$DF11,FALSE) -> 5258207.6 | G11: =HLOOKUP(G$1,[5]DatosVinculos!$B$1:$DH$127,$DF11,FALSE) -> 1569938.1 | H11: =HLOOKUP(H$1,[5]DatosVinculos!$B$1:$DH$127,$DF11,FALSE) -> 1680997.1 | I11: =HLOOKUP(I$1,[5]DatosVinculos!$B$1:$DH$127,$DF11,FALSE) -> 1286272.1 | ... DD11: =HLOOKUP(DD$1,[5]DatosVinculos!$B$1:$DH$127,$DF11,FALSE) -> 1.1226604 | DF11: 11
A12: 1987T2 | B12: =HLOOKUP(B$1,[5]DatosVinculos!$B$1:$DH$127,$DF12,FALSE) -> 7338580.1 | C12: =HLOOKUP(C$1,[5]DatosVinculos!$B$1:$DH$127,$DF12,FALSE) -> 7269897.6 | D12: =HLOOKUP(D$1,[5]DatosVinculos!$B$1:$DH$127,$DF12,FALSE) -> 232424.97 | E12: =HLOOKUP(E$1,[5]DatosVinculos!$B$1:$DH$127,$DF12,FALSE) -> 5363312.6 | F12: =HLOOKUP(F$1,[5]DatosVinculos!$B$1:$DH$127,$DF12,FALSE) -> 5322704 | G12: =HLOOKUP(G$1,[5]DatosVinculos!$B$1:$DH$127,$DF12,FALSE) -> 1776766.2 | H12: =HLOOKUP(H$1,[5]DatosVinculos!$B$1:$DH$127,$DF12,FALSE) -> 1708406.2 | I12: =HLOOKUP(I$1,[5]DatosVinculos!$B$1:$DH$127,$DF12,FALSE) -> 1327211.2 | ... DD12: =HLOOKUP(DD$1,[5]DatosVinculos!$B$1:$DH$127,$DF12,FALSE) -> 0.99456502 | DF12: 12
A13: 1987T3 | B13: =HLOOKUP(B$1,[5]DatosVinculos!$B$1:$DH$127,$DF13,FALSE) -> 7211378.5 | C13: =HLOOKUP(C$1,[5]DatosVinculos!$B$1:$DH$127,$DF13,FALSE) -> 7400123.3 | D13: =HLOOKUP(D$1,[5]DatosVinculos!$B$1:$DH$127,$DF13,FALSE) -> 233288.88 | E13: =HLOOKUP(E$1,[5]DatosVinculos!$B$1:$DH$127,$DF13,FALSE) -> 5164856.1 | F13: =HLOOKUP(F$1,[5]DatosVinculos!$B$1:$DH$127,$DF13,FALSE) -> 5441861.6 | G13: =HLOOKUP(G$1,[5]DatosVinculos!$B$1:$DH$127,$DF13,FALSE) -> 1701754 | H13: =HLOOKUP(H$1,[5]DatosVinculos!$B$1:$DH$127,$DF13,FALSE) -> 1674507.8 | I13: =HLOOKUP(I$1,[5]DatosVinculos!$B$1:$DH$127,$DF13,FALSE) -> 1376132.7 | ... DD13: =HLOOKUP(DD$1,[5]DatosVinculos!$B$1:$DH$127,$DF13,FALSE) -> 1.0752334 | DF13: 13
A14: 1987T4 | B14: =HLOOKUP(B$1,[5]DatosVinculos!$B$1:$DH$127,$DF14,FALSE) -> 7617189.5 | C14: =HLOOKUP(C$1,[5]DatosVinculos!$B$1:$DH$127,$DF14,FALSE) -> 7524887.3 | D14: =HLOOKUP(D$1,[5]DatosVinculos!$B$1:$DH$127,$DF14,FALSE) -> 233715.47 | E14: =HLOOKUP(E$1,[5]DatosVinculos!$B$1:$DH$127,$DF14,FALSE) -> 5498923.3 | F14: =HLOOKUP(F$1,[5]DatosVinculos!$B$1:$DH$127,$DF14,FALSE) -> 5529010.3 | G14: =HLOOKUP(G$1,[5]DatosVinculos!$B$1:$DH$127,$DF14,FALSE) -> 1756128.8 | H14: =HLOOKUP(H$1,[5]DatosVinculos!$B$1:$DH$127,$DF14,FALSE) -> 1742706.1 | I14: =HLOOKUP(I$1,[5]DatosVinculos!$B$1:$DH$127,$DF14,FALSE) -> 1474700.7 | ... DD14: =HLOOKUP(DD$1,[5]DatosVinculos!$B$1:$DH$127,$DF14,FALSE) -> 1.1088704 | DF14: 14
A15: 1988T1 | B15: =HLOOKUP(B$1,[5]DatosVinculos!$B$1:$DH$127,$DF15,FALSE) -> 7734653.2 | C15: =HLOOKUP(C$1,[5]DatosVinculos!$B$1:$DH$127,$DF15,FALSE) -> 7702652.6 | D15: =HLOOKUP(D$1,[5]DatosVinculos!$B$1:$DH$127,$DF15,FALSE) -> 234228.29 | E15: =HLOOKUP(E$1,[5]DatosVinculos!$B$1:$DH$127,$DF15,FALSE) -> 5933955.5 | F15: =HLOOKUP(F$1,[5]DatosVinculos!$B$1:$DH$127,$DF15,FALSE) -> 5654168.5 | G15: =HLOOKUP(G$1,[5]DatosVinculos!$B$1:$DH$127,$DF15,FALSE) -> 1648862 | H15: =HLOOKUP(H$1,[5]DatosVinculos!$B$1:$DH$127,$DF15,FALSE) -> 1758037.8 | I15: =HLOOKUP(I$1,[5]DatosVinculos!$B$1:$DH$127,$DF15,FALSE) -> 1339057.6 | ... DD15: =HLOOKUP(DD$1,[5]DatosVinculos!$B$1:$DH$127,$DF15,FALSE) -> 1.1556967 | DF15: 15
A16: 1988T2 | B16: =HLOOKUP(B$1,[5]DatosVinculos!$B$1:$DH$127,$DF16,FALSE) -> 7689730.3 | C16: =HLOOKUP(C$1,[5]DatosVinculos!$B$1:$DH$127,$DF16,FALSE) -> 7615188.9 | D16: =HLOOKUP(D$1,[5]DatosVinculos!$B$1:$DH$127,$DF16,FALSE) -> 233778.19 | E16: =HLOOKUP(E$1,[5]DatosVinculos!$B$1:$DH$127,$DF16,FALSE) -> 5647761.5 | F16: =HLOOKUP(F$1,[5]DatosVinculos!$B$1:$DH$127,$DF16,FALSE) -> 5606819.9 | G16: =HLOOKUP(G$1,[5]DatosVinculos!$B$1:$DH$127,$DF16,FALSE) -> 1787290.3 | H16: =HLOOKUP(H$1,[5]DatosVinculos!$B$1:$DH$127,$DF16,FALSE) -> 1719740.1 | I16: =HLOOKUP(I$1,[5]DatosVinculos!$B$1:$DH$127,$DF16,FALSE) -> 1384666.8 | ... DD16: =HLOOKUP(DD$1,[5]DatosVinculos!$B$1:$DH$127,$DF16,FALSE) -> 1.2641645 | DF16: 16
A17: 1988T3 | B17: =HLOOKUP(B$1,[5]DatosVinculos!$B$1:$DH$127,$DF17,FALSE) -> 7808703.9 | C17: =HLOOKUP(C$1,[5]DatosVinculos!$B$1:$DH$127,$DF17,FALSE) -> 8012688.4 | D17: =HLOOKUP(D$1,[5]DatosVinculos!$B$1:$DH$127,$DF17,FALSE) -> 233973.95 | E17: =HLOOKUP(E$1,[5]DatosVinculos!$B$1:$DH$127,$DF17,FALSE) -> 5526479 | F17: =HLOOKUP(F$1,[5]DatosVinculos!$B$1:$DH$127,$DF17,FALSE) -> 5818909.9 | G17: =HLOOKUP(G$1,[5]DatosVinculos!$B$1:$DH$127,$DF17,FALSE) -> 1935117.7 | H17: =HLOOKUP(H$1,[5]DatosVinculos!$B$1:$DH$127,$DF17,FALSE) -> 1904754.1 | I17: =HLOOKUP(I$1,[5]DatosVinculos!$B$1:$DH$127,$DF17,FALSE) -> 1536320.5 | ... DD17: =HLOOKUP(DD$1,[5]DatosVinculos!$B$1:$DH$127,$DF17,FALSE) -> 1.3869881 | DF17: 17
A18: 1988T4 | B18: =HLOOKUP(B$1,[5]DatosVinculos!$B$1:$DH$127,$DF18,FALSE) -> 8321824.4 | C18: =HLOOKUP(C$1,[5]DatosVinculos!$B$1:$DH$127,$DF18,FALSE) -> 8240095.7 | D18: =HLOOKUP(D$1,[5]DatosVinculos!$B$1:$DH$127,$DF18,FALSE) -> 237110.44 | E18: =HLOOKUP(E$1,[5]DatosVinculos!$B$1:$DH$127,$DF18,FALSE) -> 5928371.3 | F18: =HLOOKUP(F$1,[5]DatosVinculos!$B$1:$DH$127,$DF18,FALSE) -> 5975221.5 | G18: =HLOOKUP(G$1,[5]DatosVinculos!$B$1:$DH$127,$DF18,FALSE) -> 1916919.3 | H18: =HLOOKUP(H$1,[5]DatosVinculos!$B$1:$DH$127,$DF18,FALSE) -> 1914316.3 | I18: =HLOOKUP(I$1,[5]DatosVinculos!$B$1:$DH$127,$DF18,FALSE) -> 1635722.1 | ... DD18: =HLOOKUP(DD$1,[5]DatosVinculos!$B$1:$DH$127,$DF18,FALSE) -> 1.3721413 | DF18: 18
... A127: 2016T1 | B127: =HLOOKUP(B$1,[5]DatosVinculos!$B$1:$DH$127,$DF127,FALSE) -> 29669125 | C127: =HLOOKUP(C$1,[5]DatosVinculos!$B$1:$DH$127,$DF127,FALSE) -> 30124246 | D127: =HLOOKUP(D$1,[5]DatosVinculos!$B$1:$DH$127,$DF127,FALSE) -> 41137238 | E127: =HLOOKUP(E$1,[5]DatosVinculos!$B$1:$DH$127,$DF127,FALSE) -> 22571447 | F127: =HLOOKUP(F$1,[5]DatosVinculos!$B$1:$DH$127,$DF127,FALSE) -> 22743686 | G127: =HLOOKUP(G$1,[5]DatosVinculos!$B$1:$DH$127,$DF127,FALSE) -> 4448900 | H127: =HLOOKUP(H$1,[5]DatosVinculos!$B$1:$DH$127,$DF127,FALSE) -> 4672398.1 | I127: =HLOOKUP(I$1,[5]DatosVinculos!$B$1:$DH$127,$DF127,FALSE) -> 3376657.6 | ... DD127: =HLOOKUP(DD$1,[5]DatosVinculos!$B$1:$DH$127,$DF127,FALSE) -> 0.41783971 | DF127: 127

Sheet DatosSinVinculos
A1: Nombre Largo | B1: PIB Real | C1: PIB Real SA | D1: PIB Nominal | E1: PIB Resto Real | F1: PIB Resto Real SA | G1: PIB RRNN Real | H1: PIB RRNN Real SA | I1: PIB Minería Real | J1: PIB Minería Real SA | K1: PIB Minería del Cobre Real | L1: PIB Minería del Cobre Real SA | M1: Consumo Total | N1: Consumo Total SA | O1: Consumo de Gobierno | P1: Consumo de Gobierno SA | Q1: Consumo Privado | R1: Consumo Privado SA | S1: Consumo Durable | T1: Consumo Durable SA | U1: Consumo Habitual | V1: Consumo Habitual SA | W1: FBCF Real | X1: FBCF Real SA | Y1: Balanza Comercial Nominal | Z1: Balanza Comercial Real | AA1: Cuenta Corriente | AB1: IPC | AC1: IPC SA | AD1: IPCSAE | AE1: IPCSAE SA | AF1: IPCSAE Bienes | AG1: IPCSAE Bienes SA | AH1: IPCSAE Servicios | AI1: IPCSAE Servicios SA | AJ1: Meta IPC | AK1: Meta IPC 2 | AL1: TPM Nominal | AM1: TCR | AN1: TCN | AO1: Precio Cobre Nominal | AP1: Precio Petróleo WTI | AQ1: IPE | AR1: PIB Externo Real | AS1: Libor | AT1: FED Funds | AU1: EMBI Chile | AV1: EMBI Chile 2 | AW1: TDI | AX1: CMO Total Real | AY1: CMO Total Real SA | AZ1: CMO Total Real en Pesos | BA1: CMO Total Real en Pesos SA | BB1: CMO Total Nom. | BC1: CMO Total Nom. SA | BD1: CMO Total Nom. en Pesos | BE1: CMO Total Nom. en Pesos SA | BF1: CMO Real Resto | BG1: CMO Real Resto SA | BH1: CMO Real Resto en Pesos | BI1: CMO Real Resto en Pesos SA | BJ1: CMO Nom. Resto | BK1: CMO Nom. Resto SA | BL1: CMO Nom. Resto en Pesos | BM1: CMO Nom. Resto en Pesos SA | BN1: IREM Total Real | BO1: IREM Total Real SA | BP1: IREM Total Real en Pesos | BQ1: IREM Total Real en Pesos SA | BR1: IREM Total Nom. | BS1: IREM Total Nom. SA | BT1: IREM Total Nom. en Pesos | BU1: IREM Total Nom. en Pesos SA | BV1: IREM MINERÍA Real | BW1: IREM MINERÍA Real SA | BX1: IREM MINERÍA Real en Pesos | BY1: IREM MINERÍA Real en Pesos SA | BZ1: IREM MINERÍA Nom. | CA1: IREM MINERÍA Nom. SA | CB1: IREM MINERÍA Nom. en Pesos | CC1: IREM MINERÍA Nom. en Pesos SA | CD1: IREM RESTO Real | CE1: IREM RESTO Real SA | CF1: IREM RESTO Real en Pesos | CG1: IREM RESTO Real en Pesos SA | CH1: IREM RESTO Nom. | CI1: IREM RESTO Nom. SA | CJ1: IREM RESTO Nom. en Pesos | CK1: IREM RESTO Nom. en Pesos SA | CL1: Empleo Total | CM1: Empleo Total SA | CN1: Empleo Minería | CO1: Empleo Minería SA | CP1: Horas Total | CQ1: Horas Total SA | CR1: Horas Minería | CS1: Horas Minería SA | CT1: Empleo Total Resto | CU1: Empleo Total Resto SA | CV1: Horas Resto | CW1: Horas Resto SA | CX1: Población > 15 años | CY1: Fuerza de Trabajo Total | CZ1: Fuerza de Trabajo Total SA | DA1: Tasa Desempleo | DB1: Tasa Desempleo SA | DC1: Tasa vacantes | DD1: Tasa Vacantes SA
A2: Unidad | B2: Mill. $ | C2: Mill. $ | D2: Mill. $ | E2: Mill. $ | F2: Mill. $ | G2: Mill. $ | H2: Mill. $ | I2: Mill. $ | J2: Mill. $ | K2: Mill. $ | L2: Mill. $ | M2: Mill. $ | N2: Mill. $ | O2: Mill. $ | P2: Mill. $ | Q2: Mill. $ | R2: Mill. $ | S2: Mill. $ | T2: Mill. $ | U2: Mill. $ | V2: Mill. $ | W2: Mill. $ | X2: Mill. $ | Y2: Mill. $ | Z2: Mill. $ | AA2: Mill. US $ | AB2: Índice | AC2: Índice | AD2: Índice | AE2: Índice | AF2: Índice | AG2: Índice | AH2: Índice | AI2: Índice | AJ2: Índice | AK2: Índice | AL2: Índice | AM2: Índice | AN2: Índice | AO2: USD/libra | AP2: USD/Barril | AQ2: Índice | AR2: Índice | AS2: Tasa, 3 meses | AT2: Tasa | AU2: Índice | AV2: Índice | AW2: Índice | AX2: Índice | AY2: Índice | AZ2: Pesos | BA2: Pesos | BB2: Índice | BC2: Índice | BD2: Pesos | BE2: Pesos | BF2: Índice | BG2: Índice | BH2: Pesos | BI2: Pesos | BJ2: Índice | BK2: Índice | BL2: Pesos | BM2: Pesos | BN2: Índice | BO2: Índice | BP2: Pesos | BQ2: Pesos | BR2: Índice | BS2: Índice | BT2: Pesos | BU2: Pesos | BV2: Índice | BW2: Índice | BX2: Pesos | BY2: Pesos | BZ2: Índice | CA2: Índice | CB2: Pesos | CC2: Pesos | CD2: Índice | CE2: Índice | CF2: Pesos | CG2: Pesos | CH2: Índice | CI2: Índice | CJ2: Pesos | CK2: Pesos | CL2: miles de personas | CM2: miles de personas | CN2: miles de personas | CO2: miles de personas | CP2: Horas semanales | CQ2: Horas semanales | CR2: Horas semanales | CS2: Horas semanales | CT2: miles de personas | CU2: miles de personas | CV2: Horas semanales | CW2: Horas semanales | CX2: miles de personas | CY2: miles de personas | CZ2: Unidades | DA2: Tasa | DB2: Tasa | DC2: Tasa | DD2: Tasa
A3: Origen datos | B3: GAM | C3: Propio | D3: GAM | E3: GAM | F3: Propio | G3: GAM | H3: Propio | I3: GAM | J3: Propio | K3: GAM | L3: Propio | M3: GAM | N3: Propio | O3: GAM | P3: Propio | Q3: GAM | R3: Propio | S3: GAM | T3: Propio | U3: GAM | V3: Propio | W3: GAM | X3: Propio | Y3: B7/CC.NN | Z3: B7/CC.NN | AA3: B7/CC.NN | AB3: INE/DAC | AC3: Propio | AD3: INE/DAC | AE3: Propio | AF3: INE/DAC | AG3: Propio | AH3: INE/DAC | AI3: Propio | AJ3: CC.NN. | AK3: CC.NN. | AL3: DMP/B7 | AM3: B7 | AN3: B7 | AO3: B7 | AP3: B7 | AQ3: B7 | AR3: DMP | AS3: B7 | AT3: FRED | AU3: GAM/B7 | AV3: GAM/B7 | AW3: DMP/B7 | AX3: Propio | AY3: Propio | AZ3: Propio | BA3: Propio | BB3: GAM | BC3: Propio | BD3: Propio | BE3: Propio | BF3: Propio | BG3: Propio | BH3: Propio | BI3: Propio | BJ3: GAM | BK3: Propio | BL3: Propio | BM3: Propio | BN3: INE/DAC | BO3: Propio | BP3: INE/DAC | BQ3: Propio | BR3: INE/DAC | BS3: Propio | BT3: INE/DAC | BU3: Propio | BV3: INE/DAC | BW3: Propio | BX3: INE/DAC | BY3: Propio | BZ3: INE/DAC | CA3: Propio | CB3: INE/DAC | CC3: Propio | CD3: INE/DAC | CE3: Propio | CF3: INE/DAC | CG3: Propio | CH3: INE/DAC | CI3: Propio | CJ3: INE/DAC | CK3: Propio | CL3: GAM | CM3: Propio | CN3: GAM | CO3: Propio | CP3: GAM | CQ3: Propio | CR3: GAM | CS3: Propio | CT3: GAM | CU3: Propio | CV3: GAM | CW3: Propio | CX3: GAM | CY3: GAM | CZ3: Propio | DA3: GAM | DB3: Propio | DC3: GAM | DD3: Propio
A4: Acceso | B4: Pública | D4: Pública | E4: No Público | G4: No Público | I4: Pública | K4: Pública | M4: No Público | O4: Pública | Q4: Pública | S4: Pública | U4: Pública | W4: Pública | Y4: Pública | Z4: Pública | AA4: Pública | AB4: Pública | AD4: Pública | AF4: No Pública | AH4: No Pública | AJ4: No Pública | AK4: Pública | AL4: Pública | AM4: Pública | AN4: Pública | AO4: Pública | AP4: Pública | AQ4: Pública | AR4: Pública | AS4: Pública | AT4: Pública | AU4: No Pública | AV4: Pública | AW4: Pública | AX4: Pública | AZ4: Pública | BB4: Pública | BD4: Pública | BF4: Pública | BH4: Pública | BJ4: Pública | BL4: Pública | BN4: Pública | BP4: Pública | BR4: Pública | BT4: Pública | BV4: Pública | BX4: Pública | BZ4: Pública | CB4: Pública | CD4: Pública | CF4: Pública | CH4: Pública | CJ4: Pública | CL4: Pública | CN4: Pública | CP4: Pública | CR4: Pública | CT4: Pública | CV4: Pública | CX4: Pública | CY4: Pública | DA4: Pública | DC4: Pública
A5: Fecha actualización | B5: 42572 | C5: 42572 | D5: 42572 | E5: 42572 | F5: 42572 | G5: 42572 | H5: 42572 | I5: 42572 | J5: 42572 | K5: 42572 | L5: 42572 | M5: 42572 | N5: 42572 | O5: 42572 | P5: 42572 | Q5: 42572 | R5: 42572 | S5: 42572 | T5: 42572 | U5: 42572 | V5: 42572 | W5: 42572 | X5: 42572 | Y5: 42572 | Z5: 42572 | AA5: 42572 | AB5: 42572 | AC5: 42572 | AD5: 42572 | AE5: 42572 | AF5: 42572 | AG5: 42572 | AH5: 42572 | AI5: 42572 | AJ5: 42572 | AK5: 42572 | AL5: 42572 | AM5: 42572 | AN5: 42572 | AO5: 42572 | AP5: 42572 | AQ5: 42572 | AR5: 42572 | AS5: 42572 | AT5: 42572 | AU5: 42572 | AV5: 42572 | AW5: 42572 | AX5: 42572 | AY5: 42572 | AZ5: 42572 | BA5: 42572 | BB5: 42572 | BC5: 42572 | BD5: 42572 | BE5: 42572 | BF5: 42572 | BG5: 42572 | BH5: 42572 | BI5: 42572 | BJ5: 42572 | BK5: 42572 | BL5: 42572 | BM5: 42572 | BN5: 42572 | BO5: 42572 | BP5: 42572 | BQ5: 42572 | BR5: 42572 | BS5: 42572 | BT5: 42572 | BU5: 42572 | BV5: 42572 | BW5: 42572 | BX5: 42572 | BY5: 42572 | BZ5: 42572 | CA5: 42572 | CB5: 42572 | CC5: 42572 | CD5: 42572 | CE5: 42572 | CF5: 42572 | CG5: 42572 | CH5: 42572 | CI5: 42572 | CJ5: 42572 | CK5: 42572 | CL5: 42572 | CM5: 42572 | CN5: 42572 | CO5: 42572 | CP5: 42572 | CQ5: 42572 | CR5: 42572 | CS5: 42572 | CT5: 42572 | CU5: 42572 | CV5: 42572 | CW5: 42572 | CX5: 42572 | CY5: 42572 | CZ5: 42572 | DA5: 42572 | DB5: 42572 | DC5: 42572 | DD5: 42572
A6: Ult. Dato Efectivo | B6: 2016T1 | C6: 2016T1 | D6: 2016T1 | E6: 2016T1 | F6: 2016T1 | G6: 2016T1 | H6: 2016T1 | I6: 2016T1 | J6: 2016T1 | K6: 2016T1 | L6: 2016T1 | M6: 2016T1 | N6: 2016T1 | O6: 2016T1 | P6: 2016T1 | Q6: 2016T1 | R6: 2016T1 | S6: 2016T1 | T6: 2016T1 | U6: 2016T1 | V6: 2016T1 | W6: 2016T1 | X6: 2016T1 | Y6: 2016T1 | Z6: 2016T1 | AA6: 2016T1 | AB6: 2016T1 | AC6: 2016T1 | AD6: 2016T1 | AE6: 2016T1 | AF6: 2016T1 | AG6: 2016T1 | AH6: 2016T1 | AI6: 2016T1 | AJ6: 2016T1 | AK6: 2016T1 | AL6: 2016T1 | AM6: 2016T1 | AN6: 2016T1 | AO6: 2016T1 | AP6: 2016T1 | AQ6: 2016T1 | AR6: 2016T1 | AS6: 2016T1 | AT6: 2016T1 | AU6: 2016T1 | AV6: 2016T1 | AW6: 2016T1 | AX6: 2016T1 | AY6: 2016T1 | AZ6: 2016T1 | BA6: 2016T1 | BB6: 2016T1 | BC6: 2016T1 | BD6: 2016T1 | BE6: 2016T1 | BF6: 2016T1 | BG6: 2016T1 | BH6: 2016T1 | BI6: 2016T1 | BJ6: 2016T1 | BK6: 2016T1 | BL6: 2016T1 | BM6: 2016T1 | BN6: 2016T1 | BO6: 2016T1 | BP6: 2016T1 | BQ6: 2016T1 | BR6: 2016T1 | BS6: 2016T1 | BT6: 2016T1 | BU6: 2016T1 | BV6: 2016T1 | BW6: 2016T1 | BX6: 2016T1 | BY6: 2016T1 | BZ6: 2016T1 | CA6: 2016T1 | CB6: 2016T1 | CC6: 2016T1 | CD6: 2016T1 | CE6: 2016T1 | CF6: 2016T1 | CG6: 2016T1 | CH6: 2016T1 | CI6: 2016T1 | CJ6: 2016T1 | CK6: 2016T1 | CL6: 2016T1 | CM6: 2016T1 | CN6: 2016T1 | CO6: 2016T1 | CP6: 2016T1 | CQ6: 2016T1 | CR6: 2016T1 | CS6: 2016T1 | CT6: 2016T1 | CU6: 2016T1 | CV6: 2016T1 | CW6: 2016T1 | CX6: 2016T1 | CY6: 2016T1 | CZ6: 2016T1 | DA6: 2016T1 | DB6: 2016T1 | DC6: 2016T1 | DD6: 2016T1
A7: 1986T1 | B7: 6597579.2 | C7: 6586781.3 | D7: 226339.71 | E7: 5008334.3 | F7: 4792721 | G7: 1552179.2 | H7: 1662532.2 | I7: 1291807 | J7: 1368417.4 | K7: 1070146.4 | L7: 1170615.3 | M7: 4305524.3 | N7: 4575572.1 | O7: 1066583.3 | P7: 1332446.6 | Q7: 3225419.4 | R7: 3283848.1 | S7: 43344.689 | T7: 49301.576 | U7: 3302112.6 | V7: 3327725.7 | W7: 626397.44 | X7: 608266.66 | Y7: 28016.598 | Z7: 340611.56 | AA7: -165.78504 | AB7: 12.744153 | AC7: 12.740184 | AD7: 13.746713 | AE7: 13.73078 | AF7: 26.379028 | AG7: 27.284283 | AH7: 9.429148 | AI7: 9.2262319 | AJ7: 25.3 | AK7: 19.252516 | AL7: 0 | AM7: 99.905172 | AN7: 186.85129 | AO7: 0.645 | AP7: 16.933333 | AQ7: 97.759067 | AR7: 66.340154 | AS7: 7.8915625 | AT7: 7.8266667 | AU7: 200 | AV7: 200 | AW7: 59.156872 | AX7: 61.359855 | AY7: 61.177192 | AZ7: 440488.99 | BA7: 439177.69 | BB7: 7.8197938 | BC7: 7.7880288 | BD7: 56136.59 | BE7: 55908.556 | BF7: 60.940872 | BG7: 60.545179 | BH7: 407347.32 | BI7: 404702.39 | BJ7: 7.7663978 | BK7: 7.7125911 | BL7: 51912.965 | BM7: 51553.305 | BN7: 57.1008 | BO7: 56.920368 | BP7: 244254.48 | BQ7: 243482.66 | BR7: 7.2770133 | BS7: 7.2480977 | BT7: 31128.164 | BU7: 31004.475 | BV7: 61.49292 | BW7: 62.097403 | BX7: 636270.83 | BY7: 642525.44 | BZ7: 7.8367518 | CA7: 7.9051408 | CB7: 81087.327 | CC7: 81794.952 | CD7: 55.230871 | CE7: 54.923611 | CF7: 221009.52 | CG7: 219780 | CH7: 7.0387066 | CI7: 6.9913424 | CJ7: 28165.791 | CK7: 27976.26 | CL7: 3988.6661 | CM7: 3993.1118 | CN7: 165.66594 | CO7: 165.46853 | CP7: 45.223858 | CQ7: 45.211849 | CR7: 41.248723 | CS7: 41.492441 | CT7: 3729.8219 | CU7: 3731.1656 | CV7: 44.963274 | CW7: 44.861952 | CX7: 8393.0516 | CY7: 4614.1181 | CZ7: 4615.7739 | DA7: 13.555178 | DB7: 13.492523 | DC7: 1.2797679 | DD7: 1.1529623
A8: 1986T2 | B8: 6932888.5 | C8: 6867057.2 | D8: 227443.88 | E8: 5080417.1 | F8: 5037438.2 | G8: 1732906.2 | H8: 1667568.6 | I8: 1381416.4 | J8: 1405350.9 | K8: 1188686.2 | L8: 1202307.8 | M8: 4744384.4 | N8: 4717096.6 | O8: 1359073.1 | P8: 1306994.5 | Q8: 3406420.5 | R8: 3419879.1 | S8: 80728.726 | T8: 82095.056 | U8: 3404424.6 | V8: 3429323.8 | W8: 640307.65 | X8: 637639.56 | Y8: 49137.327 | Z8: 354744.07 | AA8: -302.20433 | AB8: 13.209652 | AC8: 13.201985 | AD8: 14.374801 | AE8: 14.23627 | AF8: 29.380886 | AG8: 28.301213 | AH8: 9.5037519 | AI8: 9.558938 | AJ8: 22 | AK8: 19.212554 | AL8: 0 | AM8: 98.161851 | AN8: 188.66823 | AO8: 0.64433333 | AP8: 13.966667 | AQ8: 98.701307 | AR8: 67.035899 | AS8: 6.987175 | AT8: 6.92 | AU8: 219.83 | AV8: 219.83 | AW8: 64.031081 | AX8: 62.063363 | AY8: 61.983942 | AZ8: 445539.31 | BA8: 444969.17 | BB8: 8.1983541 | BC8: 8.1806974 | BD8: 58854.192 | BE8: 58727.438 | BF8: 61.281382 | BG8: 61.252786 | BH8: 409623.4 | BI8: 409432.25 | BJ8: 8.0950571 | BK8: 8.085441 | BL8: 54109.824 | BM8: 54045.547 | BN8: 57.755476 | BO8: 57.678432 | BP8: 247054.92 | BQ8: 246725.35 | BR8: 7.6292973 | BS8: 7.6125616 | BT8: 32635.094 | BU8: 32563.506 | BV8: 63.300572 | BW8: 62.924327 | BX8: 654974.7 | BY8: 651081.68 | BZ8: 8.3617851 | CA8: 8.3122606 | CB8: 86519.877 | CC8: 86007.444 | CD8: 55.532053 | CE8: 55.515559 | CF8: 222214.72 | CG8: 222148.72 | CH8: 7.3355908 | CI8: 7.3215641 | CJ8: 29353.791 | CK8: 29297.662 | CL8: 4042.9765 | CM8: 4043.3261 | CN8: 164.432 | CO8: 162.23264 | CP8: 45.512199 | CQ8: 45.320139 | CR8: 42.857185 | CS8: 42.516469 | CT8: 3783.0996 | CU8: 3788.9089 | CV8: 45.154992 | CW8: 44.988499 | CX8: 8434.3216 | CY8: 4577.0349 | CZ8: 4576.8235 | DA8: 11.668219 | DB8: 11.739884 | DC8: 1.2926855 | DD8: 1.227143
A9: 1986T3 | B9: 6825215.5 | C9: 7007356.7 | D9: 229020.71 | E9: 4845933 | F9: 5113008 | G9: 1733732.7 | H9: 1703619.4 | I9: 1389412.8 | J9: 1368294.4 | K9: 1205403.7 | L9: 1170547.4 | M9: 4664088.9 | N9: 4810622.1 | O9: 1339453.9 | P9: 1308903.8 | Q9: 3347095.3 | R9: 3512038.8 | S9: 71521.766 | T9: 68808.737 | U9: 3341635.9 | V9: 3536391.8 | W9: 667281.7 | X9: 702667.69 | Y9: 114458.1 | Z9: 281431.37 | AA9: -420.67886 | AB9: 13.616914 | AC9: 13.70306 | AD9: 14.701816 | AE9: 14.764296 | AF9: 29.422927 | AG9: 29.348624 | AH9: 9.8441414 | AI9: 9.9155052 | AJ9: 18.8 | AK9: 19.175804 | AL9: 0 | AM9: 101.01772 | AN9: 194.1229 | AO9: 0.60333333 | AP9: 13.9 | AQ9: 101.54045 | AR9: 67.607951 | AS9: 6.2785234 | AT9: 6.2066667 | AU9: 224.665 | AV9: 224.665 | AW9: 62.464096 | AX9: 62.272631 | AY9: 62.181696 | AZ9: 447041.61 | BA9: 446388.81 | BB9: 8.4796103 | BC9: 8.5183332 | BD9: 60873.269 | BE9: 61151.252 | BF9: 61.160728 | BG9: 61.208275 | BH9: 408816.91 | BI9: 409134.73 | BJ9: 8.3282035 | BK9: 8.3900272 | BL9: 55668.245 | BM9: 56081.493 | BN9: 57.950219 | BO9: 57.854121 | BP9: 247887.95 | BQ9: 247476.88 | BR9: 7.8910312 | BS9: 7.9255886 | BT9: 33754.688 | BU9: 33902.511 | BV9: 64.297493 | BW9: 63.646899 | BX9: 665289.91 | BY9: 658558.17 | BZ9: 8.755334 | CA9: 8.7140226 | CB9: 90591.951 | CC9: 90164.499 | CD9: 55.481517 | CE9: 55.504955 | CF9: 222012.5 | CG9: 222106.28 | CH9: 7.5548702 | CI9: 7.6078971 | CJ9: 30231.25 | CK9: 30443.44 | CL9: 4102.796 | CM9: 4096.6773 | CN9: 165.65098 | CO9: 163.38644 | CP9: 44.422129 | CQ9: 45.152834 | CR9: 42.910824 | CS9: 43.281989 | CT9: 3843.6143 | CU9: 3841.3684 | CV9: 44.032482 | CW9: 44.772055 | CX9: 8476.6416 | CY9: 4627.6984 | CZ9: 4624.2538 | DA9: 11.342623 | DB9: 11.257858 | DC9: 1.124389 | DD9: 1.1776982
A10: 1986T4 | B10: 7251292.1 | C10: 7149515.2 | D10: 229910.33 | E10: 5251839.4 | F10: 5264111.8 | G10: 1680204.6 | H10: 1664716.2 | I10: 1417365 | J10: 1341158.2 | K10: 1223516 | L10: 1147108.2 | M10: 5284017.3 | N10: 4878893.7 | O10: 1470788.3 | P10: 1294612.7 | Q10: 3844607.7 | R10: 3598854.5 | S10: 89572.505 | T10: 81742.867 | U10: 3863760.3 | V10: 3611531.4 | W10: 796896.89 | X10: 783285 | Y10: 18575.376 | Z10: 363807.19 | AA10: -302.53177 | AB10: 14.196413 | AC10: 14.119639 | AD10: 15.124586 | AE10: 15.226332 | AF10: 30.0536 | AG10: 30.282604 | AH10: 10.169935 | AI10: 10.258908 | AJ10: 15.5 | AK10: 19.145875 | AL10: 0 | AM10: 101.01812 | AN10: 201.68778 | AO10: 0.59666667 | AP10: 15.4 | AQ10: 101.99917 | AR10: 68.426721 | AS10: 6.1423387 | AT10: 6.2666667 | AU10: 205 | AV10: 205 | AW10: 66.450839 | AX10: 62.43181 | AY10: 62.808074 | AZ10: 448184.32 | BA10: 450885.44 | BB10: 8.8630779 | BC10: 8.8804353 | BD10: 63626.099 | BE10: 63750.704 | BF10: 62.064335 | BG10: 62.467981 | BH10: 414856.9 | BI10: 417554.98 | BJ10: 8.8109096 | BK10: 8.8195389 | BL10: 58894.8 | BM10: 58952.48 | BN10: 58.09835 | BO10: 58.472157 | BP10: 248521.6 | BQ10: 250120.6 | BR10: 8.2478819 | BS10: 8.2650985 | BT10: 35281.153 | BU10: 35354.799 | BV10: 63.806349 | BW10: 64.227727 | BX10: 660208.01 | BY10: 664568.03 | BZ10: 9.058213 | CA10: 9.0770378 | CB10: 93725.858 | CC10: 93920.639 | CD10: 56.21762 | CE10: 56.541546 | CF10: 224958.05 | CG10: 226254.26 | CH10: 7.9808857 | CI10: 7.9973782 | CJ10: 31935.975 | CK10: 32001.971 | CL10: 4124.3414 | CM10: 4125.9894 | CN10: 163.85046 | CO10: 168.59302 | CP10: 46.141594 | CQ10: 45.625072 | CR10: 43.457694 | CS10: 43.174205 | CT10: 3866.7728 | CU10: 3862.3942 | CV10: 45.867959 | CW10: 45.403082 | CX10: 8519.3916 | CY10: 4656.3921 | CZ10: 4658.5736 | DA10: 11.426242 | DB10: 11.481067 | DC10: 0.97500381 | DD10: 1.1057671
A11: 1987T1 | B11: 7227526.9 | C11: 7210289.2 | D11: 230737.18 | E11: 5503497.1 | F11: 5258207.6 | G11: 1569938.1 | H11: 1680997.1 | I11: 1286272.1 | J11: 1361541.8 | K11: 1065561.2 | L11: 1164685 | M11: 4606419.8 | N11: 4889924.8 | O11: 1015867.5 | P11: 1268757.4 | Q11: 3576085.7 | R11: 3638720 | S11: 76661.393 | T11: 86776.151 | U11: 3604200.7 | V11: 3632340.5 | W11: 859519.9 | X11: 835672.62 | Y11: 110251.56 | Z11: 396752.1 | AA11: -3.9382287 | AB11: 14.94365 | AC11: 14.937741 | AD11: 16.119241 | AE11: 16.098195 | AF11: 30.931752 | AG11: 31.976837 | AH11: 11.056513 | AI11: 10.824588 | AJ11: 14.9 | AK11: 19.125096 | AL11: 0 | AM11: 101.77644 | AN11: 206.15159 | AO11: 0.63333333 | AP11: 18.3 | AQ11: 105.8586 | AR11: 68.698927 | AS11: 6.3810484 | AT11: 6.22 | AU11: 160.665 | AV11: 160.665 | AW11: 63.780469 | AX11: 62.16037 | AY11: 61.962945 | AZ11: 446235.71 | BA11: 444818.44 | BB11: 9.2890283 | BC11: 9.2471243 | BD11: 66683.904 | BE11: 66383.084 | BF11: 61.567042 | BG11: 61.159282 | BH11: 411532.83 | BI11: 408807.24 | BJ11: 9.2003635 | BK11: 9.1349101 | BL11: 61498.028 | BM11: 61060.517 | BN11: 57.84575 | BO11: 57.653947 | BP11: 247441.07 | BQ11: 246620.62 | BR11: 8.6442666 | BS11: 8.6062195 | BT11: 36976.729 | BU11: 36813.978 | BV11: 62.809418 | BW11: 63.433182 | BX11: 649892.71 | BY11: 656346.83 | BZ11: 9.3860198 | CA11: 9.4666201 | CB11: 97117.694 | CC11: 97951.67 | CD11: 55.918348 | CE11: 55.599581 | CF11: 223760.5 | CG11: 222484.94 | CH11: 8.3562424 | CI11: 8.2958452 | CJ11: 33437.987 | CK11: 33196.304 | CL11: 4160.5714 | CM11: 4164.3289 | CN11: 170.51547 | CO11: 170.48578 | CP11: 45.442658 | CQ11: 45.406134 | CR11: 43.023653 | CS11: 43.265449 | CT11: 3893.2264 | CU11: 3893.3783 | CV11: 45.316407 | CW11: 45.192514 | CX11: 8562.1316 | CY11: 4677.3397 | CZ11: 4678.5502 | DA11: 11.048337 | DB11: 11.026862 | DC11: 1.246435 | DD11: 1.1226604
A12: 1987T2 | B12: 7338580.1 | C12: 7269897.6 | D12: 232424.97 | E12: 5363312.6 | F12: 5322704 | G12: 1776766.2 | H12: 1708406.2 | I12: 1327211.2 | J12: 1348803.2 | K12: 1142043.5 | L12: 1153915.1 | M12: 4964507.6 | N12: 4937974.1 | O12: 1324365.9 | P12: 1272738.7 | Q12: 3662230.2 | R12: 3678417.9 | S12: 94616.265 | T12: 96396.315 | U12: 3645623.9 | V12: 3670033.5 | W12: 839768.26 | X12: 836751.48 | Y12: -14182.945 | Z12: 396851.56 | AA12: -190.38086 | AB12: 15.743801 | AC12: 15.739781 | AD12: 17.132474 | AE12: 16.972808 | AF12: 35.017338 | AG12: 33.748492 | AH12: 11.326959 | AI12: 11.391724 | AJ12: 15.7 | AK12: 19.114603 | AL12: 0 | AM12: 103.66926 | AN12: 214.09661 | AO12: 0.69 | AP12: 19.4 | AQ12: 109.37985 | AR12: 69.827932 | AS12: 7.1561508 | AT12: 6.65 | AU12: 172.165 | AV12: 172.165 | AW12: 68.538718 | AX12: 61.406572 | AY12: 61.305935 | AZ12: 440824.36 | BA12: 440101.91 | BB12: 9.6677288 | BC12: 9.646397 | BD12: 69402.512 | BE12: 69249.376 | BF12: 60.394976 | BG12: 60.339662 | BH12: 403698.39 | BI12: 403328.65 | BJ12: 9.5084651 | BK12: 9.49579 | BL12: 63557.473 | BM12: 63472.749 | BN12: 57.144274 | BO12: 57.048032 | BP12: 244440.44 | BQ12: 244028.76 | BR12: 8.9966811 | BS12: 8.9763304 | BT12: 38484.218 | BU12: 38397.166 | BV12: 63.220362 | BW12: 62.797097 | BX12: 654144.77 | BY12: 649765.22 | BZ12: 9.9532883 | CA12: 9.8942523 | CB12: 102987.25 | CC12: 102376.41 | CD12: 54.864909 | CE12: 54.824615 | CF12: 219545.1 | CG12: 219383.87 | CH12: 8.6378224 | CI12: 8.6200004 | CJ12: 34564.745 | CK12: 34493.43 | CL12: 4201.3147 | CM12: 4201.9548 | CN12: 169.95353 | CO12: 167.5774 | CP12: 44.758515 | CQ12: 44.58867 | CR12: 43.489126 | CS12: 43.202424 | CT12: 3932.1309 | CU12: 3938.403 | CV12: 44.573028 | CW12: 44.427777 | CX12: 8604.9416 | CY12: 4725.264 | CZ12: 4725.3687 | DA12: 11.088255 | DB12: 11.12892 | DC12: 1.0489714 | DD12: 0.99456502
A13: 1987T3 | B13: 7211378.5 | C13: 7400123.3 | D13: 233288.88 | E13: 5164856.1 | F13: 5441861.6 | G13: 1701754 | H13: 1674507.8 | I13: 1376132.7 | J13: 1355690.4 | K13: 1193882.4 | L13: 1159785.4 | M13: 4825644.8 | N13: 4974570.9 | O13: 1305374.2 | P13: 1276688.1 | Q13: 3543508.9 | R13: 3713750.6 | S13: 101277.15 | T13: 97669.268 | U13: 3490100.2 | V13: 3692652.3 | W13: 786831.55 | X13: 827672.84 | Y13: 223632.25 | Z13: 299111.3 | AA13: -327.79832 | AB13: 16.420916 | AC13: 16.523743 | AD13: 17.729221 | AE13: 17.801619 | AF13: 35.481712 | AG13: 35.423699 | AH13: 11.871252 | AI13: 11.954578 | AJ13: 16.5 | AK13: 19.114365 | AL13: 0 | AM13: 104.43317 | AN13: 224.59469 | AO13: 0.79333333 | AP13: 20.4 | AQ13: 109.59568 | AR13: 70.857014 | AS13: 7.2367063 | AT13: 6.8433333 | AU13: 196.665 | AV13: 196.665 | AW13: 70.013803 | AX13: 61.896203 | AY13: 61.801936 | AZ13: 444339.31 | BA13: 443662.59 | BB13: 10.163923 | BC13: 10.216495 | BD13: 72964.583 | BE13: 73341.987 | BF13: 60.691314 | BG13: 60.736779 | BH13: 405679.2 | BI13: 405983.1 | BJ13: 9.9660694 | BK13: 10.039106 | BL13: 66616.239 | BM13: 67104.437 | BN13: 57.599919 | BO13: 57.501532 | BP13: 246389.51 | BQ13: 245968.65 | BR13: 9.4584341 | BS13: 9.5055493 | BT13: 40459.413 | BU13: 40660.953 | BV13: 63.364061 | BW13: 62.756933 | BX13: 655631.63 | BY13: 649349.64 | BZ13: 10.404959 | CA13: 10.361517 | CB13: 107660.72 | CC13: 107211.22 | CD13: 55.080881 | CE13: 55.093929 | CF13: 220409.33 | CG13: 220461.54 | CH13: 9.044785 | CI13: 9.1134315 | CJ13: 36193.23 | CK13: 36467.923 | CL13: 4203.2053 | CM13: 4197.6524 | CN13: 169.48235 | CO13: 167.12092 | CP13: 43.700067 | CQ13: 44.390838 | CR13: 40.932345 | CS13: 41.242594 | CT13: 3935.6997 | CU13: 3934.3972 | CV13: 43.599968 | CW13: 44.303548 | CX13: 8648.4716 | CY13: 4720.0526 | CZ13: 4716.9524 | DA13: 10.950033 | DB13: 10.882341 | DC13: 1.0232937 | DD13: 1.0752334
A14: 1987T4 | B14: 7617189.5 | C14: 7524887.3 | D14: 233715.47 | E14: 5498923.3 | F14: 5529010.3 | G14: 1756128.8 | H14: 1742706.1 | I14: 1474700.7 | J14: 1399729.8 | K14: 1273010.1 | L14: 1197187 | M14: 5464423.3 | N14: 5053025.6 | O14: 1456341.2 | P14: 1282644.1 | Q14: 4040532.2 | R14: 3787181.3 | S14: 118572.57 | T14: 108157.15 | U14: 4014999.7 | V14: 3757104.2 | W14: 837705.94 | X14: 821985.79 | Y14: -36213.93 | Z14: 392850.24 | AA14: -213.38259 | AB14: 17.348104 | AC14: 17.248875 | AD14: 18.482337 | AE14: 18.603258 | AF14: 36.725683 | AG14: 36.964078 | AH14: 12.427723 | AI14: 12.527265 | AJ14: 17.4 | AK14: 19.124394 | AL14: 0 | AM14: 107.469 | AN14: 232.77113 | AO14: 1.11 | AP14: 18.733333 | AQ14: 114.8831 | AR14: 71.884935 | AS14: 7.9846311 | AT14: 6.9166667 | AU14: 107.665 | AV14: 107.665 | AW14: 83.171862 | AX14: 62.251665 | AY14: 62.706105 | AZ14: 446891.1 | BA14: 450153.42 | BB14: 10.799484 | BC14: 10.821923 | BD14: 77527.134 | BE14: 77688.221 | BF14: 61.135404 | BG14: 61.610863 | BH14: 408647.63 | BI14: 411825.75 | BJ14: 10.605834 | BK14: 10.626293 | BL14: 70892.618 | BM14: 71029.373 | BN14: 57.930709 | BO14: 58.369602 | BP14: 247804.49 | BQ14: 249681.9 | BR14: 10.04988 | BS14: 10.071695 | BT14: 42989.382 | BU14: 43082.698 | BV14: 63.60776 | BW14: 64.083933 | BX14: 658153.2 | BY14: 663080.19 | BZ14: 11.034741 | CA14: 11.052964 | CB14: 114177.1 | CC14: 114365.67 | CD14: 55.371581 | CE14: 55.773945 | CF14: 221572.58 | CG14: 223182.66 | CH14: 9.6059196 | CI14: 9.6290271 | CJ14: 38438.642 | CK14: 38531.108 | CL14: 4264.7021 | CM14: 4266.4441 | CN14: 161.62303 | CO14: 166.26365 | CP14: 45.615586 | CQ14: 45.122708 | CR14: 44.378786 | CS14: 44.064073 | CT14: 4008.7089 | CU14: 4003.8902 | CV14: 45.403476 | CW14: 44.958692 | CX14: 8692.3016 | CY14: 4765.5755 | CZ14: 4767.4261 | DA14: 10.51024 | DB14: 10.543326 | DC14: 0.97784621 | DD14: 1.1088704
A15: 1988T1 | B15: 7734653.2 | C15: 7702652.6 | D15: 234228.29 | E15: 5933955.5 | F15: 5654168.5 | G15: 1648862 | H15: 1758037.8 | I15: 1339057.6 | J15: 1411914.8 | K15: 1109289.3 | L15: 1207584.6 | M15: 4830246.5 | N15: 5117565.8 | O15: 1033477.8 | P15: 1288744.9 | Q15: 3781599.2 | R15: 3845431.1 | S15: 96136.499 | T15: 108131.26 | U15: 3783379.1 | V15: 3812520.4 | W15: 855633.46 | X15: 834436.39 | Y15: 208072.68 | Z15: 473068.91 | AA15: 146.51447 | AB15: 17.778014 | AC15: 17.764867 | AD15: 19.17658 | AE15: 19.150011 | AF15: 36.798581 | AG15: 37.972421 | AH15: 13.153603 | AI15: 12.902036 | AJ15: 17.1 | AK15: 19.145627 | AL15: 0 | AM15: 110.94401 | AN15: 242.35859 | AO15: 1.1133333 | AP15: 16.666667 | AQ15: 116.84042 | AR15: 72.633643 | AS15: 6.9734624 | AT15: 6.6633333 | AU15: 56 | AV15: 56 | AW15: 67.888236 | AX15: 64.455342 | AY15: 64.205587 | AZ15: 462710.81 | BA15: 460917.87 | BB15: 11.45888 | BC15: 11.393569 | BD15: 82260.794 | BE15: 81791.942 | BF15: 63.410499 | BG15: 62.95617 | BH15: 423855.07 | BI15: 420818.19 | BJ15: 11.273128 | BK15: 11.183113 | BL15: 75353.014 | BM15: 74751.326 | BN15: 59.981425 | BO15: 59.75015 | BP15: 256576.64 | BQ15: 255587.34 | BR15: 10.663506 | BS15: 10.605011 | BT15: 45614.232 | BU15: 45364.013 | BV15: 64.966922 | BW15: 65.549365 | BX15: 672216.53 | BY15: 678243.1 | BZ15: 11.549829 | CA15: 11.644226 | CB15: 119506.75 | CC15: 120483.49 | CD15: 57.382169 | CE15: 57.018782 | CF15: 229618.07 | CG15: 228163.95 | CH15: 10.20141 | CI15: 10.116929 | CJ15: 40821.533 | CK15: 40483.476 | CL15: 4315.5455 | CM15: 4317.48 | CN15: 165.66134 | CO15: 165.93381 | CP15: 44.905347 | CQ15: 44.881085 | CR15: 43.428722 | CS15: 43.675415 | CT15: 4058.1447 | CU15: 4057.2776 | CV15: 44.956067 | CW15: 44.845615 | CX15: 8736.1516 | CY15: 4823.7139 | CZ15: 4824.1412 | DA15: 10.534796 | DB15: 10.557256 | DC15: 1.2873898 | DD15: 1.1556967
A16: 1988T2 | B16: 7689730.3 | C16: 7615188.9 | D16: 233778.19 | E16: 5647761.5 | F16: 5606819.9 | G16: 1787290.3 | H16: 1719740.1 | I16: 1384666.8 | J16: 1406593.7 | K16: 1191483.2 | L16: 1203324.2 | M16: 5202399.3 | N16: 5180032.2 | O16: 1368047.5 | P16: 1313850.8 | Q16: 3857498.7 | R16: 3878459.4 | S16: 109895.13 | T16: 112244.97 | U16: 3820088.8 | V16: 3843951.9 | W16: 932889.35 | X16: 929829.32 | Y16: 23341.968 | Z16: 509136.06 | AA16: -36.165536 | AB16: 18.254817 | AC16: 18.272964 | AD16: 19.864972 | AE16: 19.692126 | AF16: 40.602334 | AG16: 39.226184 | AH16: 13.133522 | AI16: 13.195023 | AJ16: 16.4 | AK16: 19.180922 | AL16: 0 | AM16: 113.11247 | AN16: 245.11419 | AO16: 1.1 | AP16: 17.266667 | AQ16: 120.97412 | AR16: 73.219108 | AS16: 7.4828629 | AT16: 7.1566667 | AU16: 52.5 | AV16: 52.5 | AW16: 76.881305 | AX16: 65.668161 | AY16: 65.465966 | AZ16: 471417.37 | BA16: 469965.86 | BB16: 11.987602 | BC16: 11.965231 | BD16: 86056.377 | BE16: 85895.777 | BF16: 64.772379 | BG16: 64.603635 | BH16: 432958.28 | BI16: 431830.35 | BJ16: 11.824079 | BK16: 11.802899 | BL16: 79035.741 | BM16: 78894.166 | BN16: 61.110061 | BO16: 60.918491 | BP16: 261404.5 | BQ16: 260585.04 | BR16: 11.15553 | BS16: 11.133624 | BT16: 47718.912 | BU16: 47625.21 | BV16: 66.454655 | BW16: 65.932949 | BX16: 687610.19 | BY16: 682212.06 | BZ16: 12.131176 | CA16: 12.058328 | CB16: 125521.98 | CC16: 124768.22 | CD16: 58.698786 | CE16: 58.555217 | CF16: 234886.58 | CG16: 234312.08 | CH16: 10.715356 | CI16: 10.693109 | CJ16: 42878.115 | CK16: 42789.093 | CL16: 4401.4528 | CM16: 4403.3425 | CN16: 171.237 | CO16: 168.64382 | CP16: 45.738677 | CQ16: 45.56434 | CR16: 43.856176 | CS16: 43.661255 | CT16: 4131.9995 | CU16: 4138.837 | CV16: 45.712961 | CW16: 45.57082 | CX16: 8780.0416 | CY16: 4892.7286 | CZ16: 4893.9857 | DA16: 10.040937 | DB16: 10.038494 | DC16: 1.3346336 | DD16: 1.2641645
A17: 1988T3 | B17: 7808703.9 | C17: 8012688.4 | D17: 233973.95 | E17: 5526479 | F17: 5818909.9 | G17: 1935117.7 | H17: 1904754.1 | I17: 1536320.5 | J17: 1515570 | K17: 1332855.4 | L17: 1296641.9 | M17: 5180986.6 | N17: 5333231.2 | O17: 1355605.7 | P17: 1327985.8 | Q17: 3850330.3 | R17: 4023983.1 | S17: 131821.23 | T17: 127913.71 | U17: 3751280.2 | V17: 3962227.5 | W17: 966298.74 | X17: 1014242.4 | Y17: 196330.43 | Z17: 389162.97 | AA17: -206.79012 | AB17: 18.538432 | AC17: 18.645506 | AD17: 20.015447 | AE17: 20.091696 | AF17: 40.057163 | AG17: 40.042165 | AH17: 13.402078 | AI17: 13.491115 | AJ17: 15.6 | AK17: 19.233027 | AL17: 0 | AM17: 110.99305 | AN17: 246.51344 | AO17: 1.0333333 | AP17: 15.2 | AQ17: 119.76679 | AR17: 73.99145 | AS17: 8.4156746 | AT17: 7.9833333 | AU17: 52.165 | AV17: 52.165 | AW17: 73.9394 | AX17: 67.550344 | AY17: 67.528224 | AZ17: 484929.15 | BA17: 484770.36 | BB17: 12.522774 | BC17: 12.600581 | BD17: 89898.261 | BE17: 90456.817 | BF17: 67.190344 | BG17: 67.317108 | BH17: 449120.7 | BI17: 449968.03 | BJ17: 12.456036 | BK17: 12.555957 | BL17: 83259.935 | BM17: 83927.833 | BN17: 62.8616 | BO17: 62.825195 | BP17: 268896.88 | BQ17: 268741.16 | BR17: 11.653555 | BS17: 11.722557 | BT17: 49849.265 | BU17: 50144.431 | BV17: 66.981895 | BW17: 66.446994 | BX17: 693065.57 | BY17: 687530.92 | BZ17: 12.417393 | CA17: 12.385244 | CB17: 128483.49 | CC17: 128150.84 | CD17: 60.914622 | CE17: 60.993365 | CF17: 243753.38 | CG17: 244068.48 | CH17: 11.292616 | CI17: 11.386072 | CJ17: 45188.054 | CK17: 45562.024 | CL17: 4480.3725 | CM17: 4475.73 | CN17: 173.69037 | CO17: 171.16565 | CP17: 45.161286 | CQ17: 45.833011 | CR17: 42.910043 | CS17: 43.166283 | CT17: 4210.5936 | CU17: 4210.1917 | CV17: 45.19737 | CW17: 45.875593 | CX17: 8824.3516 | CY17: 4969.0977 | CZ17: 4965.8228 | DA17: 9.8352907 | DB17: 9.7853897 | DC17: 1.3094262 | DD17: 1.3869881
A18: 1988T4 | B18: 8321824.4 | C18: 8240095.7 | D18: 237110.44 | E18: 5928371.3 | F18: 5975221.5 | G18: 1916919.3 | H18: 1914316.3 | I18: 1635722.1 | J18: 1557541.8 | K18: 1412009 | L18: 1332084.1 | M18: 5869020.7 | N18: 5437010.9 | O18: 1528851.1 | P18: 1347278.9 | Q18: 4375022.3 | R18: 4107055.3 | S18: 141906.56 | T18: 128988.33 | U18: 4321110.7 | V18: 4049626.7 | W18: 1039415.3 | X18: 1017976.7 | Y18: 113072.23 | Z18: 475242.11 | AA18: -134.75882 | AB18: 19.350229 | AC18: 19.2251 | AD18: 20.615362 | AE18: 20.739505 | AF18: 40.964152 | AG18: 41.155461 | AH18: 13.861993 | AI18: 13.956229 | AJ18: 14.9 | AK18: 19.302668 | AL18: 0 | AM18: 109.63786 | AN18: 246.01787 | AO18: 1.4733333 | AP18: 14.766667 | AQ18: 123.66507 | AR18: 74.795777 | AS18: 9.0327049 | AT18: 8.47 | AU18: 67.5 | AV18: 67.5 | AW18: 88.509027 | AX18: 66.246724 | AY18: 66.84431 | AZ18: 475570.75 | BA18: 479860.69 | BB18: 12.818893 | BC18: 12.846062 | BD18: 92024.029 | BE18: 92219.069 | BF18: 66.223548 | BG18: 66.881128 | BH18: 442658.34 | BI18: 447053.8 | BJ18: 12.814408 | BK18: 12.85543 | BL18: 85655.402 | BM18: 85929.602 | BN18: 61.648466 | BO18: 62.213857 | BP18: 263707.58 | BQ18: 266126.1 | BR18: 11.929119 | BS18: 11.956304 | BT18: 51028.02 | BU18: 51144.307 | BV18: 65.118972 | BW18: 65.690892 | BX18: 673789.8 | BY18: 679707.49 | BZ18: 12.60067 | CA18: 12.611052 | CB18: 130379.87 | CC18: 130487.29 | CD18: 60.055771 | CE18: 60.631074 | CF18: 240316.64 | CG18: 242618.75 | CH18: 11.620929 | CI18: 11.658461 | CJ18: 46501.82 | CK18: 46652.006 | CL18: 4542.8598 | CM18: 4544.2989 | CN18: 167.38856 | CO18: 172.11426 | CP18: 45.631015 | CQ18: 45.156222 | CR18: 43.098011 | CS18: 42.756378 | CT18: 4281.4663 | CU18: 4276.1157 | CV18: 45.692605 | CW18: 45.263448 | CX18: 8868.8216 | CY18: 4983.5482 | CZ18: 4985.1805 | DA18: 8.8428625 | DB18: 8.8620731 | DC18: 1.2139945 | DD18: 1.3721413
... A127: 2016T1 | B127: 29669125 | C127: 30124246 | D127: 41137238 | E127: 22571447 | F127: 22743686 | G127: 4448900 | H127: 4672398.1 | I127: 3376657.6 | J127: 3525435.8 | K127: 3079651.7 | L127: 3206153 | M127: 22271056 | N127: 23877104 | O127: 2910527.6 | P127: 3777291.2 | Q127: 19440991 | R127: 20204134 | S127: 2141426.5 | T127: 2304889.7 | U127: 17313745 | V127: 17912647 | W127: 7027057.2 | X127: 7158239.6 | Y127: 1479957.5 | Z127: 221876.78 | AA127: 515 | AB127: 111.74 | AC127: 111.90986 | AD127: 111.84113 | AE127: 111.67234 | AF127: 109.12104 | AG127: 108.91979 | AH127: 113.62672 | AI127: 113.4604 | AJ127: 3 | AK127: 3 | AL127: 3.5 | AM127: 96.67 | AN127: 702.06714 | AO127: 2.1 | AP127: 33.2 | AQ127: 219.93 | AR127: 184.0113 | AS127: 0.62484113 | AT127: 0.36 | AU127: 256 | AV127: 256 | AW127: 104.95997 | AX127: 135.40958 | AY127: 134.73583 | AZ127: 972075.79 | BA127: 967239.09 | BB127: 151.30667 | BC127: 150.77866 | BD127: 1086197.5 | BE127: 1082407.1 | BF127: 135.49434 | BG127: 134.86541 | BH127: 905685.39 | BI127: 901481.44 | BJ127: 151.40138 | BK127: 150.84942 | BL127: 1012012.9 | BM127: 1008323.4 | BN127: 130.12052 | BO127: 129.42099 | BP127: 556603.74 | BQ127: 553611.45 | BR127: 145.39667 | BS127: 144.71144 | BT127: 621949.02 | BU127: 619017.89 | BV127: 132.21765 | BW127: 131.04632 | BX127: 1368063.7 | BY127: 1355943.9 | BZ127: 147.74 | CA127: 146.65475 | CB127: 1528674.4 | CC127: 1517445.2 | CD127: 130.05411 | CE127: 129.38744 | CF127: 520419.04 | CG127: 517751.3 | CH127: 145.32246 | CI127: 144.72587 | CJ127: 581516.23 | CK127: 579128.93 | CL127: 8077.9816 | CM127: 8065.2326 | CN127: 199.68467 | CO127: 201.39832 | CP127: 36.916658 | CQ127: 37.94605 | CR127: 40.614447 | CS127: 42.164694 | CT127: 7751.4089 | CU127: 7737.4153 | CV127: 36.782936 | CW127: 37.793969 | CX127: 14498.56 | CY127: 8617.7258 | CZ127: 8600.1841 | DA127: 6.3 | DB127: 6.2389167 | DC127: 0.51289633 | DD127: 0.41783971

Sheet Notas_MKirchner
A1: Autor: | B1: Markus Kirchner
A2: Última
A3: Modificación: | B3: 41423
A5: La fuente de los datos es "DatosSinVinculos", ver "Notas_CPerez".
A6: Abajo se describen las transformaciones para llegar a las series observables del modelo.
A8: Hojas:
A9: Trans: transformaciones de variables (tasas base trimestral, etc.)
A10: Logs: logaritmo natural. Elegir con 1/0.
A11: Growth: tasas de crecimiento trimestral (dlog), usar en combinación con logs. Elegir con 1/0.
A12: Annual: anualizar, usar en combinación con tasas. Elegir con 1/0.
A13: Lin86: tendencia lineal 1986Q2-2012Q4. Elegir con 1/0.
A14: Lin91: tendencia lineal 1991Q1-2012Q4. Elegir con 1/0.
A15: Lin01: tendencia lineal 2001Q3-2012Q4. Elegir con 1/0.
A16: HP86: tendencia filtro HP 1986Q2-2012Q4. Elegir con 1/0 y elegir lambda para filtro HP por usar, requiere plug-in Excel filtro HP (http://ideas.repec.org/c/dge/qmrbcd/165.html).
A17: HP91: tendencia filtro HP 1991Q1-2012Q4. Elegir con 1/0 y elegir lambda para filtro HP por usar.
... A28: Charts (3): resumen de variables observadas.

Sheet Trans
B1: Y | C1: Y REST | D1: Y CU | E1: Y MINE | F1: Y RRNN | G1: C | H1: FBKF | I1: IPC | J1: IPCSAE | K1: TPMN | L1: TPMR | M1: RER | N1: TCN | O1: TBY | P1: CAY | Q1: G | R1: R+S EXT | S1: R EXT | T1: SPREAD | U1: Y EXT | V1: IPE | W1: PCUR | X1: WR | Y1: WR REST | Z1: H*N/FT | AA1: H | AB1: N/FT | AC1: U | AD1: V
A2: Unit | B2: Level SA | C2: Level SA | D2: Level SA | E2: Level SA | F2: Level SA | G2: Level SA | H2: Level SA | I2: Level SA | J2: Level SA | K2: Gross Q rate | L2: Gross Q rate | M2: Level | N2: Level | O2: Ratio YN | P2: Ratio YN | Q2: Level SA | R2: Gross Q rate | S2: Gross Q rate | T2: Gross Q rate | U2: Level SA | V2: Level SA | W2: Level | X2: Level SA | Y2: Level SA | Z2: Level SA | AA2: Level SA | AB2: Level SA | AC2: Level SA | AD2: Level SA
A3: 1986Q1 | B3: =DatosSinVinculos!C7 -> 6586781.3 | C3: =DatosSinVinculos!F7 -> 4792721 | D3: =DatosSinVinculos!L7 -> 1170615.3 | E3: =DatosSinVinculos!J7 -> 1368417.4 | F3: =DatosSinVinculos!H7 -> 1662532.2 | G3: =DatosSinVinculos!R7 -> 3283848.1 | H3: =DatosSinVinculos!X7 -> 608266.66 | I3: =DatosSinVinculos!AC7 -> 12.740184 | K3: =(1+DatosSinVinculos!AL7/100)^(1/4) -> 1 | M3: =DatosSinVinculos!AM7 -> 99.905172 | N3: =DatosSinVinculos!AN7 -> 186.85129 | O3: =DatosSinVinculos!Y7/DatosSinVinculos!D7 -> 0.12378119 | P3: =DatosSinVinculos!AA7*DatosSinVinculos!AN7/DatosSinVinculos!D7 -> -0.13686131 | Q3: =DatosSinVinculos!P7 -> 1332446.6 | S3: =(1+DatosSinVinculos!AS7/100)^(1/4) -> 1.0191706 | U3: =DatosSinVinculos!AR7 -> 66.340154 | V3: =DatosSinVinculos!AQ7 -> 97.759067 | W3: =DatosSinVinculos!AO7/DatosSinVinculos!AQ7*100*100 -> 65.978535 | X3: =DatosSinVinculos!BO7 -> 56.920368 | Y3: =DatosSinVinculos!CE7 -> 54.923611 | Z3: =DatosSinVinculos!CQ7*DatosSinVinculos!CM7/DatosSinVinculos!CZ7 -> 39.112827 | AA3: =DatosSinVinculos!CQ7 -> 45.211849 | AB3: =DatosSinVinculos!CM7/DatosSinVinculos!CZ7 -> 0.86510125 | AC3: =DatosSinVinculos!DB7/100 -> 0.13492523 | AD3: =DatosSinVinculos!DD7/100 -> 0.011529623
A4: 1986Q2 | B4: =DatosSinVinculos!C8 -> 6867057.2 | C4: =DatosSinVinculos!F8 -> 5037438.2 | D4: =DatosSinVinculos!L8 -> 1202307.8 | E4: =DatosSinVinculos!J8 -> 1405350.9 | F4: =DatosSinVinculos!H8 -> 1667568.6 | G4: =DatosSinVinculos!R8 -> 3419879.1 | H4: =DatosSinVinculos!X8 -> 637639.56 | I4: =DatosSinVinculos!AC8 -> 13.201985 | K4: =(1+DatosSinVinculos!AL8/100)^(1/4) -> 1 | L4: =K4/(I4/I3) -> 0.96502035 | M4: =DatosSinVinculos!AM8 -> 98.161851 | N4: =DatosSinVinculos!AN8 -> 188.66823 | O4: =DatosSinVinculos!Y8/DatosSinVinculos!D8 -> 0.21604154 | P4: =DatosSinVinculos!AA8*DatosSinVinculos!AN8/DatosSinVinculos!D8 -> -0.25068317 | Q4: =DatosSinVinculos!P8 -> 1306994.5 | S4: =(1+DatosSinVinculos!AS8/100)^(1/4) -> 1.017028 | U4: =DatosSinVinculos!AR8 -> 67.035899 | V4: =DatosSinVinculos!AQ8 -> 98.701307 | W4: =DatosSinVinculos!AO8/DatosSinVinculos!AQ8*100*100 -> 65.281135 | X4: =DatosSinVinculos!BO8 -> 57.678432 | Y4: =DatosSinVinculos!CE8 -> 55.515559 | Z4: =DatosSinVinculos!CQ8*DatosSinVinculos!CM8/DatosSinVinculos!CZ8 -> 40.037398 | AA4: =DatosSinVinculos!CQ8 -> 45.320139 | AB4: =DatosSinVinculos!CM8/DatosSinVinculos!CZ8 -> 0.88343501 | AC4: =DatosSinVinculos!DB8/100 -> 0.11739884 | AD4: =DatosSinVinculos!DD8/100 -> 0.01227143
A5: 1986Q3 | B5: =DatosSinVinculos!C9 -> 7007356.7 | C5: =DatosSinVinculos!F9 -> 5113008 | D5: =DatosSinVinculos!L9 -> 1170547.4 | E5: =DatosSinVinculos!J9 -> 1368294.4 | F5: =DatosSinVinculos!H9 -> 1703619.4 | G5: =DatosSinVinculos!R9 -> 3512038.8 | H5: =DatosSinVinculos!X9 -> 702667.69 | I5: =DatosSinVinculos!AC9 -> 13.70306 | K5: =(1+DatosSinVinculos!AL9/100)^(1/4) -> 1 | L5: =K5/(I5/I4) -> 0.96343331 | M5: =DatosSinVinculos!AM9 -> 101.01772 | N5: =DatosSinVinculos!AN9 -> 194.1229 | O5: =DatosSinVinculos!Y9/DatosSinVinculos!D9 -> 0.49977183 | P5: =DatosSinVinculos!AA9*DatosSinVinculos!AN9/DatosSinVinculos!D9 -> -0.35657648 | Q5: =DatosSinVinculos!P9 -> 1308903.8 | S5: =(1+DatosSinVinculos!AS9/100)^(1/4) -> 1.0153397 | U5: =DatosSinVinculos!AR9 -> 67.607951 | V5: =DatosSinVinculos!AQ9 -> 101.54045 | W5: =DatosSinVinculos!AO9/DatosSinVinculos!AQ9*100*100 -> 59.418026 | X5: =DatosSinVinculos!BO9 -> 57.854121 | Y5: =DatosSinVinculos!CE9 -> 55.504955 | Z5: =DatosSinVinculos!CQ9*DatosSinVinculos!CM9/DatosSinVinculos!CZ9 -> 40.001392 | AA5: =DatosSinVinculos!CQ9 -> 45.152834 | AB5: =DatosSinVinculos!CM9/DatosSinVinculos!CZ9 -> 0.885911 | AC5: =DatosSinVinculos!DB9/100 -> 0.11257858 | AD5: =DatosSinVinculos!DD9/100 -> 0.011776982
A6: 1986Q4 | B6: =DatosSinVinculos!C10 -> 7149515.2 | C6: =DatosSinVinculos!F10 -> 5264111.8 | D6: =DatosSinVinculos!L10 -> 1147108.2 | E6: =DatosSinVinculos!J10 -> 1341158.2 | F6: =DatosSinVinculos!H10 -> 1664716.2 | G6: =DatosSinVinculos!R10 -> 3598854.5 | H6: =DatosSinVinculos!X10 -> 783285 | I6: =DatosSinVinculos!AC10 -> 14.119639 | K6: =(1+DatosSinVinculos!AL10/100)^(1/4) -> 1 | L6: =K6/(I6/I5) -> 0.9704965 | M6: =DatosSinVinculos!AM10 -> 101.01812 | N6: =DatosSinVinculos!AN10 -> 201.68778 | O6: =DatosSinVinculos!Y10/DatosSinVinculos!D10 -> 0.080794004 | P6: =DatosSinVinculos!AA10*DatosSinVinculos!AN10/DatosSinVinculos!D10 -> -0.26539461 | Q6: =DatosSinVinculos!P10 -> 1294612.7 | S6: =(1+DatosSinVinculos!AS10/100)^(1/4) -> 1.0150143 | U6: =DatosSinVinculos!AR10 -> 68.426721 | V6: =DatosSinVinculos!AQ10 -> 101.99917 | W6: =DatosSinVinculos!AO10/DatosSinVinculos!AQ10*100*100 -> 58.497207 | X6: =DatosSinVinculos!BO10 -> 58.472157 | Y6: =DatosSinVinculos!CE10 -> 56.541546 | Z6: =DatosSinVinculos!CQ10*DatosSinVinculos!CM10/DatosSinVinculos!CZ10 -> 40.409057 | AA6: =DatosSinVinculos!CQ10 -> 45.625072 | AB6: =DatosSinVinculos!CM10/DatosSinVinculos!CZ10 -> 0.88567657 | AC6: =DatosSinVinculos!DB10/100 -> 0.11481067 | AD6: =DatosSinVinculos!DD10/100 -> 0.011057671
A7: 1987Q1 | B7: =DatosSinVinculos!C11 -> 7210289.2 | C7: =DatosSinVinculos!F11 -> 5258207.6 | D7: =DatosSinVinculos!L11 -> 1164685 | E7: =DatosSinVinculos!J11 -> 1361541.8 | F7: =DatosSinVinculos!H11 -> 1680997.1 | G7: =DatosSinVinculos!R11 -> 3638720 | H7: =DatosSinVinculos!X11 -> 835672.62 | I7: =DatosSinVinculos!AC11 -> 14.937741 | K7: =(1+DatosSinVinculos!AL11/100)^(1/4) -> 1 | L7: =K7/(I7/I6) -> 0.94523259 | M7: =DatosSinVinculos!AM11 -> 101.77644 | N7: =DatosSinVinculos!AN11 -> 206.15159 | O7: =DatosSinVinculos!Y11/DatosSinVinculos!D11 -> 0.47782312 | P7: =DatosSinVinculos!AA11*DatosSinVinculos!AN11/DatosSinVinculos!D11 -> -0.0035186012 | Q7: =DatosSinVinculos!P11 -> 1268757.4 | S7: =(1+DatosSinVinculos!AS11/100)^(1/4) -> 1.0155845 | U7: =DatosSinVinculos!AR11 -> 68.698927 | V7: =DatosSinVinculos!AQ11 -> 105.8586 | W7: =DatosSinVinculos!AO11/DatosSinVinculos!AQ11*100*100 -> 59.828234 | X7: =DatosSinVinculos!BO11 -> 57.653947 | Y7: =DatosSinVinculos!CE11 -> 55.599581 | Z7: =DatosSinVinculos!CQ11*DatosSinVinculos!CM11/DatosSinVinculos!CZ11 -> 40.415528 | AA7: =DatosSinVinculos!CQ11 -> 45.406134 | AB7: =DatosSinVinculos!CM11/DatosSinVinculos!CZ11 -> 0.89008961 | AC7: =DatosSinVinculos!DB11/100 -> 0.11026862 | AD7: =DatosSinVinculos!DD11/100 -> 0.011226604
A8: 1987Q2 | B8: =DatosSinVinculos!C12 -> 7269897.6 | C8: =DatosSinVinculos!F12 -> 5322704 | D8: =DatosSinVinculos!L12 -> 1153915.1 | E8: =DatosSinVinculos!J12 -> 1348803.2 | F8: =DatosSinVinculos!H12 -> 1708406.2 | G8: =DatosSinVinculos!R12 -> 3678417.9 | H8: =DatosSinVinculos!X12 -> 836751.48 | I8: =DatosSinVinculos!AC12 -> 15.739781 | K8: =(1+DatosSinVinculos!AL12/100)^(1/4) -> 1 | L8: =K8/(I8/I7) -> 0.94904372 | M8: =DatosSinVinculos!AM12 -> 103.66926 | N8: =DatosSinVinculos!AN12 -> 214.09661 | O8: =DatosSinVinculos!Y12/DatosSinVinculos!D12 -> -0.061021609 | P8: =DatosSinVinculos!AA12*DatosSinVinculos!AN12/DatosSinVinculos!D12 -> -0.17536798 | Q8: =DatosSinVinculos!P12 -> 1272738.7 | S8: =(1+DatosSinVinculos!AS12/100)^(1/4) -> 1.0174294 | U8: =DatosSinVinculos!AR12 -> 69.827932 | V8: =DatosSinVinculos!AQ12 -> 109.37985 | W8: =DatosSinVinculos!AO12/DatosSinVinculos!AQ12*100*100 -> 63.082915 | X8: =DatosSinVinculos!BO12 -> 57.048032 | Y8: =DatosSinVinculos!CE12 -> 54.824615 | Z8: =DatosSinVinculos!CQ12*DatosSinVinculos!CM12/DatosSinVinculos!CZ12 -> 39.649726 | AA8: =DatosSinVinculos!CQ12 -> 44.58867 | AB8: =DatosSinVinculos!CM12/DatosSinVinculos!CZ12 -> 0.88923322 | AC8: =DatosSinVinculos!DB12/100 -> 0.1112892 | AD8: =DatosSinVinculos!DD12/100 -> 0.0099456502
A9: 1987Q3 | B9: =DatosSinVinculos!C13 -> 7400123.3 | C9: =DatosSinVinculos!F13 -> 5441861.6 | D9: =DatosSinVinculos!L13 -> 1159785.4 | E9: =DatosSinVinculos!J13 -> 1355690.4 | F9: =DatosSinVinculos!H13 -> 1674507.8 | G9: =DatosSinVinculos!R13 -> 3713750.6 | H9: =DatosSinVinculos!X13 -> 827672.84 | I9: =DatosSinVinculos!AC13 -> 16.523743 | K9: =(1+DatosSinVinculos!AL13/100)^(1/4) -> 1 | L9: =K9/(I9/I8) -> 0.95255544 | M9: =DatosSinVinculos!AM13 -> 104.43317 | N9: =DatosSinVinculos!AN13 -> 224.59469 | O9: =DatosSinVinculos!Y13/DatosSinVinculos!D13 -> 0.95860654 | P9: =DatosSinVinculos!AA13*DatosSinVinculos!AN13/DatosSinVinculos!D13 -> -0.31558196 | Q9: =DatosSinVinculos!P13 -> 1276688.1 | S9: =(1+DatosSinVinculos!AS13/100)^(1/4) -> 1.0176205 | U9: =DatosSinVinculos!AR13 -> 70.857014 | V9: =DatosSinVinculos!AQ13 -> 109.59568 | W9: =DatosSinVinculos!AO13/DatosSinVinculos!AQ13*100*100 -> 72.387279 | X9: =DatosSinVinculos!BO13 -> 57.501532 | Y9: =DatosSinVinculos!CE13 -> 55.093929 | Z9: =DatosSinVinculos!CQ13*DatosSinVinculos!CM13/DatosSinVinculos!CZ13 -> 39.50375 | AA9: =DatosSinVinculos!CQ13 -> 44.390838 | AB9: =DatosSinVinculos!CM13/DatosSinVinculos!CZ13 -> 0.88990774 | AC9: =DatosSinVinculos!DB13/100 -> 0.10882341 | AD9: =DatosSinVinculos!DD13/100 -> 0.010752334
A10: 1987Q4 | B10: =DatosSinVinculos!C14 -> 7524887.3 | C10: =DatosSinVinculos!F14 -> 5529010.3 | D10: =DatosSinVinculos!L14 -> 1197187 | E10: =DatosSinVinculos!J14 -> 1399729.8 | F10: =DatosSinVinculos!H14 -> 1742706.1 | G10: =DatosSinVinculos!R14 -> 3787181.3 | H10: =DatosSinVinculos!X14 -> 821985.79 | I10: =DatosSinVinculos!AC14 -> 17.248875 | K10: =(1+DatosSinVinculos!AL14/100)^(1/4) -> 1 | L10: =K10/(I10/I9) -> 0.9579606 | M10: =DatosSinVinculos!AM14 -> 107.469 | N10: =DatosSinVinculos!AN14 -> 232.77113 | O10: =DatosSinVinculos!Y14/DatosSinVinculos!D14 -> -0.1549488 | P10: =DatosSinVinculos!AA14*DatosSinVinculos!AN14/DatosSinVinculos!D14 -> -0.21252041 | Q10: =DatosSinVinculos!P14 -> 1282644.1 | S10: =(1+DatosSinVinculos!AS14/100)^(1/4) -> 1.0193903 | U10: =DatosSinVinculos!AR14 -> 71.884935 | V10: =DatosSinVinculos!AQ14 -> 114.8831 | W10: =DatosSinVinculos!AO14/DatosSinVinculos!AQ14*100*100 -> 96.619955 | X10: =DatosSinVinculos!BO14 -> 58.369602 | Y10: =DatosSinVinculos!CE14 -> 55.773945 | Z10: =DatosSinVinculos!CQ14*DatosSinVinculos!CM14/DatosSinVinculos!CZ14 -> 40.381017 | AA10: =DatosSinVinculos!CQ14 -> 45.122708 | AB10: =DatosSinVinculos!CM14/DatosSinVinculos!CZ14 -> 0.89491563 | AC10: =DatosSinVinculos!DB14/100 -> 0.10543326 | AD10: =DatosSinVinculos!DD14/100 -> 0.011088704
A11: 1988Q1 | B11: =DatosSinVinculos!C15 -> 7702652.6 | C11: =DatosSinVinculos!F15 -> 5654168.5 | D11: =DatosSinVinculos!L15 -> 1207584.6 | E11: =DatosSinVinculos!J15 -> 1411914.8 | F11: =DatosSinVinculos!H15 -> 1758037.8 | G11: =DatosSinVinculos!R15 -> 3845431.1 | H11: =DatosSinVinculos!X15 -> 834436.39 | I11: =DatosSinVinculos!AC15 -> 17.764867 | K11: =(1+DatosSinVinculos!AL15/100)^(1/4) -> 1 | L11: =K11/(I11/I10) -> 0.97095435 | M11: =DatosSinVinculos!AM15 -> 110.94401 | N11: =DatosSinVinculos!AN15 -> 242.35859 | O11: =DatosSinVinculos!Y15/DatosSinVinculos!D15 -> 0.88833285 | P11: =DatosSinVinculos!AA15*DatosSinVinculos!AN15/DatosSinVinculos!D15 -> 0.15160014 | Q11: =DatosSinVinculos!P15 -> 1288744.9 | S11: =(1+DatosSinVinculos!AS15/100)^(1/4) -> 1.0169955 | U11: =DatosSinVinculos!AR15 -> 72.633643 | V11: =DatosSinVinculos!AQ15 -> 116.84042 | W11: =DatosSinVinculos!AO15/DatosSinVinculos!AQ15*100*100 -> 95.286659 | X11: =DatosSinVinculos!BO15 -> 59.75015 | Y11: =DatosSinVinculos!CE15 -> 57.018782 | Z11: =DatosSinVinculos!CQ15*DatosSinVinculos!CM15/DatosSinVinculos!CZ15 -> 40.167396 | AA11: =DatosSinVinculos!CQ15 -> 44.881085 | AB11: =DatosSinVinculos!CM15/DatosSinVinculos!CZ15 -> 0.89497381 | AC11: =DatosSinVinculos!DB15/100 -> 0.10557256 | AD11: =DatosSinVinculos!DD15/100 -> 0.011556967
A12: 1988Q2 | B12: =DatosSinVinculos!C16 -> 7615188.9 | C12: =DatosSinVinculos!F16 -> 5606819.9 | D12: =DatosSinVinculos!L16 -> 1203324.2 | E12: =DatosSinVinculos!J16 -> 1406593.7 | F12: =DatosSinVinculos!H16 -> 1719740.1 | G12: =DatosSinVinculos!R16 -> 3878459.4 | H12: =DatosSinVinculos!X16 -> 929829.32 | I12: =DatosSinVinculos!AC16 -> 18.272964 | K12: =(1+DatosSinVinculos!AL16/100)^(1/4) -> 1 | L12: =K12/(I12/I11) -> 0.97219411 | M12: =DatosSinVinculos!AM16 -> 113.11247 | N12: =DatosSinVinculos!AN16 -> 245.11419 | O12: =DatosSinVinculos!Y16/DatosSinVinculos!D16 -> 0.099846644 | P12: =DatosSinVinculos!AA16*DatosSinVinculos!AN16/DatosSinVinculos!D16 -> -0.037919218 | Q12: =DatosSinVinculos!P16 -> 1313850.8 | S12: =(1+DatosSinVinculos!AS16/100)^(1/4) -> 1.018204 | U12: =DatosSinVinculos!AR16 -> 73.219108 | V12: =DatosSinVinculos!AQ16 -> 120.97412 | W12: =DatosSinVinculos!AO16/DatosSinVinculos!AQ16*100*100 -> 90.928539 | X12: =DatosSinVinculos!BO16 -> 60.918491 | Y12: =DatosSinVinculos!CE16 -> 58.555217 | Z12: =DatosSinVinculos!CQ16*DatosSinVinculos!CM16/DatosSinVinculos!CZ16 -> 40.996318 | AA12: =DatosSinVinculos!CQ16 -> 45.56434 | AB12: =DatosSinVinculos!CM16/DatosSinVinculos!CZ16 -> 0.89974568 | AC12: =DatosSinVinculos!DB16/100 -> 0.10038494 | AD12: =DatosSinVinculos!DD16/100 -> 0.012641645
A13: 1988Q3 | B13: =DatosSinVinculos!C17 -> 8012688.4 | C13: =DatosSinVinculos!F17 -> 5818909.9 | D13: =DatosSinVinculos!L17 -> 1296641.9 | E13: =DatosSinVinculos!J17 -> 1515570 | F13: =DatosSinVinculos!H17 -> 1904754.1 | G13: =DatosSinVinculos!R17 -> 4023983.1 | H13: =DatosSinVinculos!X17 -> 1014242.4 | I13: =DatosSinVinculos!AC17 -> 18.645506 | K13: =(1+DatosSinVinculos!AL17/100)^(1/4) -> 1 | L13: =K13/(I13/I12) -> 0.98001971 | M13: =DatosSinVinculos!AM17 -> 110.99305 | N13: =DatosSinVinculos!AN17 -> 246.51344 | O13: =DatosSinVinculos!Y17/DatosSinVinculos!D17 -> 0.83911232 | P13: =DatosSinVinculos!AA17*DatosSinVinculos!AN17/DatosSinVinculos!D17 -> -0.21787272 | Q13: =DatosSinVinculos!P17 -> 1327985.8 | S13: =(1+DatosSinVinculos!AS17/100)^(1/4) -> 1.020406 | U13: =DatosSinVinculos!AR17 -> 73.99145 | V13: =DatosSinVinculos!AQ17 -> 119.76679 | W13: =DatosSinVinculos!AO17/DatosSinVinculos!AQ17*100*100 -> 86.278786 | X13: =DatosSinVinculos!BO17 -> 62.825195 | Y13: =DatosSinVinculos!CE17 -> 60.993365 | Z13: =DatosSinVinculos!CQ17*DatosSinVinculos!CM17/DatosSinVinculos!CZ17 -> 41.309606 | AA13: =DatosSinVinculos!CQ17 -> 45.833011 | AB13: =DatosSinVinculos!CM17/DatosSinVinculos!CZ17 -> 0.90130684 | AC13: =DatosSinVinculos!DB17/100 -> 0.097853897 | AD13: =DatosSinVinculos!DD17/100 -> 0.013869881
A14: 1988Q4 | B14: =DatosSinVinculos!C18 -> 8240095.7 | C14: =DatosSinVinculos!F18 -> 5975221.5 | D14: =DatosSinVinculos!L18 -> 1332084.1 | E14: =DatosSinVinculos!J18 -> 1557541.8 | F14: =DatosSinVinculos!H18 -> 1914316.3 | G14: =DatosSinVinculos!R18 -> 4107055.3 | H14: =DatosSinVinculos!X18 -> 1017976.7 | I14: =DatosSinVinculos!AC18 -> 19.2251 | K14: =(1+DatosSinVinculos!AL18/100)^(1/4) -> 1 | L14: =K14/(I14/I13) -> 0.96985223 | M14: =DatosSinVinculos!AM18 -> 109.63786 | N14: =DatosSinVinculos!AN18 -> 246.01787 | O14: =DatosSinVinculos!Y18/DatosSinVinculos!D18 -> 0.47687581 | P14: =DatosSinVinculos!AA18*DatosSinVinculos!AN18/DatosSinVinculos!D18 -> -0.13982125 | Q14: =DatosSinVinculos!P18 -> 1347278.9 | S14: =(1+DatosSinVinculos!AS18/100)^(1/4) -> 1.0218548 | U14: =DatosSinVinculos!AR18 -> 74.795777 | V14: =DatosSinVinculos!AQ18 -> 123.66507 | W14: =DatosSinVinculos!AO18/DatosSinVinculos!AQ18*100*100 -> 119.139 | X14: =DatosSinVinculos!BO18 -> 62.213857 | Y14: =DatosSinVinculos!CE18 -> 60.631074 | Z14: =DatosSinVinculos!CQ18*DatosSinVinculos!CM18/DatosSinVinculos!CZ18 -> 41.162676 | AA14: =DatosSinVinculos!CQ18 -> 45.156222 | AB14: =DatosSinVinculos!CM18/DatosSinVinculos!CZ18 -> 0.91156155 | AC14: =DatosSinVinculos!DB18/100 -> 0.088620731 | AD14: =DatosSinVinculos!DD18/100 -> 0.013721413
A15: 1989Q1 | B15: =DatosSinVinculos!C19 -> 8382158.6 | C15: =DatosSinVinculos!F19 -> 6118884.5 | D15: =DatosSinVinculos!L19 -> 1296970 | E15: =DatosSinVinculos!J19 -> 1516727.9 | F15: =DatosSinVinculos!H19 -> 1870046.2 | G15: =DatosSinVinculos!R19 -> 4274923.3 | H15: =DatosSinVinculos!X19 -> 1129914 | I15: =DatosSinVinculos!AC19 -> 20.055607 | K15: =(1+DatosSinVinculos!AL19/100)^(1/4) -> 1 | L15: =K15/(I15/I14) -> 0.95858978 | M15: =DatosSinVinculos!AM19 -> 107.5739 | N15: =DatosSinVinculos!AN19 -> 247.5825 | O15: =DatosSinVinculos!Y19/DatosSinVinculos!D19 -> 0.2064192 | P15: =DatosSinVinculos!AA19*DatosSinVinculos!AN19/DatosSinVinculos!D19 -> 0.040510029 | Q15: =DatosSinVinculos!P19 -> 1362102.9 | S15: =(1+DatosSinVinculos!AS19/100)^(1/4) -> 1.0237152 | U15: =DatosSinVinculos!AR19 -> 76.094931 | V15: =DatosSinVinculos!AQ19 -> 125.12737 | W15: =DatosSinVinculos!AO19/DatosSinVinculos!AQ19*100*100 -> 117.74668 | X15: =DatosSinVinculos!BO19 -> 62.055836 | Y15: =DatosSinVinculos!CE19 -> 60.594894 | Z15: =DatosSinVinculos!CQ19*DatosSinVinculos!CM19/DatosSinVinculos!CZ19 -> 41.492895 | AA15: =DatosSinVinculos!CQ19 -> 45.2877 | AB15: =DatosSinVinculos!CM19/DatosSinVinculos!CZ19 -> 0.91620673 | AC15: =DatosSinVinculos!DB19/100 -> 0.084174725 | AD15: =DatosSinVinculos!DD19/100 -> 0.01398009
A16: 1989Q2 | B16: =DatosSinVinculos!C20 -> 8677204.3 | C16: =DatosSinVinculos!F20 -> 6345610.9 | D16: =DatosSinVinculos!L20 -> 1375648.8 | E16: =DatosSinVinculos!J20 -> 1608145.1 | F16: =DatosSinVinculos!H20 -> 1915124.2 | G16: =DatosSinVinculos!R20 -> 4386562.8 | H16: =DatosSinVinculos!X20 -> 1216686.7 | I16: =DatosSinVinculos!AC20 -> 21.0148 | J16: =DatosSinVinculos!AE20 -> 22.609742 | K16: =(1+DatosSinVinculos!AL20/100)^(1/4) -> 1 | L16: =K16/(I16/I15) -> 0.95435631 | M16: =DatosSinVinculos!AM20 -> 104.11224 | N16: =DatosSinVinculos!AN20 -> 255.21177 | O16: =DatosSinVinculos!Y20/DatosSinVinculos!D20 -> 0.52583564 | P16: =DatosSinVinculos!AA20*DatosSinVinculos!AN20/DatosSinVinculos!D20 -> -0.28257444 | Q16: =DatosSinVinculos!P20 -> 1370135.6 | S16: =(1+DatosSinVinculos!AS20/100)^(1/4) -> 1.0235951 | U16: =DatosSinVinculos!AR20 -> 76.267281 | V16: =DatosSinVinculos!AQ20 -> 122.52559 | W16: =DatosSinVinculos!AO20/DatosSinVinculos!AQ20*100*100 -> 103.37977 | X16: =DatosSinVinculos!BO20 -> 62.587467 | Y16: =DatosSinVinculos!CE20 -> 60.968171 | Z16: =DatosSinVinculos!CQ20*DatosSinVinculos!CM20/DatosSinVinculos!CZ20 -> 41.696586 | AA16: =DatosSinVinculos!CQ20 -> 45.422687 | AB16: =DatosSinVinculos!CM20/DatosSinVinculos!CZ20 -> 0.91796828 | AC16: =DatosSinVinculos!DB20/100 -> 0.082116671 | AD16: =DatosSinVinculos!DD20/100 -> 0.015520026
A17: 1989Q3 | B17: =DatosSinVinculos!C21 -> 8827126.7 | C17: =DatosSinVinculos!F21 -> 6442065.6 | D17: =DatosSinVinculos!L21 -> 1385912.3 | E17: =DatosSinVinculos!J21 -> 1619733.6 | F17: =DatosSinVinculos!H21 -> 1936501.5 | G17: =DatosSinVinculos!R21 -> 4378634.6 | H17: =DatosSinVinculos!X21 -> 1267947.3 | I17: =DatosSinVinculos!AC21 -> 22.114488 | J17: =DatosSinVinculos!AE21 -> 23.848318 | K17: =(1+DatosSinVinculos!AL21/100)^(1/4) -> 1 | L17: =K17/(I17/I16) -> 0.95027296 | M17: =DatosSinVinculos!AM21 -> 110.86943 | N17: =DatosSinVinculos!AN21 -> 276.36148 | O17: =DatosSinVinculos!Y21/DatosSinVinculos!D21 -> 0.45797618 | P17: =DatosSinVinculos!AA21*DatosSinVinculos!AN21/DatosSinVinculos!D21 -> -0.34952328 | Q17: =DatosSinVinculos!P21 -> 1376539 | S17: =(1+DatosSinVinculos!AS21/100)^(1/4) -> 1.0215782 | U17: =DatosSinVinculos!AR21 -> 77.116535 | V17: =DatosSinVinculos!AQ21 -> 126.54436 | W17: =DatosSinVinculos!AO21/DatosSinVinculos!AQ21*100*100 -> 97.199119 | X17: =DatosSinVinculos!BO21 -> 62.863085 | Y17: =DatosSinVinculos!CE21 -> 60.76921 | Z17: =DatosSinVinculos!CQ21*DatosSinVinculos!CM21/DatosSinVinculos!CZ21 -> 41.405932 | AA17: =DatosSinVinculos!CQ21 -> 44.925886 | AB17: =DatosSinVinculos!CM21/DatosSinVinculos!CZ21 -> 0.92164978 | AC17: =DatosSinVinculos!DB21/100 -> 0.077977528 | AD17: =DatosSinVinculos!DD21/100 -> 0.01393852
A18: 1989Q4 | B18: =DatosSinVinculos!C22 -> 8835353.4 | C18: =DatosSinVinculos!F22 -> 6426061.4 | D18: =DatosSinVinculos!L22 -> 1375162.7 | E18: =DatosSinVinculos!J22 -> 1607971.8 | F18: =DatosSinVinculos!H22 -> 1947272.3 | G18: =DatosSinVinculos!R22 -> 4421667.5 | H18: =DatosSinVinculos!X22 -> 1316344 | I18: =DatosSinVinculos!AC22 -> 23.29051 | J18: =DatosSinVinculos!AE22 -> 25.142778 | K18: =(1+DatosSinVinculos!AL22/100)^(1/4) -> 1 | L18: =K18/(I18/I17) -> 0.94950639 | M18: =DatosSinVinculos!AM22 -> 111.65457 | N18: =DatosSinVinculos!AN22 -> 288.29583 | O18: =DatosSinVinculos!Y22/DatosSinVinculos!D22 -> 0.48224617 | P18: =DatosSinVinculos!AA22*DatosSinVinculos!AN22/DatosSinVinculos!D22 -> -0.19751299 | Q18: =DatosSinVinculos!P22 -> 1374422.1 | S18: =(1+DatosSinVinculos!AS22/100)^(1/4) -> 1.0208887 | U18: =DatosSinVinculos!AR22 -> 78.197229 | V18: =DatosSinVinculos!AQ22 -> 130.18506 | W18: =DatosSinVinculos!AO22/DatosSinVinculos!AQ22*100*100 -> 91.408341 | X18: =DatosSinVinculos!BO22 -> 62.974703 | Y18: =DatosSinVinculos!CE22 -> 60.982742 | Z18: =DatosSinVinculos!CQ22*DatosSinVinculos!CM22/DatosSinVinculos!CZ22 -> 41.075849 | AA18: =DatosSinVinculos!CQ22 -> 44.629538 | AB18: =DatosSinVinculos!CM22/DatosSinVinculos!CZ22 -> 0.92037361 | AC18: =DatosSinVinculos!DB22/100 -> 0.079637856 | AD18: =DatosSinVinculos!DD22/100 -> 0.015116383
A19: 1990Q1 | B19: =DatosSinVinculos!C23 -> 9038298.7 | C19: =DatosSinVinculos!F23 -> 6610163.1 | D19: =DatosSinVinculos!L23 -> 1408871.1 | E19: =DatosSinVinculos!J23 -> 1648024.6 | F19: =DatosSinVinculos!H23 -> 1968170 | G19: =DatosSinVinculos!R23 -> 4448058.8 | H19: =DatosSinVinculos!X23 -> 1297165.9 | I19: =DatosSinVinculos!AC23 -> 24.75793 | J19: =DatosSinVinculos!AE23 -> 26.704044 | K19: =(1+DatosSinVinculos!AL23/100)^(1/4) -> 1 | L19: =K19/(I19/I18) -> 0.94072931 | M19: =DatosSinVinculos!AM23 -> 115.15757 | N19: =DatosSinVinculos!AN23 -> 295.38281 | O19: =DatosSinVinculos!Y23/DatosSinVinculos!D23 -> 0.022183049 | P19: =DatosSinVinculos!AA23*DatosSinVinculos!AN23/DatosSinVinculos!D23 -> -0.007590741 | Q19: =DatosSinVinculos!P23 -> 1381518.6 | S19: =(1+DatosSinVinculos!AS23/100)^(1/4) -> 1.0203885 | U19: =DatosSinVinculos!AR23 -> 79.19936 | V19: =DatosSinVinculos!AQ23 -> 138.50692 | W19: =DatosSinVinculos!AO23/DatosSinVinculos!AQ23*100*100 -> 80.1404 | X19: =DatosSinVinculos!BO23 -> 63.112426 | Y19: =DatosSinVinculos!CE23 -> 60.973819 | Z19: =DatosSinVinculos!CQ23*DatosSinVinculos!CM23/DatosSinVinculos!CZ23 -> 41.96913 | AA19: =DatosSinVinculos!CQ23 -> 45.450788 | AB19: =DatosSinVinculos!CM23/DatosSinVinculos!CZ23 -> 0.92339718 | AC19: =DatosSinVinculos!DB23/100 -> 0.076585788 | AD19: =DatosSinVinculos!DD23/100 -> 0.013797052
A20: 1990Q2 | B20: =DatosSinVinculos!C24 -> 8952797.5 | C20: =DatosSinVinculos!F24 -> 6555316.5 | D20: =DatosSinVinculos!L24 -> 1398934.8 | E20: =DatosSinVinculos!J24 -> 1635526.5 | F20: =DatosSinVinculos!H24 -> 1926418.7 | G20: =DatosSinVinculos!R24 -> 4405484.4 | H20: =DatosSinVinculos!X24 -> 1265468.7 | I20: =DatosSinVinculos!AC24 -> 26.25219 | J20: =DatosSinVinculos!AE24 -> 28.277292 | K20: =(1+DatosSinVinculos!AL24/100)^(1/4) -> 1 | L20: =K20/(I20/I19) -> 0.94308053 | M20: =DatosSinVinculos!AM24 -> 111.12789 | N20: =DatosSinVinculos!AN24 -> 296.72683 | O20: =DatosSinVinculos!Y24/DatosSinVinculos!D24 -> 0.047251738 | P20: =DatosSinVinculos!AA24*DatosSinVinculos!AN24/DatosSinVinculos!D24 -> -0.015117239 | Q20: =DatosSinVinculos!P24 -> 1375095.2 | S20: =(1+DatosSinVinculos!AS24/100)^(1/4) -> 1.0204953 | U20: =DatosSinVinculos!AR24 -> 79.578797 | V20: =DatosSinVinculos!AQ24 -> 140.07896 | W20: =DatosSinVinculos!AO24/DatosSinVinculos!AQ24*100*100 -> 86.379855 | X20: =DatosSinVinculos!BO24 -> 63.481108 | Y20: =DatosSinVinculos!CE24 -> 61.079146 | Z20: =DatosSinVinculos!CQ24*DatosSinVinculos!CM24/DatosSinVinculos!CZ24 -> 41.232927 | AA20: =DatosSinVinculos!CQ24 -> 44.789176 | AB20: =DatosSinVinculos!CM24/DatosSinVinculos!CZ24 -> 0.92060026 | AC20: =DatosSinVinculos!DB24/100 -> 0.079742158 | AD20: =DatosSinVinculos!DD24/100 -> 0.012644928
A21: 1990Q3 | B21: =DatosSinVinculos!C25 -> 8879835.8 | C21: =DatosSinVinculos!F25 -> 6497495.5 | D21: =DatosSinVinculos!L25 -> 1375421.4 | E21: =DatosSinVinculos!J25 -> 1607205.2 | F21: =DatosSinVinculos!H25 -> 1886916.4 | G21: =DatosSinVinculos!R25 -> 4445893 | H21: =DatosSinVinculos!X25 -> 1253350 | I21: =DatosSinVinculos!AC25 -> 27.958891 | J21: =DatosSinVinculos!AE25 -> 29.875971 | K21: =(1+DatosSinVinculos!AL25/100)^(1/4) -> 1 | L21: =K21/(I21/I20) -> 0.93895677 | M21: =DatosSinVinculos!AM25 -> 110.66819 | N21: =DatosSinVinculos!AN25 -> 302.36525 | O21: =DatosSinVinculos!Y25/DatosSinVinculos!D25 -> 0.034717825 | P21: =DatosSinVinculos!AA25*DatosSinVinculos!AN25/DatosSinVinculos!D25 -> -0.026913033 | Q21: =DatosSinVinculos!P25 -> 1378754.7 | S21: =(1+DatosSinVinculos!AS25/100)^(1/4) -> 1.0198407 | U21: =DatosSinVinculos!AR25 -> 80.113972 | V21: =DatosSinVinculos!AQ25 -> 145.98615 | W21: =DatosSinVinculos!AO25/DatosSinVinculos!AQ25*100*100 -> 90.419537 | X21: =DatosSinVinculos!BO25 -> 63.930433 | Y21: =DatosSinVinculos!CE25 -> 61.485044 | Z21: =DatosSinVinculos!CQ25*DatosSinVinculos!CM25/DatosSinVinculos!CZ25 -> 41.502448 | AA21: =DatosSinVinculos!CQ25 -> 45.075109 | AB21: =DatosSinVinculos!CM25/DatosSinVinculos!CZ25 -> 0.92073983 | AC21: =DatosSinVinculos!DB25/100 -> 0.079191542 | AD21: =DatosSinVinculos!DD25/100 -> 0.012971941
A22: 1990Q4 | B22: =DatosSinVinculos!C26 -> 8990639.5 | C22: =DatosSinVinculos!F26 -> 6617840.6 | D22: =DatosSinVinculos!L26 -> 1304839.9 | E22: =DatosSinVinculos!J26 -> 1525775.2 | F22: =DatosSinVinculos!H26 -> 1876114.4 | G22: =DatosSinVinculos!R26 -> 4538235.7 | H22: =DatosSinVinculos!X26 -> 1236898.8 | I22: =DatosSinVinculos!AC26 -> 29.99697 | J22: =DatosSinVinculos!AE26 -> 31.672607 | K22: =(1+DatosSinVinculos!AL26/100)^(1/4) -> 1 | L22: =K22/(I22/I21) -> 0.93205719 | M22: =DatosSinVinculos!AM26 -> 113.86201 | N22: =DatosSinVinculos!AN26 -> 324.25016 | O22: =DatosSinVinculos!Y26/DatosSinVinculos!D26 -> 0.044160997 | P22: =DatosSinVinculos!AA26*DatosSinVinculos!AN26/DatosSinVinculos!D26 -> -0.0069341009 | Q22: =DatosSinVinculos!P26 -> 1394597.3 | S22: =(1+DatosSinVinculos!AS26/100)^(1/4) -> 1.0196329 | U22: =DatosSinVinculos!AR26 -> 80.475502 | V22: =DatosSinVinculos!AQ26 -> 152.2357 | W22: =DatosSinVinculos!AO26/DatosSinVinculos!AQ26*100*100 -> 77.511384 | X22: =DatosSinVinculos!BO26 -> 64.568135 | Y22: =DatosSinVinculos!CE26 -> 62.216473 | Z22: =DatosSinVinculos!CQ26*DatosSinVinculos!CM26/DatosSinVinculos!CZ26 -> 41.521039 | AA22: =DatosSinVinculos!CQ26 -> 45.20671 | AB22: =DatosSinVinculos!CM26/DatosSinVinculos!CZ26 -> 0.91847071 | AC22: =DatosSinVinculos!DB26/100 -> 0.081306387 | AD22: =DatosSinVinculos!DD26/100 -> 0.011266969
A23: 1991Q1 | B23: =DatosSinVinculos!C27 -> 9246792.4 | C23: =DatosSinVinculos!F27 -> 6684179.3 | D23: =DatosSinVinculos!L27 -> 1548480.3 | E23: =DatosSinVinculos!J27 -> 1811745 | F23: =DatosSinVinculos!H27 -> 2120260.9 | G23: =DatosSinVinculos!R27 -> 4640272.2 | H23: =DatosSinVinculos!X27 -> 1223791.9 | I23: =DatosSinVinculos!AC27 -> 30.766175 | J23: =DatosSinVinculos!AE27 -> 32.839646 | K23: =(1+DatosSinVinculos!AL27/100)^(1/4) -> 1 | L23: =K23/(I23/I22) -> 0.97499835 | M23: =DatosSinVinculos!AM27 -> 113.7289 | N23: =DatosSinVinculos!AN27 -> 338.29597 | O23: =DatosSinVinculos!Y27/DatosSinVinculos!D27 -> -0.012672744 | P23: =DatosSinVinculos!AA27*DatosSinVinculos!AN27/DatosSinVinculos!D27 -> 0.027443143 | Q23: =DatosSinVinculos!P27 -> 1402919.4 | S23: =(1+DatosSinVinculos!AS27/100)^(1/4) -> 1.0167852 | U23: =DatosSinVinculos!AR27 -> 80.837642 | V23: =DatosSinVinculos!AQ27 -> 148.11237 | W23: =DatosSinVinculos!AO27/DatosSinVinculos!AQ27*100*100 -> 74.492992 | X23: =DatosSinVinculos!BO27 -> 67.212794 | Y23: =DatosSinVinculos!CE27 -> 65.279735 | Z23: =DatosSinVinculos!CQ27*DatosSinVinculos!CM27/DatosSinVinculos!CZ27 -> 40.833698 | AA23: =DatosSinVinculos!CQ27 -> 44.593488 | AB23: =DatosSinVinculos!CM27/DatosSinVinculos!CZ27 -> 0.91568746 | AC23: =DatosSinVinculos!DB27/100 -> 0.083954363 | AD23: =DatosSinVinculos!DD27/100 -> 0.013591157
A24: 1991Q2 | B24: =DatosSinVinculos!C28 -> 9573804.8 | C24: =DatosSinVinculos!F28 -> 6928891.7 | D24: =DatosSinVinculos!L28 -> 1560182.5 | E24: =DatosSinVinculos!J28 -> 1824832.2 | F24: =DatosSinVinculos!H28 -> 2166825.8 | G24: =DatosSinVinculos!R28 -> 4873221.8 | H24: =DatosSinVinculos!X28 -> 1236590.8 | I24: =DatosSinVinculos!AC28 -> 32.524881 | J24: =DatosSinVinculos!AE28 -> 34.506057 | K24: =(1+DatosSinVinculos!AL28/100)^(1/4) -> 1 | L24: =K24/(I24/I23) -> 0.94592736 | M24: =DatosSinVinculos!AM28 -> 104.89375 | N24: =DatosSinVinculos!AN28 -> 341.66226 | O24: =DatosSinVinculos!Y28/DatosSinVinculos!D28 -> 0.065339062 | P24: =DatosSinVinculos!AA28*DatosSinVinculos!AN28/DatosSinVinculos!D28 -> 0.0026499321 | Q24: =DatosSinVinculos!P28 -> 1425340.1 | S24: =(1+DatosSinVinculos!AS28/100)^(1/4) -> 1.0150621 | U24: =DatosSinVinculos!AR28 -> 81.661978 | V24: =DatosSinVinculos!AQ28 -> 141.96385 | W24: =DatosSinVinculos!AO28/DatosSinVinculos!AQ28*100*100 -> 74.666897 | X24: =DatosSinVinculos!BO28 -> 66.414912 | Y24: =DatosSinVinculos!CE28 -> 64.256291 | Z24: =DatosSinVinculos!CQ28*DatosSinVinculos!CM28/DatosSinVinculos!CZ28 -> 42.039402 | AA24: =DatosSinVinculos!CQ28 -> 45.785248 | AB24: =DatosSinVinculos!CM28/DatosSinVinculos!CZ28 -> 0.91818661 | AC24: =DatosSinVinculos!DB28/100 -> 0.082417879 | AD24: =DatosSinVinculos!DD28/100 -> 0.015387958
A25: 1991Q3 | B25: =DatosSinVinculos!C29 -> 9681625.5 | C25: =DatosSinVinculos!F29 -> 7005547.3 | D25: =DatosSinVinculos!L29 -> 1464902.2 | E25: =DatosSinVinculos!J29 -> 1710970.2 | F25: =DatosSinVinculos!H29 -> 2183517.7 | G25: =DatosSinVinculos!R29 -> 4826935.6 | H25: =DatosSinVinculos!X29 -> 1266081.9 | I25: =DatosSinVinculos!AC29 -> 34.043321 | J25: =DatosSinVinculos!AE29 -> 36.133974 | K25: =(1+DatosSinVinculos!AL29/100)^(1/4) -> 1 | L25: =K25/(I25/I24) -> 0.95539684 | M25: =DatosSinVinculos!AM29 -> 103.23819 | N25: =DatosSinVinculos!AN29 -> 351.45355 | O25: =DatosSinVinculos!Y29/DatosSinVinculos!D29 -> -0.008499886 | P25: =DatosSinVinculos!AA29*DatosSinVinculos!AN29/DatosSinVinculos!D29 -> -0.025711648 | Q25: =DatosSinVinculos!P29 -> 1433095 | S25: =(1+DatosSinVinculos!AS29/100)^(1/4) -> 1.0141749 | U25: =DatosSinVinculos!AR29 -> 81.953174 | V25: =DatosSinVinculos!AQ29 -> 142.75817 | W25: =DatosSinVinculos!AO29/DatosSinVinculos!AQ29*100*100 -> 71.682995 | X25: =DatosSinVinculos!BO29 -> 66.138725 | Y25: =DatosSinVinculos!CE29 -> 64.72534 | Z25: =DatosSinVinculos!CQ29*DatosSinVinculos!CM29/DatosSinVinculos!CZ29 -> 41.072519 | AA25: =DatosSinVinculos!CQ29 -> 45.006127 | AB25: =DatosSinVinculos!CM29/DatosSinVinculos!CZ29 -> 0.91259839 | AC25: =DatosSinVinculos!DB29/100 -> 0.087748013 | AD25: =DatosSinVinculos!DD29/100 -> 0.015300954
A26: 1991Q4 | B26: =DatosSinVinculos!C30 -> 10140087 | C26: =DatosSinVinculos!F30 -> 7282407.6 | D26: =DatosSinVinculos!L30 -> 1591092.3 | E26: =DatosSinVinculos!J30 -> 1859760.2 | F26: =DatosSinVinculos!H30 -> 2291694.9 | G26: =DatosSinVinculos!R30 -> 5069517.6 | H26: =DatosSinVinculos!X30 -> 1317183.3 | I26: =DatosSinVinculos!AC30 -> 35.387592 | J26: =DatosSinVinculos!AE30 -> 37.623505 | K26: =(1+DatosSinVinculos!AL30/100)^(1/4) -> 1 | L26: =K26/(I26/I25) -> 0.96201292 | M26: =DatosSinVinculos!AM30 -> 103.64495 | N26: =DatosSinVinculos!AN30 -> 364.79476 | O26: =DatosSinVinculos!Y30/DatosSinVinculos!D30 -> 0.099223293 | P26: =DatosSinVinculos!AA30*DatosSinVinculos!AN30/DatosSinVinculos!D30 -> -0.012731246 | Q26: =DatosSinVinculos!P30 -> 1459068.3 | S26: =(1+DatosSinVinculos!AS30/100)^(1/4) -> 1.0123452 | U26: =DatosSinVinculos!AR30 -> 82.272863 | V26: =DatosSinVinculos!AQ30 -> 145.32653 | W26: =DatosSinVinculos!AO30/DatosSinVinculos!AQ30*100*100 -> 72.480456 | X26: =DatosSinVinculos!BO30 -> 67.803189 | Y26: =DatosSinVinculos!CE30 -> 65.426925 | Z26: =DatosSinVinculos!CQ30*DatosSinVinculos!CM30/DatosSinVinculos!CZ30 -> 42.271762 | AA26: =DatosSinVinculos!CQ30 -> 45.872569 | AB26: =DatosSinVinculos!CM30/DatosSinVinculos!CZ30 -> 0.92150414 | AC26: =DatosSinVinculos!DB30/100 -> 0.077969121 | AD26: =DatosSinVinculos!DD30/100 -> 0.017022933
A27: 1992Q1 | B27: =DatosSinVinculos!C31 -> 10410176 | C27: =DatosSinVinculos!F31 -> 7547058.5 | D27: =DatosSinVinculos!L31 -> 1519896.8 | E27: =DatosSinVinculos!J31 -> 1780884.5 | F27: =DatosSinVinculos!H31 -> 2275554.3 | G27: =DatosSinVinculos!R31 -> 5248878.9 | H27: =DatosSinVinculos!X31 -> 1442114.7 | I27: =DatosSinVinculos!AC31 -> 36.575665 | J27: =DatosSinVinculos!AE31 -> 38.867013 | K27: =(1+DatosSinVinculos!AL31/100)^(1/4) -> 1 | L27: =K27/(I27/I26) -> 0.96751741 | M27: =DatosSinVinculos!AM31 -> 99.051597 | N27: =DatosSinVinculos!AN31 -> 355.5525 | O27: =DatosSinVinculos!Y31/DatosSinVinculos!D31 -> -0.069241916 | P27: =DatosSinVinculos!AA31*DatosSinVinculos!AN31/DatosSinVinculos!D31 -> 0.0076415606 | Q27: =DatosSinVinculos!P31 -> 1483183.8 | S27: =(1+DatosSinVinculos!AS31/100)^(1/4) -> 1.0104337 | U27: =DatosSinVinculos!AR31 -> 82.661325 | V27: =DatosSinVinculos!AQ31 -> 145.59176 | W27: =DatosSinVinculos!AO31/DatosSinVinculos!AQ31*100*100 -> 68.227306 | X27: =DatosSinVinculos!BO31 -> 68.715838 | Y27: =DatosSinVinculos!CE31 -> 66.881172 | Z27: =DatosSinVinculos!CQ31*DatosSinVinculos!CM31/DatosSinVinculos!CZ31 -> 42.161079 | AA27: =DatosSinVinculos!CQ31 -> 45.499042 | AB27: =DatosSinVinculos!CM31/DatosSinVinculos!CZ31 -> 0.92663663 | AC27: =DatosSinVinculos!DB31/100 -> 0.072589855 | AD27: =DatosSinVinculos!DD31/100 -> 0.017466343
... A55: 1999Q1 | B55: =DatosSinVinculos!C59 -> 15248765 | C55: =DatosSinVinculos!F59 -> 10668137 | D55: =DatosSinVinculos!L59 -> 2929651.2 | E55: =DatosSinVinculos!J59 -> 3215236.1 | F55: =DatosSinVinculos!H59 -> 3705328.3 | G55: =DatosSinVinculos!R59 -> 8514291.8 | H55: =DatosSinVinculos!X59 -> 2527778.4 | I55: =DatosSinVinculos!AC59 -> 63.833051 | J55: =DatosSinVinculos!AE59 -> 71.728373 | K55: =(1+DatosSinVinculos!AL59/100)^(1/4) -> 1.0179969 | L55: =K55/(I55/I54) -> 1.0112866 | M55: =DatosSinVinculos!AM59 -> 79.003184 | N55: =DatosSinVinculos!AN59 -> 487.45619 | O55: =DatosSinVinculos!Y59/DatosSinVinculos!D59 -> 0.042580996 | P55: =DatosSinVinculos!AA59*DatosSinVinculos!AN59/DatosSinVinculos!D59 -> 0.025914285 | Q55: =DatosSinVinculos!P59 -> 1879955.1 | S55: =(1+DatosSinVinculos!AS59/100)^(1/4) -> 1.0122812 | U55: =DatosSinVinculos!AR59 -> 102.1043 | V55: =DatosSinVinculos!AQ59 -> 148.06775 | W55: =DatosSinVinculos!AO59/DatosSinVinculos!AQ59*100*100 -> 43.223457 | X55: =DatosSinVinculos!BO59 -> 89.843928 | Y55: =DatosSinVinculos!CE59 -> 90.77028 | Z55: =DatosSinVinculos!CQ59*DatosSinVinculos!CM59/DatosSinVinculos!CZ59 -> 40.475254 | AA55: =DatosSinVinculos!CQ59 -> 44.431693 | AB55: =DatosSinVinculos!CM59/DatosSinVinculos!CZ59 -> 0.91095456 | AC55: =DatosSinVinculos!DB59/100 -> 0.089203609 | AD55: =DatosSinVinculos!DD59/100 -> 0.013753213
A56: 1999Q2 | B56: =DatosSinVinculos!C60 -> 15293593 | C56: =DatosSinVinculos!F60 -> 10759530 | D56: =DatosSinVinculos!L60 -> 2895107.3 | E56: =DatosSinVinculos!J60 -> 3208271.1 | F56: =DatosSinVinculos!H60 -> 3667493.1 | G56: =DatosSinVinculos!R60 -> 8485849.1 | H56: =DatosSinVinculos!X60 -> 2473349.4 | I56: =DatosSinVinculos!AC60 -> 64.388661 | J56: =DatosSinVinculos!AE60 -> 72.33917 | K56: =(1+DatosSinVinculos!AL60/100)^(1/4) -> 1.0148405 | L56: =K56/(I56/I55) -> 1.0060834 | M56: =DatosSinVinculos!AM60 -> 78.759715 | N56: =DatosSinVinculos!AN60 -> 489.72082 | O56: =DatosSinVinculos!Y60/DatosSinVinculos!D60 -> 0.036446317 | P56: =DatosSinVinculos!AA60*DatosSinVinculos!AN60/DatosSinVinculos!D60 -> -0.003033694 | Q56: =DatosSinVinculos!P60 -> 1896087.5 | R56: =(1+DatosSinVinculos!AS60/100)^(1/4)*(1+DatosSinVinculos!AV60/10000)^(1/4) -> 1.0172196 | S56: =(1+DatosSinVinculos!AS60/100)^(1/4) -> 1.0124443 | T56: =(1+DatosSinVinculos!AV60/10000)^(1/4) -> 1.0047165 | U56: =DatosSinVinculos!AR60 -> 102.9782 | V56: =DatosSinVinculos!AQ60 -> 148.15341 | W56: =DatosSinVinculos!AO60/DatosSinVinculos!AQ60*100*100 -> 44.998402 | X56: =DatosSinVinculos!BO60 -> 90.323546 | Y56: =DatosSinVinculos!CE60 -> 91.179577 | Z56: =DatosSinVinculos!CQ60*DatosSinVinculos!CM60/DatosSinVinculos!CZ60 -> 39.762391 | AA56: =DatosSinVinculos!CQ60 -> 44.310492 | AB56: =DatosSinVinculos!CM60/DatosSinVinculos!CZ60 -> 0.89735837 | AC56: =DatosSinVinculos!DB60/100 -> 0.10318561 | AD56: =DatosSinVinculos!DD60/100 -> 0.013135895
A57: 1999Q3 | B57: =DatosSinVinculos!C61 -> 15623495 | C57: =DatosSinVinculos!F61 -> 11007274 | D57: =DatosSinVinculos!L61 -> 2934404.1 | E57: =DatosSinVinculos!J61 -> 3243861.8 | F57: =DatosSinVinculos!H61 -> 3707208 | G57: =DatosSinVinculos!R61 -> 8703342.5 | H57: =DatosSinVinculos!X61 -> 2481619.6 | I57: =DatosSinVinculos!AC61 -> 64.71632 | J57: =DatosSinVinculos!AE61 -> 72.645775 | K57: =(1+DatosSinVinculos!AL61/100)^(1/4) -> 1.0122722 | L57: =K57/(I57/I56) -> 1.0071471 | M57: =DatosSinVinculos!AM61 -> 83.643016 | N57: =DatosSinVinculos!AN61 -> 518.00738 | O57: =DatosSinVinculos!Y61/DatosSinVinculos!D61 -> 0.013229351 | P57: =DatosSinVinculos!AA61*DatosSinVinculos!AN61/DatosSinVinculos!D61 -> -0.018951788 | Q57: =DatosSinVinculos!P61 -> 1910821.4 | R57: =(1+DatosSinVinculos!AS61/100)^(1/4)*(1+DatosSinVinculos!AV61/10000)^(1/4) -> 1.0180559 | S57: =(1+DatosSinVinculos!AS61/100)^(1/4) -> 1.0133348 | T57: =(1+DatosSinVinculos!AV61/10000)^(1/4) -> 1.004659 | U57: =DatosSinVinculos!AR61 -> 104.17784 | V57: =DatosSinVinculos!AQ61 -> 149.34177 | W57: =DatosSinVinculos!AO61/DatosSinVinculos!AQ61*100*100 -> 50.889982 | X57: =DatosSinVinculos!BO61 -> 90.949929 | Y57: =DatosSinVinculos!CE61 -> 91.80606 | Z57: =DatosSinVinculos!CQ61*DatosSinVinculos!CM61/DatosSinVinculos!CZ61 -> 39.954431 | AA57: =DatosSinVinculos!CQ61 -> 44.678307 | AB57: =DatosSinVinculos!CM61/DatosSinVinculos!CZ61 -> 0.89426913 | AC57: =DatosSinVinculos!DB61/100 -> 0.10493706 | AD57: =DatosSinVinculos!DD61/100 -> 0.01442086
A58: 1999Q4 | B58: =DatosSinVinculos!C62 -> 15991228 | C58: =DatosSinVinculos!F62 -> 11257942 | D58: =DatosSinVinculos!L62 -> 2927068.6 | E58: =DatosSinVinculos!J62 -> 3246565.1 | F58: =DatosSinVinculos!H62 -> 3823042.7 | G58: =DatosSinVinculos!R62 -> 8934523.8 | H58: =DatosSinVinculos!X62 -> 2590367.9 | I58: =DatosSinVinculos!AC62 -> 64.979401 | J58: =DatosSinVinculos!AE62 -> 72.901583 | K58: =(1+DatosSinVinculos!AL62/100)^(1/4) -> 1.0122722 | L58: =K58/(I58/I57) -> 1.0081739 | M58: =DatosSinVinculos!AM62 -> 87.753103 | N58: =DatosSinVinculos!AN62 -> 540.00032 | O58: =DatosSinVinculos!Y62/DatosSinVinculos!D62 -> 0.035816945 | P58: =DatosSinVinculos!AA62*DatosSinVinculos!AN62/DatosSinVinculos!D62 -> 0.00050232677 | Q58: =DatosSinVinculos!P62 -> 1921160.1 | R58: =(1+DatosSinVinculos!AS62/100)^(1/4)*(1+DatosSinVinculos!AV62/10000)^(1/4) -> 1.0188695 | S58: =(1+DatosSinVinculos!AS62/100)^(1/4) -> 1.0150008 | T58: =(1+DatosSinVinculos!AV62/10000)^(1/4) -> 1.0038115 | U58: =DatosSinVinculos!AR62 -> 105.68016 | V58: =DatosSinVinculos!AQ62 -> 151.51784 | W58: =DatosSinVinculos!AO62/DatosSinVinculos!AQ62*100*100 -> 51.919079 | X58: =DatosSinVinculos!BO62 -> 91.478791 | Y58: =DatosSinVinculos!CE62 -> 92.3679 | Z58: =DatosSinVinculos!CQ62*DatosSinVinculos!CM62/DatosSinVinculos!CZ62 -> 39.372349 | AA58: =DatosSinVinculos!CQ62 -> 43.753958 | AB58: =DatosSinVinculos!CM62/DatosSinVinculos!CZ62 -> 0.899858 | AC58: =DatosSinVinculos!DB62/100 -> 0.10016154 | AD58: =DatosSinVinculos!DD62/100 -> 0.014880436
A59: 2000Q1 | B59: =DatosSinVinculos!C63 -> 16152864 | C59: =DatosSinVinculos!F63 -> 11327202 | D59: =DatosSinVinculos!L63 -> 2986478.3 | E59: =DatosSinVinculos!J63 -> 3302274 | F59: =DatosSinVinculos!H63 -> 3877509.8 | G59: =DatosSinVinculos!R63 -> 8941461.7 | H59: =DatosSinVinculos!X63 -> 2637966.2 | I59: =DatosSinVinculos!AC63 -> 65.900987 | J59: =DatosSinVinculos!AE63 -> 73.672383 | K59: =(1+DatosSinVinculos!AL63/100)^(1/4) -> 1.0127887 | L59: =K59/(I59/I58) -> 0.99862548 | M59: =DatosSinVinculos!AM63 -> 83.04563 | N59: =DatosSinVinculos!AN63 -> 512.308 | O59: =DatosSinVinculos!Y63/DatosSinVinculos!D63 -> 0.051872859 | P59: =DatosSinVinculos!AA63*DatosSinVinculos!AN63/DatosSinVinculos!D63 -> 0.034005319 | Q59: =DatosSinVinculos!P63 -> 1930727.5 | R59: =(1+DatosSinVinculos!AS63/100)^(1/4)*(1+DatosSinVinculos!AV63/10000)^(1/4) -> 1.0190116 | S59: =(1+DatosSinVinculos!AS63/100)^(1/4) -> 1.0149508 | T59: =(1+DatosSinVinculos!AV63/10000)^(1/4) -> 1.0040009 | U59: =DatosSinVinculos!AR63 -> 106.92481 | V59: =DatosSinVinculos!AQ63 -> 152.71697 | W59: =DatosSinVinculos!AO63/DatosSinVinculos!AQ63*100*100 -> 53.306728 | X59: =DatosSinVinculos!BO63 -> 91.408023 | Y59: =DatosSinVinculos!CE63 -> 92.306962 | Z59: =DatosSinVinculos!CQ63*DatosSinVinculos!CM63/DatosSinVinculos!CZ63 -> 40.058624 | AA59: =DatosSinVinculos!CQ63 -> 44.066662 | AB59: =DatosSinVinculos!CM63/DatosSinVinculos!CZ63 -> 0.90904603 | AC59: =DatosSinVinculos!DB63/100 -> 0.0911261 | AD59: =DatosSinVinculos!DD63/100 -> 0.015394462
A60: 2000Q2 | B60: =DatosSinVinculos!C64 -> 16223272 | C60: =DatosSinVinculos!F64 -> 11393913 | D60: =DatosSinVinculos!L64 -> 2960295 | E60: =DatosSinVinculos!J64 -> 3258862.4 | F60: =DatosSinVinculos!H64 -> 3859678.5 | G60: =DatosSinVinculos!R64 -> 8963986 | H60: =DatosSinVinculos!X64 -> 2691118.7 | I60: =DatosSinVinculos!AC64 -> 66.698303 | J60: =DatosSinVinculos!AE64 -> 74.446437 | K60: =(1+DatosSinVinculos!AL64/100)^(1/4) -> 1.0134752 | L60: =K60/(I60/I59) -> 1.00136 | M60: =DatosSinVinculos!AM64 -> 82.963747 | N60: =DatosSinVinculos!AN64 -> 520.08574 | O60: =DatosSinVinculos!Y64/DatosSinVinculos!D64 -> 0.015342172 | P60: =DatosSinVinculos!AA64*DatosSinVinculos!AN64/DatosSinVinculos!D64 -> -0.02674929 | Q60: =DatosSinVinculos!P64 -> 1941507.4 | R60: =(1+DatosSinVinculos!AS64/100)^(1/4)*(1+DatosSinVinculos!AV64/10000)^(1/4) -> 1.0212886 | S60: =(1+DatosSinVinculos!AS64/100)^(1/4) -> 1.0161952 | T60: =(1+DatosSinVinculos!AV64/10000)^(1/4) -> 1.0050122 | U60: =DatosSinVinculos!AR64 -> 107.72011 | V60: =DatosSinVinculos!AQ64 -> 152.47201 | W60: =DatosSinVinculos!AO64/DatosSinVinculos!AQ64*100*100 -> 51.739883 | X60: =DatosSinVinculos!BO64 -> 91.580475 | Y60: =DatosSinVinculos!CE64 -> 92.545654 | Z60: =DatosSinVinculos!CQ64*DatosSinVinculos!CM64/DatosSinVinculos!CZ64 -> 39.798034 | AA60: =DatosSinVinculos!CQ64 -> 43.83757 | AB60: =DatosSinVinculos!CM64/DatosSinVinculos!CZ64 -> 0.90785218 | AC60: =DatosSinVinculos!DB64/100 -> 0.092722814 | AD60: =DatosSinVinculos!DD64/100 -> 0.014755397
A61: 2000Q3 | B61: =DatosSinVinculos!C65 -> 16409631 | C61: =DatosSinVinculos!F65 -> 11527657 | D61: =DatosSinVinculos!L65 -> 3050384.4 | E61: =DatosSinVinculos!J65 -> 3353278.8 | F61: =DatosSinVinculos!H65 -> 3925280.7 | G61: =DatosSinVinculos!R65 -> 9042419.6 | H61: =DatosSinVinculos!X65 -> 2778685.5 | I61: =DatosSinVinculos!AC65 -> 67.260759 | J61: =DatosSinVinculos!AE65 -> 74.942429 | K61: =(1+DatosSinVinculos!AL65/100)^(1/4) -> 1.01302 | L61: =K61/(I61/I60) -> 1.0045488 | M61: =DatosSinVinculos!AM65 -> 88.377873 | N61: =DatosSinVinculos!AN65 -> 552.55148 | O61: =DatosSinVinculos!Y65/DatosSinVinculos!D65 -> 0.015043937 | P61: =DatosSinVinculos!AA65*DatosSinVinculos!AN65/DatosSinVinculos!D65 -> -0.027983006 | Q61: =DatosSinVinculos!P65 -> 1951315.1 | R61: =(1+DatosSinVinculos!AS65/100)^(1/4)*(1+DatosSinVinculos!AV65/10000)^(1/4) -> 1.0214451 | S61: =(1+DatosSinVinculos!AS65/100)^(1/4) -> 1.0163427 | T61: =(1+DatosSinVinculos!AV65/10000)^(1/4) -> 1.0050204 | U61: =DatosSinVinculos!AR65 -> 108.41469 | V61: =DatosSinVinculos!AQ65 -> 153.7059 | W61: =DatosSinVinculos!AO65/DatosSinVinculos!AQ65*100*100 -> 55.240311 | X61: =DatosSinVinculos!BO65 -> 92.183001 | Y61: =DatosSinVinculos!CE65 -> 93.177656 | Z61: =DatosSinVinculos!CQ65*DatosSinVinculos!CM65/DatosSinVinculos!CZ65 -> 39.393492 | AA61: =DatosSinVinculos!CQ65 -> 43.832333 | AB61: =DatosSinVinculos!CM65/DatosSinVinculos!CZ65 -> 0.89873134 | AC61: =DatosSinVinculos!DB65/100 -> 0.10059592 | AD61: =DatosSinVinculos!DD65/100 -> 0.014638512
A62: 2000Q4 | B62: =DatosSinVinculos!C66 -> 16561400 | C62: =DatosSinVinculos!F66 -> 11646806 | D62: =DatosSinVinculos!L66 -> 3132921.4 | E62: =DatosSinVinculos!J66 -> 3409592 | F62: =DatosSinVinculos!H66 -> 3930269.2 | G62: =DatosSinVinculos!R66 -> 9100502.4 | H62: =DatosSinVinculos!X66 -> 2881207.6 | I62: =DatosSinVinculos!AC66 -> 67.963054 | J62: =DatosSinVinculos!AE66 -> 75.680963 | K62: =(1+DatosSinVinculos!AL66/100)^(1/4) -> 1.0122722 | L62: =K62/(I62/I61) -> 1.0018119 | M62: =DatosSinVinculos!AM66 -> 89.688116 | N62: =DatosSinVinculos!AN66 -> 572.28115 | O62: =DatosSinVinculos!Y66/DatosSinVinculos!D66 -> 0.025343264 | P62: =DatosSinVinculos!AA66*DatosSinVinculos!AN66/DatosSinVinculos!D66 -> -0.02676089 | Q62: =DatosSinVinculos!P66 -> 1962430.3 | R62: =(1+DatosSinVinculos!AS66/100)^(1/4)*(1+DatosSinVinculos!AV66/10000)^(1/4) -> 1.0219778 | S62: =(1+DatosSinVinculos!AS66/100)^(1/4) -> 1.0163418 | T62: =(1+DatosSinVinculos!AV66/10000)^(1/4) -> 1.0055454 | U62: =DatosSinVinculos!AR66 -> 109.08289 | V62: =DatosSinVinculos!AQ66 -> 152.77417 | W62: =DatosSinVinculos!AO66/DatosSinVinculos!AQ66*100*100 -> 54.870668 | X62: =DatosSinVinculos!BO66 -> 92.462172 | Y62: =DatosSinVinculos!CE66 -> 93.447744 | Z62: =DatosSinVinculos!CQ66*DatosSinVinculos!CM66/DatosSinVinculos!CZ66 -> 40.012506 | AA62: =DatosSinVinculos!CQ66 -> 44.335753 | AB62: =DatosSinVinculos!CM66/DatosSinVinculos!CZ66 -> 0.90248847 | AC62: =DatosSinVinculos!DB66/100 -> 0.097558677 | AD62: =DatosSinVinculos!DD66/100 -> 0.014269479
A63: 2001Q1 | B63: =DatosSinVinculos!C67 -> 16786215 | C63: =DatosSinVinculos!F67 -> 11795395 | D63: =DatosSinVinculos!L67 -> 3119777.5 | E63: =DatosSinVinculos!J67 -> 3414435.1 | F63: =DatosSinVinculos!H67 -> 3976025.5 | G63: =DatosSinVinculos!R67 -> 9183734.2 | H63: =DatosSinVinculos!X67 -> 2900477.8 | I63: =DatosSinVinculos!AC67 -> 68.566787 | J63: =DatosSinVinculos!AE67 -> 76.275524 | K63: =(1+DatosSinVinculos!AL67/100)^(1/4) -> 1.0111639 | L63: =K63/(I63/I62) -> 1.0022606 | M63: =DatosSinVinculos!AM67 -> 89.807629 | N63: =DatosSinVinculos!AN67 -> 574.35047 | O63: =DatosSinVinculos!Y67/DatosSinVinculos!D67 -> 0.034119158 | P63: =DatosSinVinculos!AA67*DatosSinVinculos!AN67/DatosSinVinculos!D67 -> -0.0092260456 | Q63: =DatosSinVinculos!P67 -> 1975984 | R63: =(1+DatosSinVinculos!AS67/100)^(1/4)*(1+DatosSinVinculos!AV67/10000)^(1/4) -> 1.0180268 | S63: =(1+DatosSinVinculos!AS67/100)^(1/4) -> 1.0130821 | T63: =(1+DatosSinVinculos!AV67/10000)^(1/4) -> 1.0048808 | U63: =DatosSinVinculos!AR67 -> 109.40244 | V63: =DatosSinVinculos!AQ67 -> 153.2502 | W63: =DatosSinVinculos!AO67/DatosSinVinculos!AQ67*100*100 -> 52.210898 | X63: =DatosSinVinculos!BO67 -> 92.629636 | Y63: =DatosSinVinculos!CE67 -> 93.549985 | Z63: =DatosSinVinculos!CQ67*DatosSinVinculos!CM67/DatosSinVinculos!CZ67 -> 39.837532 | AA63: =DatosSinVinculos!CQ67 -> 44.265305 | AB63: =DatosSinVinculos!CM67/DatosSinVinculos!CZ67 -> 0.89997193 | AC63: =DatosSinVinculos!DB67/100 -> 0.099952228 | AD63: =DatosSinVinculos!DD67/100 -> 0.012782471
A64: 2001Q2 | B64: =DatosSinVinculos!C68 -> 16945962 | C64: =DatosSinVinculos!F68 -> 11909564 | D64: =DatosSinVinculos!L68 -> 3164534.2 | E64: =DatosSinVinculos!J68 -> 3475519.4 | F64: =DatosSinVinculos!H68 -> 4059292.5 | G64: =DatosSinVinculos!R68 -> 9302800.8 | H64: =DatosSinVinculos!X68 -> 2851603.9 | I64: =DatosSinVinculos!AC68 -> 69.101026 | J64: =DatosSinVinculos!AE68 -> 76.696648 | K64: =(1+DatosSinVinculos!AL68/100)^(1/4) -> 1.0091892 | L64: =K64/(I64/I63) -> 1.0013869 | M64: =DatosSinVinculos!AM68 -> 91.981608 | N64: =DatosSinVinculos!AN68 -> 606.36148 | O64: =DatosSinVinculos!Y68/DatosSinVinculos!D68 -> 0.037085386 | P64: =DatosSinVinculos!AA68*DatosSinVinculos!AN68/DatosSinVinculos!D68 -> -0.0088780818 | Q64: =DatosSinVinculos!P68 -> 1988201.9 | R64: =(1+DatosSinVinculos!AS68/100)^(1/4)*(1+DatosSinVinculos!AV68/10000)^(1/4) -> 1.014723 | S64: =(1+DatosSinVinculos!AS68/100)^(1/4) -> 1.0102653 | T64: =(1+DatosSinVinculos!AV68/10000)^(1/4) -> 1.0044124 | U64: =DatosSinVinculos!AR68 -> 109.76093 | V64: =DatosSinVinculos!AQ68 -> 150.02906 | W64: =DatosSinVinculos!AO68/DatosSinVinculos!AQ68*100*100 -> 49.934585 | X64: =DatosSinVinculos!BO68 -> 93.176273 | Y64: =DatosSinVinculos!CE68 -> 94.12647 | Z64: =DatosSinVinculos!CQ68*DatosSinVinculos!CM68/DatosSinVinculos!CZ68 -> 39.541842 | AA64: =DatosSinVinculos!CQ68 -> 43.790008 | AB64: =DatosSinVinculos!CM68/DatosSinVinculos!CZ68 -> 0.90298778 | AC64: =DatosSinVinculos!DB68/100 -> 0.097406219 | AD64: =DatosSinVinculos!DD68/100 -> 0.01443076
A65: 2001Q3 | B65: =DatosSinVinculos!C69 -> 16823572 | C65: =DatosSinVinculos!F69 -> 11793866 | D65: =DatosSinVinculos!L69 -> 3209870.3 | E65: =DatosSinVinculos!J69 -> 3513252.3 | F65: =DatosSinVinculos!H69 -> 4083628.1 | G65: =DatosSinVinculos!R69 -> 9225098.4 | H65: =DatosSinVinculos!X69 -> 2842686.1 | I65: =DatosSinVinculos!AC69 -> 69.660908 | J65: =DatosSinVinculos!AE69 -> 77.522997 | K65: =(1+DatosSinVinculos!AL69/100)^(1/4) -> 1.0134752 | L65: =K65/(I65/I64) -> 1.0053296 | M65: =DatosSinVinculos!AM69 -> 100.19088 | N65: =DatosSinVinculos!AN69 -> 669.8025 | O65: =DatosSinVinculos!Y69/DatosSinVinculos!D69 -> -0.0071893135 | P65: =DatosSinVinculos!AA69*DatosSinVinculos!AN69/DatosSinVinculos!D69 -> -0.044735519 | Q65: =DatosSinVinculos!P69 -> 1997480.9 | R65: =(1+DatosSinVinculos!AS69/100)^(1/4)*(1+DatosSinVinculos!AV69/10000)^(1/4) -> 1.0133718 | S65: =(1+DatosSinVinculos!AS69/100)^(1/4) -> 1.0085487 | T65: =(1+DatosSinVinculos!AV69/10000)^(1/4) -> 1.0047823 | U65: =DatosSinVinculos!AR69 -> 109.7284 | V65: =DatosSinVinculos!AQ69 -> 148.93191 | W65: =DatosSinVinculos!AO69/DatosSinVinculos!AQ69*100*100 -> 44.831815 | X65: =DatosSinVinculos!BO69 -> 93.695244 | Y65: =DatosSinVinculos!CE69 -> 94.653017 | Z65: =DatosSinVinculos!CQ69*DatosSinVinculos!CM69/DatosSinVinculos!CZ69 -> 38.309037 | AA65: =DatosSinVinculos!CQ69 -> 42.428208 | AB65: =DatosSinVinculos!CM69/DatosSinVinculos!CZ69 -> 0.90291433 | AC65: =DatosSinVinculos!DB69/100 -> 0.09692057 | AD65: =DatosSinVinculos!DD69/100 -> 0.016028335
A66: 2001Q4 | B66: =DatosSinVinculos!C70 -> 16925925 | C66: =DatosSinVinculos!F70 -> 11919491 | D66: =DatosSinVinculos!L70 -> 3109365.4 | E66: =DatosSinVinculos!J70 -> 3466265.5 | F66: =DatosSinVinculos!H70 -> 4016078.2 | G66: =DatosSinVinculos!R70 -> 9312334.4 | H66: =DatosSinVinculos!X70 -> 2785832.3 | I66: =DatosSinVinculos!AC70 -> 70.046038 | J66: =DatosSinVinculos!AE70 -> 78.257707 | K66: =(1+DatosSinVinculos!AL70/100)^(1/4) -> 1.0158683 | L66: =K66/(I66/I65) -> 1.0102828 | M66: =DatosSinVinculos!AM70 -> 101.02433 | N66: =DatosSinVinculos!AN70 -> 689.82597 | O66: =DatosSinVinculos!Y70/DatosSinVinculos!D70 -> 0.035863544 | P66: =DatosSinVinculos!AA70*DatosSinVinculos!AN70/DatosSinVinculos!D70 -> -0.0010124407 | Q66: =DatosSinVinculos!P70 -> 2010955.1 | R66: =(1+DatosSinVinculos!AS70/100)^(1/4)*(1+DatosSinVinculos!AV70/10000)^(1/4) -> 1.0103877 | S66: =(1+DatosSinVinculos!AS70/100)^(1/4) -> 1.0053487 | T66: =(1+DatosSinVinculos!AV70/10000)^(1/4) -> 1.0050122 | U66: =DatosSinVinculos!AR70 -> 110.16024 | V66: =DatosSinVinculos!AQ70 -> 147.30119 | W66: =DatosSinVinculos!AO70/DatosSinVinculos!AQ70*100*100 -> 43.899194 | X66: =DatosSinVinculos!BO70 -> 94.125253 | Y66: =DatosSinVinculos!CE70 -> 95.130393 | Z66: =DatosSinVinculos!CQ70*DatosSinVinculos!CM70/DatosSinVinculos!CZ70 -> 39.712565 | AA66: =DatosSinVinculos!CQ70 -> 43.875466 | AB66: =DatosSinVinculos!CM70/DatosSinVinculos!CZ70 -> 0.90512006 | AC66: =DatosSinVinculos!DB70/100 -> 0.094813963 | AD66: =DatosSinVinculos!DD70/100 -> 0.014604025
A67: 2002Q1 | B67: =DatosSinVinculos!C71 -> 17009968 | C67: =DatosSinVinculos!F71 -> 11995457 | D67: =DatosSinVinculos!L71 -> 3018555.6 | E67: =DatosSinVinculos!J71 -> 3346725 | F67: =DatosSinVinculos!H71 -> 3950839 | G67: =DatosSinVinculos!R71 -> 9417897.3 | H67: =DatosSinVinculos!X71 -> 2849688.3 | I67: =DatosSinVinculos!AC71 -> 70.280935 | J67: =DatosSinVinculos!AE71 -> 78.76151 | K67: =(1+DatosSinVinculos!AL71/100)^(1/4) -> 1.0139072 | L67: =K67/(I67/I66) -> 1.0105184 | M67: =DatosSinVinculos!AM71 -> 94.106552 | N67: =DatosSinVinculos!AN71 -> 669.71258 | O67: =DatosSinVinculos!Y71/DatosSinVinculos!D71 -> 0.054266349 | P67: =DatosSinVinculos!AA71*DatosSinVinculos!AN71/DatosSinVinculos!D71 -> 0.016506062 | Q67: =DatosSinVinculos!P71 -> 2033071.7 | R67: =(1+DatosSinVinculos!AS71/100)^(1/4)*(1+DatosSinVinculos!AV71/10000)^(1/4) -> 1.0087062 | S67: =(1+DatosSinVinculos!AS71/100)^(1/4) -> 1.0047195 | T67: =(1+DatosSinVinculos!AV71/10000)^(1/4) -> 1.003968 | U67: =DatosSinVinculos!AR71 -> 110.38925 | V67: =DatosSinVinculos!AQ71 -> 140.96831 | W67: =DatosSinVinculos!AO71/DatosSinVinculos!AQ71*100*100 -> 50.097055 | X67: =DatosSinVinculos!BO71 -> 95.005125 | Y67: =DatosSinVinculos!CE71 -> 96.005431 | Z67: =DatosSinVinculos!CQ71*DatosSinVinculos!CM71/DatosSinVinculos!CZ71 -> 39.099925 | AA67: =DatosSinVinculos!CQ71 -> 43.452627 | AB67: =DatosSinVinculos!CM71/DatosSinVinculos!CZ71 -> 0.89982878 | AC67: =DatosSinVinculos!DB71/100 -> 0.10008967 | AD67: =DatosSinVinculos!DD71/100 -> 0.015294953
... A123: 2016Q6 | B123: =DatosSinVinculos!C127 -> 30124246 | C123: =DatosSinVinculos!F127 -> 22743686 | D123: =DatosSinVinculos!L127 -> 3206153 | E123: =DatosSinVinculos!J127 -> 3525435.8 | F123: =DatosSinVinculos!H127 -> 4672398.1 | G123: =DatosSinVinculos!R127 -> 20204134 | H123: =DatosSinVinculos!X127 -> 7158239.6 | I123: =DatosSinVinculos!AC127 -> 111.90986 | J123: =DatosSinVinculos!AE127 -> 111.67234 | K123: =(1+DatosSinVinculos!AL127/100)^(1/4) -> 1.0086374 | L123: =K123/(I123/I122) -> 0.99772779 | M123: =DatosSinVinculos!AM127 -> 96.67 | N123: =DatosSinVinculos!AN127 -> 702.06714 | O123: =DatosSinVinculos!Y127/DatosSinVinculos!D127 -> 0.035976103 | P123: =DatosSinVinculos!AA127*DatosSinVinculos!AN127/DatosSinVinculos!D127 -> 0.0087892283 | Q123: =DatosSinVinculos!P127 -> 3777291.2 | R123: =(1+DatosSinVinculos!AS127/100)^(1/4)*(1+DatosSinVinculos!AV127/10000)^(1/4) -> 1.0079078 | S123: =(1+DatosSinVinculos!AS127/100)^(1/4) -> 1.0015585 | T123: =(1+DatosSinVinculos!AV127/10000)^(1/4) -> 1.0063395 | U123: =DatosSinVinculos!AR127 -> 184.0113 | V123: =DatosSinVinculos!AQ127 -> 219.93 | W123: =DatosSinVinculos!AO127/DatosSinVinculos!AQ127*100*100 -> 95.484927 | X123: =DatosSinVinculos!BO127 -> 129.42099 | Y123: =DatosSinVinculos!CE127 -> 129.38744 | Z123: =DatosSinVinculos!CQ127*DatosSinVinculos!CM127/DatosSinVinculos!CZ127 -> 35.585718 | AA123: =DatosSinVinculos!CQ127 -> 37.94605 | AB123: =DatosSinVinculos!CM127/DatosSinVinculos!CZ127 -> 0.93779768 | AC123: =DatosSinVinculos!DB127/100 -> 0.062389167 | AD123: =DatosSinVinculos!DD127/100 -> 0.0041783971

Sheet Logs
B1: Y | C1: Y REST | D1: Y CU | E1: Y MINE | F1: Y RRNN | G1: C | H1: FBKF | I1: IPC | J1: IPCSAE | K1: TPMN | L1: TPMR | M1: RER | N1: TCN | O1: TBY | P1: CAY | Q1: G | R1: R+S EXT | S1: R EXT | T1: SPREAD | U1: Y EXT | V1: IPE | W1: PCUR | X1: WR | Y1: WR REST | Z1: H*N/FT | AA1: H | AB1: N/FT | AC1: U | AD1: V
A2: 1: take ln( ) | B2: 1 | C2: 1 | D2: 1 | E2: 1 | F2: 1 | G2: 1 | H2: 1 | I2: 1 | J2: 1 | K2: 1 | L2: 1 | M2: 1 | N2: 1 | O2: 0 | P2: 0 | Q2: 1 | R2: 1 | S2: 1 | T2: 1 | U2: 1 | V2: 1 | W2: 1 | X2: 1 | Y2: 1 | Z2: 1 | AA2: 1 | AB2: 1 | AC2: 0 | AD2: 0
A3: 1986Q1 | B3: =IF(B$2,LN(Trans!B3),Trans!B3) -> 15.700575 | C3: =IF(C$2,LN(Trans!C3),Trans!C3) -> 15.382609 | D3: =IF(D$2,LN(Trans!D3),Trans!D3) -> 13.97304 | E3: =IF(E$2,LN(Trans!E3),Trans!E3) -> 14.129165 | F3: =IF(F$2,LN(Trans!F3),Trans!F3) -> 14.323852 | G3: =IF(G$2,LN(Trans!G3),Trans!G3) -> 15.004526 | H3: =IF(H$2,LN(Trans!H3),Trans!H3) -> 13.318369 | I3: =IF(I$2,LN(Trans!I3),Trans!I3) -> 2.5447611 | K3: =IF(K$2,LN(Trans!K3),Trans!K3) -> 0 | M3: =IF(M$2,LN(Trans!M3),Trans!M3) -> 4.6042215 | N3: =IF(N$2,LN(Trans!N3),Trans!N3) -> 5.2303131 | O3: =IF(O$2,LN(Trans!O3),Trans!O3) -> 0.12378119 | P3: =IF(P$2,LN(Trans!P3),Trans!P3) -> -0.13686131 | Q3: =IF(Q$2,LN(Trans!Q3),Trans!Q3) -> 14.102527 | S3: =IF(S$2,LN(Trans!S3),Trans!S3) -> 0.018989121 | U3: =IF(U$2,LN(Trans!U3),Trans!U3) -> 4.1947954 | V3: =IF(V$2,LN(Trans!V3),Trans!V3) -> 4.582506 | W3: =IF(W$2,LN(Trans!W3),Trans!W3) -> 4.1893295 | X3: =IF(X$2,LN(Trans!X3),Trans!X3) -> 4.0416532 | Y3: =IF(Y$2,LN(Trans!Y3),Trans!Y3) -> 4.0059433 | Z3: =IF(Z$2,LN(Trans!Z3),Trans!Z3) -> 3.6664505 | AA3: =IF(AA$2,LN(Trans!AA3),Trans!AA3) -> 3.8113592 | AB3: =IF(AB$2,LN(Trans!AB3),Trans!AB3) -> -0.14490872 | ... AD3: =IF(AD$2,LN(Trans!AD3),Trans!AD3) -> 0.011529623
A4: 1986Q2 | B4: =IF(B$2,LN(Trans!B4),Trans!B4) -> 15.742246 | C4: =IF(C$2,LN(Trans!C4),Trans!C4) -> 15.432408 | D4: =IF(D$2,LN(Trans!D4),Trans!D4) -> 13.999753 | E4: =IF(E$2,LN(Trans!E4),Trans!E4) -> 14.155798 | F4: =IF(F$2,LN(Trans!F4),Trans!F4) -> 14.326877 | G4: =IF(G$2,LN(Trans!G4),Trans!G4) -> 15.045116 | H4: =IF(H$2,LN(Trans!H4),Trans!H4) -> 13.365528 | I4: =IF(I$2,LN(Trans!I4),Trans!I4) -> 2.5803672 | K4: =IF(K$2,LN(Trans!K4),Trans!K4) -> 0 | L4: =IF(L$2,LN(Trans!L4),Trans!L4) -> -0.035606093 | M4: =IF(M$2,LN(Trans!M4),Trans!M4) -> 4.5866177 | N4: =IF(N$2,LN(Trans!N4),Trans!N4) -> 5.2399901 | O4: =IF(O$2,LN(Trans!O4),Trans!O4) -> 0.21604154 | P4: =IF(P$2,LN(Trans!P4),Trans!P4) -> -0.25068317 | Q4: =IF(Q$2,LN(Trans!Q4),Trans!Q4) -> 14.083241 | S4: =IF(S$2,LN(Trans!S4),Trans!S4) -> 0.016884695 | U4: =IF(U$2,LN(Trans!U4),Trans!U4) -> 4.2052283 | V4: =IF(V$2,LN(Trans!V4),Trans!V4) -> 4.5920982 | W4: =IF(W$2,LN(Trans!W4),Trans!W4) -> 4.1787031 | X4: =IF(X$2,LN(Trans!X4),Trans!X4) -> 4.0548833 | Y4: =IF(Y$2,LN(Trans!Y4),Trans!Y4) -> 4.0166633 | Z4: =IF(Z$2,LN(Trans!Z4),Trans!Z4) -> 3.689814 | AA4: =IF(AA$2,LN(Trans!AA4),Trans!AA4) -> 3.8137515 | AB4: =IF(AB$2,LN(Trans!AB4),Trans!AB4) -> -0.12393755 | ... AD4: =IF(AD$2,LN(Trans!AD4),Trans!AD4) -> 0.01227143
A5: 1986Q3 | B5: =IF(B$2,LN(Trans!B5),Trans!B5) -> 15.762471 | C5: =IF(C$2,LN(Trans!C5),Trans!C5) -> 15.447298 | D5: =IF(D$2,LN(Trans!D5),Trans!D5) -> 13.972982 | E5: =IF(E$2,LN(Trans!E5),Trans!E5) -> 14.129076 | F5: =IF(F$2,LN(Trans!F5),Trans!F5) -> 14.348266 | G5: =IF(G$2,LN(Trans!G5),Trans!G5) -> 15.071707 | H5: =IF(H$2,LN(Trans!H5),Trans!H5) -> 13.462639 | I5: =IF(I$2,LN(Trans!I5),Trans!I5) -> 2.6176192 | K5: =IF(K$2,LN(Trans!K5),Trans!K5) -> 0 | L5: =IF(L$2,LN(Trans!L5),Trans!L5) -> -0.037252011 | M5: =IF(M$2,LN(Trans!M5),Trans!M5) -> 4.615296 | N5: =IF(N$2,LN(Trans!N5),Trans!N5) -> 5.2684915 | O5: =IF(O$2,LN(Trans!O5),Trans!O5) -> 0.49977183 | P5: =IF(P$2,LN(Trans!P5),Trans!P5) -> -0.35657648 | Q5: =IF(Q$2,LN(Trans!Q5),Trans!Q5) -> 14.084701 | S5: =IF(S$2,LN(Trans!S5),Trans!S5) -> 0.01522326 | U5: =IF(U$2,LN(Trans!U5),Trans!U5) -> 4.2137256 | V5: =IF(V$2,LN(Trans!V5),Trans!V5) -> 4.6204573 | W5: =IF(W$2,LN(Trans!W5),Trans!W5) -> 4.0845976 | X5: =IF(X$2,LN(Trans!X5),Trans!X5) -> 4.0579247 | Y5: =IF(Y$2,LN(Trans!Y5),Trans!Y5) -> 4.0164723 | Z5: =IF(Z$2,LN(Trans!Z5),Trans!Z5) -> 3.6889143 | AA5: =IF(AA$2,LN(Trans!AA5),Trans!AA5) -> 3.810053 | AB5: =IF(AB$2,LN(Trans!AB5),Trans!AB5) -> -0.12113879 | ... AD5: =IF(AD$2,LN(Trans!AD5),Trans!AD5) -> 0.011776982
A6: 1986Q4 | B6: =IF(B$2,LN(Trans!B6),Trans!B6) -> 15.782555 | C6: =IF(C$2,LN(Trans!C6),Trans!C6) -> 15.476423 | D6: =IF(D$2,LN(Trans!D6),Trans!D6) -> 13.952755 | E6: =IF(E$2,LN(Trans!E6),Trans!E6) -> 14.109044 | F6: =IF(F$2,LN(Trans!F6),Trans!F6) -> 14.325165 | G6: =IF(G$2,LN(Trans!G6),Trans!G6) -> 15.096126 | H6: =IF(H$2,LN(Trans!H6),Trans!H6) -> 13.571252 | I6: =IF(I$2,LN(Trans!I6),Trans!I6) -> 2.6475667 | K6: =IF(K$2,LN(Trans!K6),Trans!K6) -> 0 | L6: =IF(L$2,LN(Trans!L6),Trans!L6) -> -0.02994748 | M6: =IF(M$2,LN(Trans!M6),Trans!M6) -> 4.6152999 | N6: =IF(N$2,LN(Trans!N6),Trans!N6) -> 5.3067208 | O6: =IF(O$2,LN(Trans!O6),Trans!O6) -> 0.080794004 | P6: =IF(P$2,LN(Trans!P6),Trans!P6) -> -0.26539461 | Q6: =IF(Q$2,LN(Trans!Q6),Trans!Q6) -> 14.073722 | S6: =IF(S$2,LN(Trans!S6),Trans!S6) -> 0.014902706 | U6: =IF(U$2,LN(Trans!U6),Trans!U6) -> 4.2257634 | V6: =IF(V$2,LN(Trans!V6),Trans!V6) -> 4.6249647 | W6: =IF(W$2,LN(Trans!W6),Trans!W6) -> 4.068979 | X6: =IF(X$2,LN(Trans!X6),Trans!X6) -> 4.0685507 | Y6: =IF(Y$2,LN(Trans!Y6),Trans!Y6) -> 4.0349757 | Z6: =IF(Z$2,LN(Trans!Z6),Trans!Z6) -> 3.6990539 | AA6: =IF(AA$2,LN(Trans!AA6),Trans!AA6) -> 3.8204574 | AB6: =IF(AB$2,LN(Trans!AB6),Trans!AB6) -> -0.12140344 | ... AD6: =IF(AD$2,LN(Trans!AD6),Trans!AD6) -> 0.011057671
A7: 1987Q1 | B7: =IF(B$2,LN(Trans!B7),Trans!B7) -> 15.79102 | C7: =IF(C$2,LN(Trans!C7),Trans!C7) -> 15.475301 | D7: =IF(D$2,LN(Trans!D7),Trans!D7) -> 13.967961 | E7: =IF(E$2,LN(Trans!E7),Trans!E7) -> 14.124128 | F7: =IF(F$2,LN(Trans!F7),Trans!F7) -> 14.334898 | G7: =IF(G$2,LN(Trans!G7),Trans!G7) -> 15.107143 | H7: =IF(H$2,LN(Trans!H7),Trans!H7) -> 13.635992 | I7: =IF(I$2,LN(Trans!I7),Trans!I7) -> 2.7038909 | K7: =IF(K$2,LN(Trans!K7),Trans!K7) -> 0 | L7: =IF(L$2,LN(Trans!L7),Trans!L7) -> -0.056324258 | M7: =IF(M$2,LN(Trans!M7),Trans!M7) -> 4.6227786 | N7: =IF(N$2,LN(Trans!N7),Trans!N7) -> 5.3286118 | O7: =IF(O$2,LN(Trans!O7),Trans!O7) -> 0.47782312 | P7: =IF(P$2,LN(Trans!P7),Trans!P7) -> -0.0035186012 | Q7: =IF(Q$2,LN(Trans!Q7),Trans!Q7) -> 14.053549 | S7: =IF(S$2,LN(Trans!S7),Trans!S7) -> 0.015464315 | U7: =IF(U$2,LN(Trans!U7),Trans!U7) -> 4.2297336 | V7: =IF(V$2,LN(Trans!V7),Trans!V7) -> 4.6621043 | W7: =IF(W$2,LN(Trans!W7),Trans!W7) -> 4.0914777 | X7: =IF(X$2,LN(Trans!X7),Trans!X7) -> 4.0544587 | Y7: =IF(Y$2,LN(Trans!Y7),Trans!Y7) -> 4.0181757 | Z7: =IF(Z$2,LN(Trans!Z7),Trans!Z7) -> 3.6992141 | AA7: =IF(AA$2,LN(Trans!AA7),Trans!AA7) -> 3.8156472 | AB7: =IF(AB$2,LN(Trans!AB7),Trans!AB7) -> -0.11643314 | ... AD7: =IF(AD$2,LN(Trans!AD7),Trans!AD7) -> 0.011226604
A8: 1987Q2 | B8: =IF(B$2,LN(Trans!B8),Trans!B8) -> 15.799253 | C8: =IF(C$2,LN(Trans!C8),Trans!C8) -> 15.487492 | D8: =IF(D$2,LN(Trans!D8),Trans!D8) -> 13.958671 | E8: =IF(E$2,LN(Trans!E8),Trans!E8) -> 14.114728 | F8: =IF(F$2,LN(Trans!F8),Trans!F8) -> 14.351071 | G8: =IF(G$2,LN(Trans!G8),Trans!G8) -> 15.117993 | H8: =IF(H$2,LN(Trans!H8),Trans!H8) -> 13.637282 | I8: =IF(I$2,LN(Trans!I8),Trans!I8) -> 2.7561913 | K8: =IF(K$2,LN(Trans!K8),Trans!K8) -> 0 | L8: =IF(L$2,LN(Trans!L8),Trans!L8) -> -0.052300413 | M8: =IF(M$2,LN(Trans!M8),Trans!M8) -> 4.6412056 | N8: =IF(N$2,LN(Trans!N8),Trans!N8) -> 5.3664274 | O8: =IF(O$2,LN(Trans!O8),Trans!O8) -> -0.061021609 | P8: =IF(P$2,LN(Trans!P8),Trans!P8) -> -0.17536798 | Q8: =IF(Q$2,LN(Trans!Q8),Trans!Q8) -> 14.056682 | S8: =IF(S$2,LN(Trans!S8),Trans!S8) -> 0.017279234 | U8: =IF(U$2,LN(Trans!U8),Trans!U8) -> 4.2460341 | V8: =IF(V$2,LN(Trans!V8),Trans!V8) -> 4.6948267 | W8: =IF(W$2,LN(Trans!W8),Trans!W8) -> 4.14445 | X8: =IF(X$2,LN(Trans!X8),Trans!X8) -> 4.0438936 | Y8: =IF(Y$2,LN(Trans!Y8),Trans!Y8) -> 4.0041393 | Z8: =IF(Z$2,LN(Trans!Z8),Trans!Z8) -> 3.680084 | AA8: =IF(AA$2,LN(Trans!AA8),Trans!AA8) -> 3.7974798 | AB8: =IF(AB$2,LN(Trans!AB8),Trans!AB8) -> -0.11739574 | ... AD8: =IF(AD$2,LN(Trans!AD8),Trans!AD8) -> 0.0099456502
A9: 1987Q3 | B9: =IF(B$2,LN(Trans!B9),Trans!B9) -> 15.817007 | C9: =IF(C$2,LN(Trans!C9),Trans!C9) -> 15.509632 | D9: =IF(D$2,LN(Trans!D9),Trans!D9) -> 13.963746 | E9: =IF(E$2,LN(Trans!E9),Trans!E9) -> 14.119821 | F9: =IF(F$2,LN(Trans!F9),Trans!F9) -> 14.33103 | G9: =IF(G$2,LN(Trans!G9),Trans!G9) -> 15.127553 | H9: =IF(H$2,LN(Trans!H9),Trans!H9) -> 13.626373 | I9: =IF(I$2,LN(Trans!I9),Trans!I9) -> 2.8047983 | K9: =IF(K$2,LN(Trans!K9),Trans!K9) -> 0 | L9: =IF(L$2,LN(Trans!L9),Trans!L9) -> -0.048606974 | M9: =IF(M$2,LN(Trans!M9),Trans!M9) -> 4.6485473 | N9: =IF(N$2,LN(Trans!N9),Trans!N9) -> 5.4142974 | O9: =IF(O$2,LN(Trans!O9),Trans!O9) -> 0.95860654 | P9: =IF(P$2,LN(Trans!P9),Trans!P9) -> -0.31558196 | Q9: =IF(Q$2,LN(Trans!Q9),Trans!Q9) -> 14.05978 | S9: =IF(S$2,LN(Trans!S9),Trans!S9) -> 0.017467104 | U9: =IF(U$2,LN(Trans!U9),Trans!U9) -> 4.260664 | V9: =IF(V$2,LN(Trans!V9),Trans!V9) -> 4.696798 | W9: =IF(W$2,LN(Trans!W9),Trans!W9) -> 4.2820306 | X9: =IF(X$2,LN(Trans!X9),Trans!X9) -> 4.0518116 | Y9: =IF(Y$2,LN(Trans!Y9),Trans!Y9) -> 4.0090395 | Z9: =IF(Z$2,LN(Trans!Z9),Trans!Z9) -> 3.6763956 | AA9: =IF(AA$2,LN(Trans!AA9),Trans!AA9) -> 3.7930331 | AB9: =IF(AB$2,LN(Trans!AB9),Trans!AB9) -> -0.11663749 | ... AD9: =IF(AD$2,LN(Trans!AD9),Trans!AD9) -> 0.010752334
A10: 1987Q4 | B10: =IF(B$2,LN(Trans!B10),Trans!B10) -> 15.833726 | C10: =IF(C$2,LN(Trans!C10),Trans!C10) -> 15.525519 | D10: =IF(D$2,LN(Trans!D10),Trans!D10) -> 13.995485 | E10: =IF(E$2,LN(Trans!E10),Trans!E10) -> 14.15179 | F10: =IF(F$2,LN(Trans!F10),Trans!F10) -> 14.37095 | G10: =IF(G$2,LN(Trans!G10),Trans!G10) -> 15.147133 | H10: =IF(H$2,LN(Trans!H10),Trans!H10) -> 13.619478 | I10: =IF(I$2,LN(Trans!I10),Trans!I10) -> 2.8477469 | K10: =IF(K$2,LN(Trans!K10),Trans!K10) -> 0 | L10: =IF(L$2,LN(Trans!L10),Trans!L10) -> -0.042948627 | M10: =IF(M$2,LN(Trans!M10),Trans!M10) -> 4.6772024 | N10: =IF(N$2,LN(Trans!N10),Trans!N10) -> 5.4500557 | O10: =IF(O$2,LN(Trans!O10),Trans!O10) -> -0.1549488 | P10: =IF(P$2,LN(Trans!P10),Trans!P10) -> -0.21252041 | Q10: =IF(Q$2,LN(Trans!Q10),Trans!Q10) -> 14.064434 | S10: =IF(S$2,LN(Trans!S10),Trans!S10) -> 0.019204682 | U10: =IF(U$2,LN(Trans!U10),Trans!U10) -> 4.2750667 | V10: =IF(V$2,LN(Trans!V10),Trans!V10) -> 4.7439151 | W10: =IF(W$2,LN(Trans!W10),Trans!W10) -> 4.5707853 | X10: =IF(X$2,LN(Trans!X10),Trans!X10) -> 4.0667952 | Y10: =IF(Y$2,LN(Trans!Y10),Trans!Y10) -> 4.0213068 | Z10: =IF(Z$2,LN(Trans!Z10),Trans!Z10) -> 3.6983598 | AA10: =IF(AA$2,LN(Trans!AA10),Trans!AA10) -> 3.8093856 | AB10: =IF(AB$2,LN(Trans!AB10),Trans!AB10) -> -0.11102584 | ... AD10: =IF(AD$2,LN(Trans!AD10),Trans!AD10) -> 0.011088704
A11: 1988Q1 | B11: =IF(B$2,LN(Trans!B11),Trans!B11) -> 15.857075 | C11: =IF(C$2,LN(Trans!C11),Trans!C11) -> 15.547904 | D11: =IF(D$2,LN(Trans!D11),Trans!D11) -> 14.004133 | E11: =IF(E$2,LN(Trans!E11),Trans!E11) -> 14.160457 | F11: =IF(F$2,LN(Trans!F11),Trans!F11) -> 14.379709 | G11: =IF(G$2,LN(Trans!G11),Trans!G11) -> 15.162396 | H11: =IF(H$2,LN(Trans!H11),Trans!H11) -> 13.634512 | I11: =IF(I$2,LN(Trans!I11),Trans!I11) -> 2.8772228 | K11: =IF(K$2,LN(Trans!K11),Trans!K11) -> 0 | L11: =IF(L$2,LN(Trans!L11),Trans!L11) -> -0.029475822 | M11: =IF(M$2,LN(Trans!M11),Trans!M11) -> 4.7090256 | N11: =IF(N$2,LN(Trans!N11),Trans!N11) -> 5.4904184 | O11: =IF(O$2,LN(Trans!O11),Trans!O11) -> 0.88833285 | P11: =IF(P$2,LN(Trans!P11),Trans!P11) -> 0.15160014 | Q11: =IF(Q$2,LN(Trans!Q11),Trans!Q11) -> 14.069179 | S11: =IF(S$2,LN(Trans!S11),Trans!S11) -> 0.016852651 | U11: =IF(U$2,LN(Trans!U11),Trans!U11) -> 4.2854282 | V11: =IF(V$2,LN(Trans!V11),Trans!V11) -> 4.7608091 | W11: =IF(W$2,LN(Trans!W11),Trans!W11) -> 4.5568898 | X11: =IF(X$2,LN(Trans!X11),Trans!X11) -> 4.0901717 | Y11: =IF(Y$2,LN(Trans!Y11),Trans!Y11) -> 4.0433807 | Z11: =IF(Z$2,LN(Trans!Z11),Trans!Z11) -> 3.6930556 | AA11: =IF(AA$2,LN(Trans!AA11),Trans!AA11) -> 3.8040164 | AB11: =IF(AB$2,LN(Trans!AB11),Trans!AB11) -> -0.11096082 | ... AD11: =IF(AD$2,LN(Trans!AD11),Trans!AD11) -> 0.011556967
A12: 1988Q2 | B12: =IF(B$2,LN(Trans!B12),Trans!B12) -> 15.845655 | C12: =IF(C$2,LN(Trans!C12),Trans!C12) -> 15.539494 | D12: =IF(D$2,LN(Trans!D12),Trans!D12) -> 14.000598 | E12: =IF(E$2,LN(Trans!E12),Trans!E12) -> 14.156682 | F12: =IF(F$2,LN(Trans!F12),Trans!F12) -> 14.357684 | G12: =IF(G$2,LN(Trans!G12),Trans!G12) -> 15.170949 | H12: =IF(H$2,LN(Trans!H12),Trans!H12) -> 13.742756 | I12: =IF(I$2,LN(Trans!I12),Trans!I12) -> 2.9054226 | K12: =IF(K$2,LN(Trans!K12),Trans!K12) -> 0 | L12: =IF(L$2,LN(Trans!L12),Trans!L12) -> -0.028199796 | M12: =IF(M$2,LN(Trans!M12),Trans!M12) -> 4.7283826 | N12: =IF(N$2,LN(Trans!N12),Trans!N12) -> 5.5017242 | O12: =IF(O$2,LN(Trans!O12),Trans!O12) -> 0.099846644 | P12: =IF(P$2,LN(Trans!P12),Trans!P12) -> -0.037919218 | Q12: =IF(Q$2,LN(Trans!Q12),Trans!Q12) -> 14.088473 | S12: =IF(S$2,LN(Trans!S12),Trans!S12) -> 0.018040309 | U12: =IF(U$2,LN(Trans!U12),Trans!U12) -> 4.2934564 | V12: =IF(V$2,LN(Trans!V12),Trans!V12) -> 4.7955766 | W12: =IF(W$2,LN(Trans!W12),Trans!W12) -> 4.5100739 | X12: =IF(X$2,LN(Trans!X12),Trans!X12) -> 4.1095368 | Y12: =IF(Y$2,LN(Trans!Y12),Trans!Y12) -> 4.0699702 | Z12: =IF(Z$2,LN(Trans!Z12),Trans!Z12) -> 3.7134823 | AA12: =IF(AA$2,LN(Trans!AA12),Trans!AA12) -> 3.8191254 | AB12: =IF(AB$2,LN(Trans!AB12),Trans!AB12) -> -0.10564314 | ... AD12: =IF(AD$2,LN(Trans!AD12),Trans!AD12) -> 0.012641645
A13: 1988Q3 | B13: =IF(B$2,LN(Trans!B13),Trans!B13) -> 15.896537 | C13: =IF(C$2,LN(Trans!C13),Trans!C13) -> 15.576624 | D13: =IF(D$2,LN(Trans!D13),Trans!D13) -> 14.075288 | E13: =IF(E$2,LN(Trans!E13),Trans!E13) -> 14.231302 | F13: =IF(F$2,LN(Trans!F13),Trans!F13) -> 14.459863 | G13: =IF(G$2,LN(Trans!G13),Trans!G13) -> 15.207783 | H13: =IF(H$2,LN(Trans!H13),Trans!H13) -> 13.829652 | I13: =IF(I$2,LN(Trans!I13),Trans!I13) -> 2.9256052 | K13: =IF(K$2,LN(Trans!K13),Trans!K13) -> 0 | L13: =IF(L$2,LN(Trans!L13),Trans!L13) -> -0.020182594 | M13: =IF(M$2,LN(Trans!M13),Trans!M13) -> 4.7094676 | N13: =IF(N$2,LN(Trans!N13),Trans!N13) -> 5.5074165 | O13: =IF(O$2,LN(Trans!O13),Trans!O13) -> 0.83911232 | P13: =IF(P$2,LN(Trans!P13),Trans!P13) -> -0.21787272 | Q13: =IF(Q$2,LN(Trans!Q13),Trans!Q13) -> 14.099174 | S13: =IF(S$2,LN(Trans!S13),Trans!S13) -> 0.020200623 | U13: =IF(U$2,LN(Trans!U13),Trans!U13) -> 4.3039495 | V13: =IF(V$2,LN(Trans!V13),Trans!V13) -> 4.7855464 | W13: =IF(W$2,LN(Trans!W13),Trans!W13) -> 4.4575837 | X13: =IF(X$2,LN(Trans!X13),Trans!X13) -> 4.1403562 | Y13: =IF(Y$2,LN(Trans!Y13),Trans!Y13) -> 4.1107651 | Z13: =IF(Z$2,LN(Trans!Z13),Trans!Z13) -> 3.7210951 | AA13: =IF(AA$2,LN(Trans!AA13),Trans!AA13) -> 3.8250046 | AB13: =IF(AB$2,LN(Trans!AB13),Trans!AB13) -> -0.10390953 | ... AD13: =IF(AD$2,LN(Trans!AD13),Trans!AD13) -> 0.013869881
A14: 1988Q4 | B14: =IF(B$2,LN(Trans!B14),Trans!B14) -> 15.924523 | C14: =IF(C$2,LN(Trans!C14),Trans!C14) -> 15.603132 | D14: =IF(D$2,LN(Trans!D14),Trans!D14) -> 14.102255 | E14: =IF(E$2,LN(Trans!E14),Trans!E14) -> 14.258619 | F14: =IF(F$2,LN(Trans!F14),Trans!F14) -> 14.464871 | G14: =IF(G$2,LN(Trans!G14),Trans!G14) -> 15.228217 | H14: =IF(H$2,LN(Trans!H14),Trans!H14) -> 13.833328 | I14: =IF(I$2,LN(Trans!I14),Trans!I14) -> 2.9562167 | K14: =IF(K$2,LN(Trans!K14),Trans!K14) -> 0 | L14: =IF(L$2,LN(Trans!L14),Trans!L14) -> -0.030611559 | M14: =IF(M$2,LN(Trans!M14),Trans!M14) -> 4.6971828 | N14: =IF(N$2,LN(Trans!N14),Trans!N14) -> 5.5054042 | O14: =IF(O$2,LN(Trans!O14),Trans!O14) -> 0.47687581 | P14: =IF(P$2,LN(Trans!P14),Trans!P14) -> -0.13982125 | Q14: =IF(Q$2,LN(Trans!Q14),Trans!Q14) -> 14.113598 | S14: =IF(S$2,LN(Trans!S14),Trans!S14) -> 0.021619424 | U14: =IF(U$2,LN(Trans!U14),Trans!U14) -> 4.3147614 | V14: =IF(V$2,LN(Trans!V14),Trans!V14) -> 4.8175769 | W14: =IF(W$2,LN(Trans!W14),Trans!W14) -> 4.7802909 | X14: =IF(X$2,LN(Trans!X14),Trans!X14) -> 4.1305778 | Y14: =IF(Y$2,LN(Trans!Y14),Trans!Y14) -> 4.1048075 | Z14: =IF(Z$2,LN(Trans!Z14),Trans!Z14) -> 3.7175319 | AA14: =IF(AA$2,LN(Trans!AA14),Trans!AA14) -> 3.8101281 | AB14: =IF(AB$2,LN(Trans!AB14),Trans!AB14) -> -0.092596159 | ... AD14: =IF(AD$2,LN(Trans!AD14),Trans!AD14) -> 0.013721413
A15: 1989Q1 | B15: =IF(B$2,LN(Trans!B15),Trans!B15) -> 15.941616 | C15: =IF(C$2,LN(Trans!C15),Trans!C15) -> 15.62689 | D15: =IF(D$2,LN(Trans!D15),Trans!D15) -> 14.075541 | E15: =IF(E$2,LN(Trans!E15),Trans!E15) -> 14.232066 | F15: =IF(F$2,LN(Trans!F15),Trans!F15) -> 14.441474 | G15: =IF(G$2,LN(Trans!G15),Trans!G15) -> 15.268277 | H15: =IF(H$2,LN(Trans!H15),Trans!H15) -> 13.937652 | I15: =IF(I$2,LN(Trans!I15),Trans!I15) -> 2.9985088 | K15: =IF(K$2,LN(Trans!K15),Trans!K15) -> 0 | L15: =IF(L$2,LN(Trans!L15),Trans!L15) -> -0.04229205 | M15: =IF(M$2,LN(Trans!M15),Trans!M15) -> 4.6781781 | N15: =IF(N$2,LN(Trans!N15),Trans!N15) -> 5.5117439 | O15: =IF(O$2,LN(Trans!O15),Trans!O15) -> 0.2064192 | P15: =IF(P$2,LN(Trans!P15),Trans!P15) -> 0.040510029 | Q15: =IF(Q$2,LN(Trans!Q15),Trans!Q15) -> 14.12454 | S15: =IF(S$2,LN(Trans!S15),Trans!S15) -> 0.023438364 | U15: =IF(U$2,LN(Trans!U15),Trans!U15) -> 4.3319817 | V15: =IF(V$2,LN(Trans!V15),Trans!V15) -> 4.8293322 | W15: =IF(W$2,LN(Trans!W15),Trans!W15) -> 4.7685356 | X15: =IF(X$2,LN(Trans!X15),Trans!X15) -> 4.1280346 | Y15: =IF(Y$2,LN(Trans!Y15),Trans!Y15) -> 4.1042106 | Z15: =IF(Z$2,LN(Trans!Z15),Trans!Z15) -> 3.7255222 | AA15: =IF(AA$2,LN(Trans!AA15),Trans!AA15) -> 3.8130355 | AB15: =IF(AB$2,LN(Trans!AB15),Trans!AB15) -> -0.087513254 | ... AD15: =IF(AD$2,LN(Trans!AD15),Trans!AD15) -> 0.01398009
A16: 1989Q2 | B16: =IF(B$2,LN(Trans!B16),Trans!B16) -> 15.97621 | C16: =IF(C$2,LN(Trans!C16),Trans!C16) -> 15.663274 | D16: =IF(D$2,LN(Trans!D16),Trans!D16) -> 14.134436 | E16: =IF(E$2,LN(Trans!E16),Trans!E16) -> 14.290592 | F16: =IF(F$2,LN(Trans!F16),Trans!F16) -> 14.465293 | G16: =IF(G$2,LN(Trans!G16),Trans!G16) -> 15.294057 | H16: =IF(H$2,LN(Trans!H16),Trans!H16) -> 14.011642 | I16: =IF(I$2,LN(Trans!I16),Trans!I16) -> 3.045227 | ... Q16: =IF(Q$2,LN(Trans!Q16),Trans!Q16) -> 14.13042 | S16: =IF(S$2,LN(Trans!S16),Trans!S16) -> 0.023320995 | U16: =IF(U$2,LN(Trans!U16),Trans!U16) -> 4.334244 | V16: =IF(V$2,LN(Trans!V16),Trans!V16) -> 4.8083199 | W16: =IF(W$2,LN(Trans!W16),Trans!W16) -> 4.6384093 | X16: =IF(X$2,LN(Trans!X16),Trans!X16) -> 4.1365651 | Y16: =IF(Y$2,LN(Trans!Y16),Trans!Y16) -> 4.1103519 | Z16: =IF(Z$2,LN(Trans!Z16),Trans!Z16) -> 3.7304193 | AA16: =IF(AA$2,LN(Trans!AA16),Trans!AA16) -> 3.8160117 | AB16: =IF(AB$2,LN(Trans!AB16),Trans!AB16) -> -0.085592443 | ... AD16: =IF(AD$2,LN(Trans!AD16),Trans!AD16) -> 0.015520026
A17: 1989Q3 | B17: =IF(B$2,LN(Trans!B17),Trans!B17) -> 15.99334 | C17: =IF(C$2,LN(Trans!C17),Trans!C17) -> 15.67836 | D17: =IF(D$2,LN(Trans!D17),Trans!D17) -> 14.141869 | E17: =IF(E$2,LN(Trans!E17),Trans!E17) -> 14.297772 | F17: =IF(F$2,LN(Trans!F17),Trans!F17) -> 14.476394 | G17: =IF(G$2,LN(Trans!G17),Trans!G17) -> 15.292248 | H17: =IF(H$2,LN(Trans!H17),Trans!H17) -> 14.05291 | I17: =IF(I$2,LN(Trans!I17),Trans!I17) -> 3.096233 | ... Q17: =IF(Q$2,LN(Trans!Q17),Trans!Q17) -> 14.135083 | S17: =IF(S$2,LN(Trans!S17),Trans!S17) -> 0.021348665 | U17: =IF(U$2,LN(Trans!U17),Trans!U17) -> 4.3453177 | V17: =IF(V$2,LN(Trans!V17),Trans!V17) -> 4.8405929 | W17: =IF(W$2,LN(Trans!W17),Trans!W17) -> 4.5767617 | X17: =IF(X$2,LN(Trans!X17),Trans!X17) -> 4.1409591 | Y17: =IF(Y$2,LN(Trans!Y17),Trans!Y17) -> 4.1070833 | Z17: =IF(Z$2,LN(Trans!Z17),Trans!Z17) -> 3.7234242 | AA17: =IF(AA$2,LN(Trans!AA17),Trans!AA17) -> 3.8050141 | AB17: =IF(AB$2,LN(Trans!AB17),Trans!AB17) -> -0.08158998 | ... AD17: =IF(AD$2,LN(Trans!AD17),Trans!AD17) -> 0.01393852
A18: 1989Q4 | B18: =IF(B$2,LN(Trans!B18),Trans!B18) -> 15.994272 | C18: =IF(C$2,LN(Trans!C18),Trans!C18) -> 15.675872 | D18: =IF(D$2,LN(Trans!D18),Trans!D18) -> 14.134083 | E18: =IF(E$2,LN(Trans!E18),Trans!E18) -> 14.290484 | F18: =IF(F$2,LN(Trans!F18),Trans!F18) -> 14.48194 | G18: =IF(G$2,LN(Trans!G18),Trans!G18) -> 15.302027 | H18: =IF(H$2,LN(Trans!H18),Trans!H18) -> 14.090369 | I18: =IF(I$2,LN(Trans!I18),Trans!I18) -> 3.148046 | ... Q18: =IF(Q$2,LN(Trans!Q18),Trans!Q18) -> 14.133544 | S18: =IF(S$2,LN(Trans!S18),Trans!S18) -> 0.020673569 | U18: =IF(U$2,LN(Trans!U18),Trans!U18) -> 4.3592342 | V18: =IF(V$2,LN(Trans!V18),Trans!V18) -> 4.8689569 | W18: =IF(W$2,LN(Trans!W18),Trans!W18) -> 4.5153367 | X18: =IF(X$2,LN(Trans!X18),Trans!X18) -> 4.1427331 | Y18: =IF(Y$2,LN(Trans!Y18),Trans!Y18) -> 4.1105909 | Z18: =IF(Z$2,LN(Trans!Z18),Trans!Z18) -> 3.7154203 | AA18: =IF(AA$2,LN(Trans!AA18),Trans!AA18) -> 3.7983959 | AB18: =IF(AB$2,LN(Trans!AB18),Trans!AB18) -> -0.082975592 | ... AD18: =IF(AD$2,LN(Trans!AD18),Trans!AD18) -> 0.015116383
A19: 1990Q1 | B19: =IF(B$2,LN(Trans!B19),Trans!B19) -> 16.016982 | C19: =IF(C$2,LN(Trans!C19),Trans!C19) -> 15.704119 | D19: =IF(D$2,LN(Trans!D19),Trans!D19) -> 14.158299 | E19: =IF(E$2,LN(Trans!E19),Trans!E19) -> 14.315088 | F19: =IF(F$2,LN(Trans!F19),Trans!F19) -> 14.492615 | G19: =IF(G$2,LN(Trans!G19),Trans!G19) -> 15.307978 | H19: =IF(H$2,LN(Trans!H19),Trans!H19) -> 14.075692 | I19: =IF(I$2,LN(Trans!I19),Trans!I19) -> 3.2091458 | ... Q19: =IF(Q$2,LN(Trans!Q19),Trans!Q19) -> 14.138694 | S19: =IF(S$2,LN(Trans!S19),Trans!S19) -> 0.020183394 | U19: =IF(U$2,LN(Trans!U19),Trans!U19) -> 4.3719682 | V19: =IF(V$2,LN(Trans!V19),Trans!V19) -> 4.9309203 | W19: =IF(W$2,LN(Trans!W19),Trans!W19) -> 4.3837801 | X19: =IF(X$2,LN(Trans!X19),Trans!X19) -> 4.1449177 | Y19: =IF(Y$2,LN(Trans!Y19),Trans!Y19) -> 4.1104446 | Z19: =IF(Z$2,LN(Trans!Z19),Trans!Z19) -> 3.7369343 | AA19: =IF(AA$2,LN(Trans!AA19),Trans!AA19) -> 3.8166302 | AB19: =IF(AB$2,LN(Trans!AB19),Trans!AB19) -> -0.07969582 | ... AD19: =IF(AD$2,LN(Trans!AD19),Trans!AD19) -> 0.013797052
A20: 1990Q2 | B20: =IF(B$2,LN(Trans!B20),Trans!B20) -> 16.007477 | C20: =IF(C$2,LN(Trans!C20),Trans!C20) -> 15.695787 | D20: =IF(D$2,LN(Trans!D20),Trans!D20) -> 14.151222 | E20: =IF(E$2,LN(Trans!E20),Trans!E20) -> 14.307475 | F20: =IF(F$2,LN(Trans!F20),Trans!F20) -> 14.471173 | G20: =IF(G$2,LN(Trans!G20),Trans!G20) -> 15.298361 | H20: =IF(H$2,LN(Trans!H20),Trans!H20) -> 14.050953 | I20: =IF(I$2,LN(Trans!I20),Trans!I20) -> 3.2677494 | ... Q20: =IF(Q$2,LN(Trans!Q20),Trans!Q20) -> 14.134034 | S20: =IF(S$2,LN(Trans!S20),Trans!S20) -> 0.020288128 | U20: =IF(U$2,LN(Trans!U20),Trans!U20) -> 4.3767477 | V20: =IF(V$2,LN(Trans!V20),Trans!V20) -> 4.9422062 | W20: =IF(W$2,LN(Trans!W20),Trans!W20) -> 4.4587545 | X20: =IF(X$2,LN(Trans!X20),Trans!X20) -> 4.1507423 | Y20: =IF(Y$2,LN(Trans!Y20),Trans!Y20) -> 4.1121705 | Z20: =IF(Z$2,LN(Trans!Z20),Trans!Z20) -> 3.7192371 | AA20: =IF(AA$2,LN(Trans!AA20),Trans!AA20) -> 3.8019665 | AB20: =IF(AB$2,LN(Trans!AB20),Trans!AB20) -> -0.08272936 | ... AD20: =IF(AD$2,LN(Trans!AD20),Trans!AD20) -> 0.012644928
A21: 1990Q3 | B21: =IF(B$2,LN(Trans!B21),Trans!B21) -> 15.999294 | C21: =IF(C$2,LN(Trans!C21),Trans!C21) -> 15.686927 | D21: =IF(D$2,LN(Trans!D21),Trans!D21) -> 14.134271 | E21: =IF(E$2,LN(Trans!E21),Trans!E21) -> 14.290007 | F21: =IF(F$2,LN(Trans!F21),Trans!F21) -> 14.450455 | G21: =IF(G$2,LN(Trans!G21),Trans!G21) -> 15.307491 | H21: =IF(H$2,LN(Trans!H21),Trans!H21) -> 14.041331 | I21: =IF(I$2,LN(Trans!I21),Trans!I21) -> 3.3307353 | ... Q21: =IF(Q$2,LN(Trans!Q21),Trans!Q21) -> 14.136691 | S21: =IF(S$2,LN(Trans!S21),Trans!S21) -> 0.019646401 | U21: =IF(U$2,LN(Trans!U21),Trans!U21) -> 4.3834503 | V21: =IF(V$2,LN(Trans!V21),Trans!V21) -> 4.9835117 | W21: =IF(W$2,LN(Trans!W21),Trans!W21) -> 4.5044604 | X21: =IF(X$2,LN(Trans!X21),Trans!X21) -> 4.1577955 | Y21: =IF(Y$2,LN(Trans!Y21),Trans!Y21) -> 4.118794 | Z21: =IF(Z$2,LN(Trans!Z21),Trans!Z21) -> 3.7257524 | AA21: =IF(AA$2,LN(Trans!AA21),Trans!AA21) -> 3.8083302 | AB21: =IF(AB$2,LN(Trans!AB21),Trans!AB21) -> -0.082577767 | ... AD21: =IF(AD$2,LN(Trans!AD21),Trans!AD21) -> 0.012971941
A22: 1990Q4 | B22: =IF(B$2,LN(Trans!B22),Trans!B22) -> 16.011695 | C22: =IF(C$2,LN(Trans!C22),Trans!C22) -> 15.70528 | D22: =IF(D$2,LN(Trans!D22),Trans!D22) -> 14.081591 | E22: =IF(E$2,LN(Trans!E22),Trans!E22) -> 14.238013 | F22: =IF(F$2,LN(Trans!F22),Trans!F22) -> 14.444713 | G22: =IF(G$2,LN(Trans!G22),Trans!G22) -> 15.328049 | H22: =IF(H$2,LN(Trans!H22),Trans!H22) -> 14.028118 | I22: =IF(I$2,LN(Trans!I22),Trans!I22) -> 3.4010964 | ... Q22: =IF(Q$2,LN(Trans!Q22),Trans!Q22) -> 14.148116 | S22: =IF(S$2,LN(Trans!S22),Trans!S22) -> 0.019442633 | U22: =IF(U$2,LN(Trans!U22),Trans!U22) -> 4.3879528 | V22: =IF(V$2,LN(Trans!V22),Trans!V22) -> 5.02543 | W22: =IF(W$2,LN(Trans!W22),Trans!W22) -> 4.3504248 | X22: =IF(X$2,LN(Trans!X22),Trans!X22) -> 4.167721 | Y22: =IF(Y$2,LN(Trans!Y22),Trans!Y22) -> 4.1306198 | Z22: =IF(Z$2,LN(Trans!Z22),Trans!Z22) -> 3.7262003 | AA22: =IF(AA$2,LN(Trans!AA22),Trans!AA22) -> 3.8112455 | AB22: =IF(AB$2,LN(Trans!AB22),Trans!AB22) -> -0.085045265 | ... AD22: =IF(AD$2,LN(Trans!AD22),Trans!AD22) -> 0.011266969
A23: 1991Q1 | B23: =IF(B$2,LN(Trans!B23),Trans!B23) -> 16.039787 | C23: =IF(C$2,LN(Trans!C23),Trans!C23) -> 15.715254 | D23: =IF(D$2,LN(Trans!D23),Trans!D23) -> 14.252785 | E23: =IF(E$2,LN(Trans!E23),Trans!E23) -> 14.409801 | F23: =IF(F$2,LN(Trans!F23),Trans!F23) -> 14.56705 | G23: =IF(G$2,LN(Trans!G23),Trans!G23) -> 15.350284 | H23: =IF(H$2,LN(Trans!H23),Trans!H23) -> 14.017465 | I23: =IF(I$2,LN(Trans!I23),Trans!I23) -> 3.4264159 | ... Q23: =IF(Q$2,LN(Trans!Q23),Trans!Q23) -> 14.154066 | S23: =IF(S$2,LN(Trans!S23),Trans!S23) -> 0.01664592 | U23: =IF(U$2,LN(Trans!U23),Trans!U23) -> 4.3924427 | V23: =IF(V$2,LN(Trans!V23),Trans!V23) -> 4.9979712 | W23: =IF(W$2,LN(Trans!W23),Trans!W23) -> 4.3107051 | X23: =IF(X$2,LN(Trans!X23),Trans!X23) -> 4.2078636 | Y23: =IF(Y$2,LN(Trans!Y23),Trans!Y23) -> 4.1786816 | Z23: =IF(Z$2,LN(Trans!Z23),Trans!Z23) -> 3.7095077 | AA23: =IF(AA$2,LN(Trans!AA23),Trans!AA23) -> 3.7975878 | AB23: =IF(AB$2,LN(Trans!AB23),Trans!AB23) -> -0.088080174 | ... AD23: =IF(AD$2,LN(Trans!AD23),Trans!AD23) -> 0.013591157
A24: 1991Q2 | B24: =IF(B$2,LN(Trans!B24),Trans!B24) -> 16.074541 | C24: =IF(C$2,LN(Trans!C24),Trans!C24) -> 15.75121 | D24: =IF(D$2,LN(Trans!D24),Trans!D24) -> 14.260313 | E24: =IF(E$2,LN(Trans!E24),Trans!E24) -> 14.416999 | F24: =IF(F$2,LN(Trans!F24),Trans!F24) -> 14.588774 | G24: =IF(G$2,LN(Trans!G24),Trans!G24) -> 15.399266 | H24: =IF(H$2,LN(Trans!H24),Trans!H24) -> 14.027869 | I24: =IF(I$2,LN(Trans!I24),Trans!I24) -> 3.4820054 | ... Q24: =IF(Q$2,LN(Trans!Q24),Trans!Q24) -> 14.169921 | S24: =IF(S$2,LN(Trans!S24),Trans!S24) -> 0.014949802 | U24: =IF(U$2,LN(Trans!U24),Trans!U24) -> 4.4025885 | V24: =IF(V$2,LN(Trans!V24),Trans!V24) -> 4.9555724 | W24: =IF(W$2,LN(Trans!W24),Trans!W24) -> 4.3130368 | X24: =IF(X$2,LN(Trans!X24),Trans!X24) -> 4.1959216 | Y24: =IF(Y$2,LN(Trans!Y24),Trans!Y24) -> 4.1628796 | Z24: =IF(Z$2,LN(Trans!Z24),Trans!Z24) -> 3.7386073 | AA24: =IF(AA$2,LN(Trans!AA24),Trans!AA24) -> 3.8239619 | AB24: =IF(AB$2,LN(Trans!AB24),Trans!AB24) -> -0.085354634 | ... AD24: =IF(AD$2,LN(Trans!AD24),Trans!AD24) -> 0.015387958
A25: 1991Q3 | B25: =IF(B$2,LN(Trans!B25),Trans!B25) -> 16.08574 | C25: =IF(C$2,LN(Trans!C25),Trans!C25) -> 15.762213 | D25: =IF(D$2,LN(Trans!D25),Trans!D25) -> 14.197299 | E25: =IF(E$2,LN(Trans!E25),Trans!E25) -> 14.352571 | F25: =IF(F$2,LN(Trans!F25),Trans!F25) -> 14.596448 | G25: =IF(G$2,LN(Trans!G25),Trans!G25) -> 15.389722 | H25: =IF(H$2,LN(Trans!H25),Trans!H25) -> 14.051438 | I25: =IF(I$2,LN(Trans!I25),Trans!I25) -> 3.5276339 | ... Q25: =IF(Q$2,LN(Trans!Q25),Trans!Q25) -> 14.175347 | S25: =IF(S$2,LN(Trans!S25),Trans!S25) -> 0.014075391 | U25: =IF(U$2,LN(Trans!U25),Trans!U25) -> 4.406148 | V25: =IF(V$2,LN(Trans!V25),Trans!V25) -> 4.9611521 | W25: =IF(W$2,LN(Trans!W25),Trans!W25) -> 4.2722535 | X25: =IF(X$2,LN(Trans!X25),Trans!X25) -> 4.1917544 | Y25: =IF(Y$2,LN(Trans!Y25),Trans!Y25) -> 4.1701528 | Z25: =IF(Z$2,LN(Trans!Z25),Trans!Z25) -> 3.7153393 | AA25: =IF(AA$2,LN(Trans!AA25),Trans!AA25) -> 3.8067986 | AB25: =IF(AB$2,LN(Trans!AB25),Trans!AB25) -> -0.091459374 | ... AD25: =IF(AD$2,LN(Trans!AD25),Trans!AD25) -> 0.015300954
A26: 1991Q4 | B26: =IF(B$2,LN(Trans!B26),Trans!B26) -> 16.132007 | C26: =IF(C$2,LN(Trans!C26),Trans!C26) -> 15.800972 | D26: =IF(D$2,LN(Trans!D26),Trans!D26) -> 14.279931 | E26: =IF(E$2,LN(Trans!E26),Trans!E26) -> 14.435958 | F26: =IF(F$2,LN(Trans!F26),Trans!F26) -> 14.644802 | G26: =IF(G$2,LN(Trans!G26),Trans!G26) -> 15.438756 | H26: =IF(H$2,LN(Trans!H26),Trans!H26) -> 14.091006 | I26: =IF(I$2,LN(Trans!I26),Trans!I26) -> 3.5663613 | ... Q26: =IF(Q$2,LN(Trans!Q26),Trans!Q26) -> 14.193309 | S26: =IF(S$2,LN(Trans!S26),Trans!S26) -> 0.01226961 | U26: =IF(U$2,LN(Trans!U26),Trans!U26) -> 4.4100413 | V26: =IF(V$2,LN(Trans!V26),Trans!V26) -> 4.9789832 | W26: =IF(W$2,LN(Trans!W26),Trans!W26) -> 4.283317 | X26: =IF(X$2,LN(Trans!X26),Trans!X26) -> 4.2166092 | Y26: =IF(Y$2,LN(Trans!Y26),Trans!Y26) -> 4.1809339 | Z26: =IF(Z$2,LN(Trans!Z26),Trans!Z26) -> 3.7441193 | AA26: =IF(AA$2,LN(Trans!AA26),Trans!AA26) -> 3.8258673 | AB26: =IF(AB$2,LN(Trans!AB26),Trans!AB26) -> -0.08174801 | ... AD26: =IF(AD$2,LN(Trans!AD26),Trans!AD26) -> 0.017022933
